{"823":{"tagDescription":["Temiscouata politics (R.)"],"tagDate":["1904-11-08T00:00:00.000Z"],"tagName":["Gauvreau, Charles A."]},"17":{"tagDescription":["Post Office"],"tagDate":["1899-03-10T00:00:00.000Z"],"tagPerson":["F.S. Tourigny, F.S."],"tagName":["Leduc, J. H."]},"642":{"tagDescription":["Jaffrey, Robert"],"tagDate":["1903-10-16T00:00:00.000Z"],"tagName":["Boland, W. J."],"tagNotebook":["LAURIER PAPERS"]},"724":{"tagName":["Fitzpatrick, Charles"],"tagNotebook":["LAURIER PAPERS"],"tagDescription":["P.Q. Huntingdon Beauharnois Canals"],"tagDate":["1904-04-30T00:00:00.000Z"]},"635":{"tagName":["Curtis, Smith"],"tagNotebook":["LAURIER PAPERS"],"tagDescription":["1. British Columbia Elections 2. Mc Innes, W.W.B. 3. Martin, Joseph"],"tagDate":["1903-10-07T00:00:00.000Z"]},"299":{"tagName":["Perrault, J.E."],"tagDate":["1900-07-06T00:00:00.000Z"],"tagDescription":["Three Rivers and St. Maurice - Politics"]},"188":{"tagNotebook":["LAURIER PAPERS"],"tagName":["Davies, Louis H."],"tagDate":["1899-10-13T00:00:00.000Z"],"tagDescription":["Senate Chamberlain, Rt. Hon. Joseph"]},"759":{"tagName":["Pinault, L.F."],"tagDescription":["Quebec City"],"tagDate":["1904-07-16T00:00:00.000Z"]},"720":{"tagDate":["1904-04-28T00:00:00.000Z"],"tagDescription":["Finance Dept."],"tagNotebook":["LAURIER PAPERS"],"tagName":["Fitzpatrick, Charles"]},"543":{"tagDate":["1902-12-04T00:00:00.000Z"],"tagDescription":["Newspapers Union des Cantons de L'est"],"tagName":["Perrault, J.E."]},"712":{"tagDate":["1904-04-08T00:00:00.000Z"],"tagDescription":["Public Works Dept."],"tagNotebook":["LAURIER PAPERS"],"tagName":["Fitzpatrick, Charles"]},"667":{"tagName":["Sifton, Clifford Hon."],"tagDescription":["Manitoba Politics"],"tagDate":["1903-12-28T00:00:00.000Z"]},"570":{"tagName":["Sifton, Clifford Hon."],"tagDate":["1903-01-29T00:00:00.000Z"],"tagDescription":["British Columbia Fisheries"]},"53":{"tagName":["Sifton, Clifford Hon."],"tagDate":["1899-04-17T00:00:00.000Z"]},"278":{"tagName":["White, R. (Prop. Milton Reformer)"],"tagDescription":["Newspapers (Encl.)"],"tagDate":["1900-03-27T00:00:00.000Z"]},"802":{"tagNotebook":["LAURIER PAPERS"],"tagName":["Fitzpatrick, Charles"],"tagDate":["1904-09-23T00:00:00.000Z"]},"47":{"tagDescription":["Berthier Co."],"tagDate":["1899-04-05T00:00:00.000Z"],"tagName":["Ralston, A."]},"782":{"tagName":["Gauvreau, Charles A."],"tagDescription":["Election, Federal (R.)"],"tagDate":["1904-09-13T00:00:00.000Z"]},"639":{"tagDescription":["1. British Columbia Elections 2. Mc Innes, W.W.B. 3. Martin, Joseph (R. only)"],"tagDate":["1903-10-13T00:00:00.000Z"],"tagName":["Curtis, Smith"],"tagNotebook":["LAURIER PAPERS"]},"430":{"tagDate":["1901-06-10T00:00:00.000Z"],"tagDescription":["Military - War, South African - Borden, Hon. F.W. (Encl.)"],"tagNotebook":["LAURIER PAPERS"],"tagName":["Denison, George T."]},"28":{"tagDate":["1899-03-14T00:00:00.000Z"],"tagName":["LeBel, Chas. A."]},"755":{"tagName":["Marcil, Charles"],"tagDescription":["Railways- Atlantic & Lake Superior"],"tagDate":["1904-07-05T00:00:00.000Z"],"tagPerson":["Fitzpatrick, C. Hon."]},"271":{"tagName":["White, R. (Prop. Milton Reformer)"],"tagDate":["1900-03-17T00:00:00.000Z"],"tagDescription":["Newspapers ,patronage (R.)"]},"862":{"tagDate":["1905-01-07T00:00:00.000Z"],"tagDescription":["Lumber (R.)"],"tagName":["Lumbermen's Assn. of Ontario"]},"221":{"tagDate":["1899-12-01T00:00:00.000Z"],"tagDescription":["Railways, Intercolonial (Encl.)"],"tagName":["Gauvreau, Charles A."]},"524":{"tagName":["Lambly, W. H."],"tagDate":["1902-05-12T00:00:00.000Z"],"tagDescription":["Coronation (R.only)"]},"437":{"tagName":["Sifton, Clifford Hon."],"tagDescription":["North West Territories Judges"],"tagDate":["1901-07-16T00:00:00.000Z"]},"593":{"tagName":["Fitzpatrick, Charles"],"tagNotebook":["LAURIER PAPERS"],"tagDescription":["British Columbia, Judges (R.)"],"tagDate":["1903-03-05T00:00:00.000Z"]},"405":{"tagDescription":["Marine plants, Duty"],"tagPerson":["Gouvreau, Charles A."],"tagDate":["1901-03-30T00:00:00.000Z"],"tagName":["McCulure","Roy"]},"96":{"tagDate":["1899-06-12T00:00:00.000Z"],"tagDescription":["Freight rates (R.)"],"tagNotebook":["LAURIER PAPERS"],"tagName":["Falardeau, P.E."]},"392":{"tagDescription":["Ontario Bench"],"tagDate":["1901-02-17T00:00:00.000Z"],"tagName":["Garrow, J.T."]},"858":{"tagName":["Hamilton, W.H. Dr."],"tagDescription":["Fort William"],"tagDate":["1905-01-01T00:00:00.000Z"]},"42":{"tagDescription":["Maine and Fisheries Dept. "],"tagDate":["1899-03-25T00:00:00.000Z"],"tagName":["Dechene, F.G. Miville"],"tagNotebook":["LAURIER PAPERS"]},"465":{"tagName":["Gauvreau, Charles A."],"tagDescription":["Railways, Intercolonial"],"tagDate":["1901-10-14T00:00:00.000Z"]},"520":{"tagName":["Sifton, Clifford Hon."],"tagDescription":["St. Boniface College (Encl.)"],"tagDate":["1902-05-09T00:00:00.000Z"]},"228":{"tagDescription":["Imperial Relations Fort Erie (Encl.) (R.)"],"tagDate":["1899-12-09T00:00:00.000Z"],"tagName":["Denison, George T."],"tagNotebook":["LAURIER PAPERS"]},"582":{"tagName":["Fitzpatrick, Charles"],"tagNotebook":["LAURIER PAPERS"],"tagDescription":["Ottawa River (Encl.)"],"tagDate":["1903-02-11T00:00:00.000Z"]},"105":{"tagNotebook":["LAURIER PAPERS"],"tagName":["Charlebois, A."],"tagDate":["1899-07-08T00:00:00.000Z"],"tagDescription":["(R.)"]},"486":{"tagName":["Gauvreau, Antoine Rev."],"tagDate":["1902-01-10T00:00:00.000Z"],"tagDescription":["Quebec City"]},"383":{"tagDate":["1901-01-25T00:00:00.000Z"],"tagDescription":["Census (R. only)"],"tagName":["Gauvreau, Charles A."]},"664":{"tagDescription":["Interior Department"],"tagDate":["1903-12-19T00:00:00.000Z"],"tagName":["Sifton, Clifford Hon."]},"360":{"tagName":["Sifton, Clifford Hon."],"tagDescription":["Election, Federal (R. only)"],"tagDate":["1900-12-24T00:00:00.000Z"]},"770":{"tagName":["Falardeau, Cyrille"],"tagNotebook":["LAURIER PAPERS"],"tagDescription":["Railways Intercolonial (R.only)"],"tagDate":["1904-08-15T00:00:00.000Z"]},"73":{"tagDescription":["Northwest Territories (Encl.) (R.)"],"tagDate":["1899-05-11T00:00:00.000Z"],"tagName":["LeBel, Chas. A."]},"304":{"tagDate":["1900-08-08T00:00:00.000Z"],"tagName":["Blackstock, T.G."],"tagNotebook":["LAURIER PAPERS"]},"364":{"tagDescription":["(R. only)"],"tagDate":["1901-01-01T00:00:00.000Z"],"tagName":["Sifton, Clifford Hon."]},"774":{"tagDate":["1904-08-30T00:00:00.000Z"],"tagDescription":["Railways Quebec Central Intercolonial (Encl.) (R.)"],"tagNotebook":["LAURIER PAPERS"],"tagName":["Fitzpatrick, Charles"]},"683":{"tagName":["LeBel, Chas. A."],"tagDate":["1904-01-14T00:00:00.000Z"],"tagDescription":["Intercolonial Ry."]},"232":{"tagDate":["1900-01-04T00:00:00.000Z"],"tagName":["Sifton, Clifford Hon."]},"300":{"tagName":["Davies, Louis H."],"tagNotebook":["LAURIER PAPERS"],"tagDescription":["Marine and Fisheries Department"],"tagDate":["1900-07-06T00:00:00.000Z"]},"873":{"tagName":["United States Treasury Dept."],"tagDate":["1905-02-07T00:00:00.000Z"],"tagDescription":["U.S.Mint (Encl.)"]},"165":{"tagDate":["1899-09-20T00:00:00.000Z"],"tagDescription":["Boundaries, Alaska Chamberlain, Rt. Hon. Joseph"],"tagNotebook":["LAURIER PAPERS"],"tagName":["Davies, Louis H."]},"276":{"tagName":["Patterson, C.E.A."],"tagDescription":["Royal Canadian Mounted Police (R.)"],"tagDate":["1900-03-26T00:00:00.000Z"]},"12":{"tagDescription":["Marine & Fisheries Dept. (Encl.)"],"tagDate":["1899-03-07T00:00:00.000Z"],"tagName":["Fitzpatrick, Charles"],"tagNotebook":["LAURIER PAPERS"]},"555":{"tagDate":["1903-01-24T00:00:00.000Z"],"tagDescription":["Supreme Court (Encl.)"],"tagNotebook":["LAURIER PAPERS"],"tagName":["Fitzpatrick, Charles"]},"727":{"tagName":["Denison, George T."],"tagNotebook":["LAURIER PAPERS"],"tagDescription":["Imperial Preference Chamberlain, Rt. Hon. Joseph (R.)"],"tagDate":["1904-05-03T00:00:00.000Z"]},"617":{"tagName":["Jaffray, Robert"],"tagDescription":["Algoma Central Ry."],"tagDate":["1903-09-29T00:00:00.000Z"]},"433":{"tagDate":["1901-06-12T00:00:00.000Z"],"tagDescription":["Customs Dept."],"tagName":["White, R. S."]},"597":{"tagDescription":["Ontario Bench (R. only)"],"tagDate":["1903-03-09T00:00:00.000Z"],"tagName":["Dewart, E.H."],"tagNotebook":["LAURIER PAPERS"]},"762":{"tagNotebook":["LAURIER PAPERS"],"tagName":["Falardeau, Cyrille"],"tagDate":["1904-08-08T00:00:00.000Z"],"tagDescription":["Railways Intercolonial (R.)"]},"372":{"tagDate":["1901-01-05T00:00:00.000Z"],"tagDescription":["(Encl.) (R.)"],"tagName":["Gauvreau, Charles A."]},"573":{"tagNotebook":["LAURIER PAPERS"],"tagName":["Fitzpatrick, Charles"],"tagDate":["1903-02-10T00:00:00.000Z"],"tagDescription":["Post Office Presbyterian Church"]},"747":{"tagDescription":["Quebec Province Hospitals"],"tagDate":["1904-06-23T00:00:00.000Z"],"tagName":["Fitzpatrick, Charles"],"tagNotebook":["LAURIER PAPERS"]},"6":{"tagDate":["1899-03-04T00:00:00.000Z"],"tagDescription":["(R. only)"],"tagName":["Sifton, Clifford Hon."]},"317":{"tagName":["Sifton, Clifford Hon."],"tagDate":["1900-08-27T00:00:00.000Z"],"tagDescription":["Manitoba Lieut.-Governor"]},"702":{"tagName":["Fitzpatrick, Charles"],"tagNotebook":["LAURIER PAPERS"],"tagDescription":["Supreme Court (Encl.)"],"tagDate":["1904-03-29T00:00:00.000Z"]},"108":{"tagDate":["1899-07-20T00:00:00.000Z"],"tagDescription":["Newspapers (R.)"],"tagName":["White, R. (Prop. Milton Reformer)"]},"812":{"tagDescription":["Railways, Grand Trunk Pacific","Riviere Ouelle Pulp & Paper Co."],"tagDate":["1904-10-07T00:00:00.000Z"],"tagName":["Fitzpatrick, Charles"],"tagNotebook":["LAURIER PAPERS"]},"756":{"tagDescription":["Quebec City (Encl.)"],"tagDate":["1904-07-13T00:00:00.000Z"],"tagName":["Fitzpatrick, Charles"],"tagNotebook":["LAURIER PAPERS"]},"387":{"tagName":["Moffet, Flavien"],"tagDate":["1901-02-16T00:00:00.000Z"],"tagDescription":["Transportation; newspaper Le Temps (Encl.)"]},"859":{"tagName":["Ottawa Reform association"],"tagDescription":["Customs Department"],"tagDate":["1905-01-01T00:00:00.000Z"]},"133":{"tagName":["Davies, Louis H."],"tagNotebook":["LAURIER PAPERS"],"tagDescription":["Marine and Fisheries Department (R.)"],"tagDate":["1899-08-12T00:00:00.000Z"]},"820":{"tagDescription":["Arthabaska, Elections","Levis, P.Q., Elections"],"tagDate":["1904-10-14T00:00:00.000Z"],"tagName":["Fitzpatrick, Charles"],"tagNotebook":["LAURIER PAPERS"]},"687":{"tagDescription":["Railway Commission"],"tagDate":["1904-01-18T00:00:00.000Z"],"tagName":["Gauvreau, Charles A."]},"296":{"tagName":["Gauvreau, Charles A."],"tagDate":["1900-06-15T00:00:00.000Z"],"tagDescription":["Railways, Intercolonial"]},"540":{"tagDate":["1902-11-27T00:00:00.000Z"],"tagDescription":["Temiscouata -Affairs (Encl.)"],"tagName":["Gauvreau, Charles A."]},"794":{"tagDescription":["Queen's University","Riviere Ouelle Pulp & Paper Co."],"tagDate":["1904-09-20T00:00:00.000Z"],"tagName":["Fitzpatrick, Charles"],"tagNotebook":["LAURIER PAPERS"]},"168":{"tagName":["LeBel, Chas. A."],"tagDate":["1899-09-23T00:00:00.000Z"],"tagDescription":["Intercolonial Ry. (R.)"]},"723":{"tagNotebook":["LAURIER PAPERS"],"tagName":["Fitzpatrick, Charles"],"tagDate":["1904-04-29T00:00:00.000Z"],"tagDescription":["Credit Societies (R. only)"]},"827":{"tagName":["Power, A."],"tagDate":["1904-11-17T00:00:00.000Z"],"tagPerson":["Fitzpatrick, Charles Hon."],"tagDescription":["Marine and Fisheries Department"]},"119":{"tagNotebook":["LAURIER PAPERS"],"tagName":["Davies, Louis H."],"tagDate":["1899-07-27T00:00:00.000Z"],"tagDescription":["(R. only)"]},"773":{"tagNotebook":["LAURIER PAPERS"],"tagName":["Fitzpatrick, Charles"],"tagDate":["1904-08-19T00:00:00.000Z"],"tagDescription":["(R. only)"]},"380":{"tagName":["Lambly, W. H."],"tagDescription":["Prohibition Printing Bureau (R.)"],"tagDate":["1901-01-21T00:00:00.000Z"]},"466":{"tagName":["Gauvreau, Charles A."],"tagDate":["1901-10-18T00:00:00.000Z"],"tagDescription":["South Africa trade (Encl.)"]},"331":{"tagName":["Sifton, Clifford Hon."],"tagDescription":["Elections Federal"],"tagPerson":["Fitzpatrick, Charles Hon."],"tagDate":["1900-10-25T00:00:00.000Z"]},"797":{"tagName":["Fitzpatrick, Charles"],"tagNotebook":["LAURIER PAPERS"],"tagDescription":["Queen's University (R.)"],"tagDate":["1904-09-21T00:00:00.000Z"]},"19":{"tagDate":["1899-03-12T00:00:00.000Z"],"tagDescription":["Railways-Intercolonial Temiscouata-Politics (Encl.)"],"tagName":["Gauvreau, Charles A."]},"257":{"tagName":["Sifton, Clifford Hon."],"tagDescription":["Interior Department (R. only)"],"tagDate":["1900-02-22T00:00:00.000Z"]},"502":{"tagName":["Denison, George T."],"tagNotebook":["LAURIER PAPERS"],"tagDate":["1902-02-15T00:00:00.000Z"]},"185":{"tagNotebook":["LAURIER PAPERS"],"tagName":["Davies, Louis H."],"tagDate":["1899-10-13T00:00:00.000Z"],"tagDescription":["Boundaries, Alaska Salisbury, Lord"]},"338":{"tagDate":["1900-11-12T00:00:00.000Z"],"tagDescription":["Ontario elections United States - Relations with Lumber (R. only)"],"tagNotebook":["LAURIER PAPERS"],"tagName":["Bertram, John"]},"91":{"tagNotebook":["LAURIER PAPERS"],"tagName":["Denison, George T."],"tagDate":["1899-06-10T00:00:00.000Z"],"tagDescription":["Cable, Pacific"]},"406":{"tagDate":["1901-04-07T00:00:00.000Z"],"tagDescription":["Temiscouata, Affairs & politics (Encl.)"],"tagName":["Gauvreau, Charles A."]},"384":{"tagName":["Perrault, J.E."],"tagDate":["1901-01-26T00:00:00.000Z"],"tagDescription":["Anticosti"]},"680":{"tagName":["Perrault, J.E."],"tagDescription":["Post Office"],"tagDate":["1904-01-04T00:00:00.000Z"]},"663":{"tagDescription":["(R. only)"],"tagDate":["1903-12-17T00:00:00.000Z"],"tagName":["Patterson, C.E.A."]},"489":{"tagName":["Sifton, Clifford Hon."],"tagDescription":["Wales (Encl.)"],"tagDate":["1902-01-15T00:00:00.000Z"]},"556":{"tagDate":["1903-01-17T00:00:00.000Z"],"tagDescription":["(R. only)"],"tagName":["Gauvreau, Charles A."]},"275":{"tagDate":["1900-03-24T00:00:00.000Z"],"tagDescription":["Newspaper patronage"],"tagName":["Gobeil, A."]},"49":{"tagNotebook":["LAURIER PAPERS"],"tagName":["Davies, Louis H."],"tagDate":["1899-04-08T00:00:00.000Z"],"tagDescription":["Marine and Fisheries Department - Patronage"]},"744":{"tagNotebook":["LAURIER PAPERS"],"tagName":["Fitzpatrick, Charles"],"tagDate":["1904-06-20T00:00:00.000Z"],"tagDescription":["Pilots (R. only)"]},"452":{"tagName":["Davies, Louis H."],"tagNotebook":["LAURIER PAPERS"],"tagDescription":["Farquharson, Donald Prince Edward Isalnd (R.)"],"tagDate":["1901-09-20T00:00:00.000Z"]},"622":{"tagDescription":["Algoma Central Ry., Canadian Pacific Ry. (R.)"],"tagDate":["1903-09-24T00:00:00.000Z"],"tagName":["Jaffray, Robert"]},"590":{"tagDescription":["Rimouski, County Railways, Intercolonial"],"tagDate":["1903-02-23T00:00:00.000Z"],"tagName":["McWilliams, J. Sr. (Father Point)"]},"314":{"tagName":["Gooderham, M. R."],"tagDate":["1900-08-13T00:00:00.000Z"]},"751":{"tagName":["Fitzpatrick, Charles"],"tagNotebook":["LAURIER PAPERS"],"tagDescription":["Sir Thomas Shaugnessy French River"],"tagDate":["1904-07-01T00:00:00.000Z"]},"758":{"tagDate":["1904-07-15T00:00:00.000Z"],"tagName":["Fitzpatrick, Charles"],"tagNotebook":["LAURIER PAPERS"]},"614":{"tagName":["Sifton, Clifford Hon."],"tagDescription":["Interior Department"],"tagDate":["1903-08-22T00:00:00.000Z"]},"106":{"tagDate":["1899-07-17T00:00:00.000Z"],"tagDescription":["Tanning Industry (R. only)"],"tagNotebook":["LAURIER PAPERS"],"tagName":["Falardeau, P.E."]},"322":{"tagDate":["1900-09-19T00:00:00.000Z"],"tagDescription":["Cipher Code (R. only)"],"tagName":["Sifton, Clifford Hon."]},"445":{"tagDescription":["Cornwall and York, Duke of (R.)"],"tagDate":["1901-08-26T00:00:00.000Z"],"tagName":["Davies, Louis H."],"tagNotebook":["LAURIER PAPERS"]},"5":{"tagDate":["1899-03-04T00:00:00.000Z"],"tagDescription":["Quebec City Citadel"],"tagNotebook":["LAURIER PAPERS"],"tagName":["Fitzpatrick, Charles"]},"780":{"tagNotebook":["LAURIER PAPERS"],"tagName":["Fitzpatrick, Charles"],"tagDate":["1904-09-07T00:00:00.000Z"],"tagDescription":["Riviere Ouelle Pulp & Paper Co. (Encl.)"]},"800":{"tagName":["Gauvreau, Charles A."],"tagDate":["1904-09-21T00:00:00.000Z"],"tagDescription":["Railways, Transcontinental Elections, Federal (R. only)"]},"476":{"tagName":["Perrault, J.E."],"tagDescription":["Railways - Intercolonial (R.)"],"tagDate":["1901-11-23T00:00:00.000Z"]},"864":{"tagName":["Fitzpatrick, Charles"],"tagNotebook":["LAURIER PAPERS"],"tagDescription":["North West Territories (R.only)"],"tagDate":["1905-01-14T00:00:00.000Z"]},"397":{"tagName":["Davies, Louis H."],"tagNotebook":["LAURIER PAPERS"],"tagDescription":["Judges Salaries"],"tagDate":["1901-03-18T00:00:00.000Z"]},"286":{"tagName":["Gauvreau, Charles A."],"tagDescription":["Railways, Intercolonial"],"tagDate":["1900-06-02T00:00:00.000Z"]},"804":{"tagNotebook":["LAURIER PAPERS"],"tagName":["Fitzpatrick, Charles"],"tagDate":["1904-09-27T00:00:00.000Z"],"tagDescription":["(R. only)"]},"517":{"tagDescription":["Catholic Church (Encl.) (R.)"],"tagDate":["1902-05-05T00:00:00.000Z"],"tagName":["Gauvreau, Antoine Rev."]},"703":{"tagNotebook":["LAURIER PAPERS"],"tagName":["Cameron, E.R. (to Hon. C. Fitzpatrick)"],"tagDate":["1904-03-28T00:00:00.000Z"],"tagDescription":["Supreme Court"]},"121":{"tagNotebook":["LAURIER PAPERS"],"tagName":["Denison, George T."],"tagDate":["1899-08-02T00:00:00.000Z"],"tagDescription":["Naval Reserve (R.)"]},"784":{"tagName":["Fitzpatrick, Charles"],"tagNotebook":["LAURIER PAPERS"],"tagDescription":["Railways Quebec Central (Encl.)"],"tagDate":["1904-09-14T00:00:00.000Z"]},"673":{"tagDescription":["Railways, Intercolonial"],"tagDate":["1903-12-30T00:00:00.000Z"],"tagName":["Gauvreau, Charles A."]},"813":{"tagName":["Fitzpatrick, Charles"],"tagNotebook":["LAURIER PAPERS"],"tagDate":["1904-10-07T00:00:00.000Z"]},"640":{"tagDate":["1903-10-14T00:00:00.000Z"],"tagDescription":["Senate (R.)"],"tagNotebook":["LAURIER PAPERS"],"tagName":["Blain, Hugh"]},"145":{"tagNotebook":["LAURIER PAPERS"],"tagName":["Davies, Louis H."],"tagDate":["1899-08-22T00:00:00.000Z"],"tagDescription":["Boundaries, Alaska King, William Frederick (R.)"]},"351":{"tagName":["Gauvreau, Charles A."],"tagDescription":["Temiscouata elections"],"tagDate":["1900-12-08T00:00:00.000Z"]},"714":{"tagName":["Fitzpatrick, Charles"],"tagNotebook":["LAURIER PAPERS"],"tagDescription":["Le Chronicle, Quebec (R. only)"],"tagDate":["1904-04-18T00:00:00.000Z"]},"132":{"tagName":["LeBel, Chas. A."],"tagDate":["1899-08-08T00:00:00.000Z"]},"358":{"tagName":["Sifton, Clifford Hon."],"tagDescription":["British Columbia Commission on Chinese (R.)"],"tagDate":["1900-12-19T00:00:00.000Z"]},"651":{"tagName":["Sifton, Clifford Hon."],"tagDescription":["Railways, Canadian Pacific - Elections, Federal (R.)"]},"421":{"tagDescription":["Quebec, Plains of Abraham"],"tagDate":["1901-05-08T00:00:00.000Z"],"tagName":["Denison, George T."],"tagNotebook":["LAURIER PAPERS"]},"85":{"tagDate":["1899-05-23T00:00:00.000Z"],"tagDescription":["Redistribution (Encl.)"],"tagName":["Mills, David"]},"710":{"tagName":["Huycke, E.C.S."],"tagDescription":["Ontario bench"],"tagDate":["1904-04-05T00:00:00.000Z"],"tagPerson":["Fitzpatrick, C. Hon."]},"722":{"tagName":["Gauvreau, Charles A."],"tagDate":["1904-04-28T00:00:00.000Z"],"tagDescription":["Newspaper, Journal, (Fraserville) (R. only)"]},"340":{"tagDate":["1900-11-12T00:00:00.000Z"],"tagDescription":["Gaspe Fisheries"],"tagNotebook":["LAURIER PAPERS"],"tagName":["Davies, Louis H."]},"644":{"tagName":["Sifton, Clifford Hon."],"tagDate":["1903-10-17T00:00:00.000Z"],"tagDescription":["Railways Manitoba (R.)"]},"99":{"tagNotebook":["LAURIER PAPERS"],"tagName":["Blair, Andrew George Hon."],"tagDate":["1899-06-24T00:00:00.000Z"],"tagDescription":["Freight Rates"]},"602":{"tagDate":["1903-07-02T00:00:00.000Z"],"tagDescription":["Columbia River Improvement Co. (Encl.)"],"tagNotebook":["LAURIER PAPERS"],"tagName":["Fitzpatrick, Charles"]},"48":{"tagDescription":["Pilots"],"tagDate":["1899-04-07T00:00:00.000Z"],"tagName":["Davies, Louis H."],"tagNotebook":["LAURIER PAPERS"]},"647":{"tagName":["Gauvreau, Charles A."],"tagDescription":["Railways, Intercolonial"],"tagDate":["1903-10-20T00:00:00.000Z"]},"839":{"tagDate":["1904-12-08T00:00:00.000Z"],"tagDescription":["Elections, Federal"],"tagNotebook":["LAURIER PAPERS"],"tagName":["Fitzpatrick, Charles"]},"288":{"tagName":["Pope, Mrs. Anne (to: J.N. Gregory)"],"tagDescription":["Marine and Fisheries Department"],"tagDate":["1900-05-25T00:00:00.000Z"]},"563":{"tagDescription":["Judges, Salaries (R.)"],"tagDate":["1903-01-24T00:00:00.000Z"],"tagName":["Davies, Louis H."],"tagNotebook":["LAURIER PAPERS"]},"7":{"tagDescription":["Manitoba judges"],"tagDate":["1899-03-05T00:00:00.000Z"],"tagName":["Sifton, Clifford Hon."]},"471":{"tagName":["Sifton, Clifford Hon."],"tagDate":["1901-11-04T00:00:00.000Z"],"tagDescription":["Indian affairs (R. only)"]},"478":{"tagDescription":["Newspapers Union des Cantons de L'est"],"tagDate":["1901-12-02T00:00:00.000Z"],"tagName":["Perrault, J.E."]},"347":{"tagDescription":["Drummond - Arthabaska Politics (R.)"],"tagDate":["1900-11-29T00:00:00.000Z"],"tagName":["Perrault, J.E."]},"584":{"tagDescription":["1. British Columbia Judges 2. Justice Department (R.)"],"tagDate":["1903-02-21T00:00:00.000Z"],"tagName":["Bass, Oscar C."],"tagNotebook":["LAURIER PAPERS"]},"281":{"tagDate":["1900-04-11T00:00:00.000Z"],"tagDescription":["Ottawa, (R. only)"],"tagNotebook":["LAURIER PAPERS"],"tagName":["Davies, Louis H."]},"717":{"tagName":["Fitzpatrick, Charles"],"tagNotebook":["LAURIER PAPERS"],"tagDescription":["Railways Transcontinental (R. only)"],"tagDate":["1904-04-22T00:00:00.000Z"]},"302":{"tagName":["Gauvreau, Charles A."],"tagDescription":["Yukon, Liqour (R.)"],"tagDate":["1900-07-23T00:00:00.000Z"]},"171":{"tagName":["Davies, Louis H."],"tagNotebook":["LAURIER PAPERS"],"tagDescription":["War - South Africa"],"tagDate":["1899-10-12T00:00:00.000Z"]},"514":{"tagDate":["1902-04-24T00:00:00.000Z"],"tagDescription":["Customs Dept. (R. only)"],"tagName":["Gauvreau, Charles A."]},"211":{"tagName":["LeBel, Chas. A."],"tagDate":["1900-11-17T00:00:00.000Z"],"tagDescription":["Intercolonial Ry. (R.)"]},"807":{"tagDate":["1904-09-30T00:00:00.000Z"],"tagNotebook":["LAURIER PAPERS"],"tagName":["Fitzpatrick, Charles"]},"356":{"tagName":["Gauvreau, Charles A."],"tagDate":["1900-12-16T00:00:00.000Z"],"tagDescription":["Census (R.)"]},"835":{"tagName":["Sifton, Clifford Hon."],"tagDescription":["(R. only)"]},"842":{"tagDate":["1904-12-27T00:00:00.000Z"],"tagDescription":["Newspaper Union des Cantons de l'est Louis Lavergne (Encl.)"],"tagNotebook":["LAURIER PAPERS"],"tagName":["Fitzpatrick, Charles"]},"426":{"tagDescription":["Military (R. only)"],"tagDate":["1901-06-03T00:00:00.000Z"],"tagName":["Denison, George T."],"tagNotebook":["LAURIER PAPERS"]},"656":{"tagDate":["1903-11-18T00:00:00.000Z"],"tagDescription":["Provencher County, politics"],"tagName":["Sifton, Clifford Hon."]},"41":{"tagDescription":["Senate"],"tagDate":["1899-03-24T00:00:00.000Z"],"tagName":["Sifton, Clifford Hon."]},"522":{"tagNotebook":["LAURIER PAPERS"],"tagName":["Cyr, J. Ernest"],"tagDate":["1902-04-21T00:00:00.000Z"],"tagDescription":["St. Boniface College"]},"499":{"tagName":["Gauvreau, Antoine Rev."],"tagDate":["1902-02-05T00:00:00.000Z"],"tagDescription":["Quebec City"]},"867":{"tagName":["Lumbermen's Assn. of Ontario"],"tagDate":["1905-01-24T00:00:00.000Z"],"tagDescription":["Lumber (R.)"]},"394":{"tagName":["Gauvreau, Charles A."],"tagDate":["1901-03-08T00:00:00.000Z"]},"323":{"tagName":["Madore, J.A.C."],"tagDescription":["FitzGibbon & Company (R.)"],"tagDate":["1900-09-29T00:00:00.000Z"]},"822":{"tagNotebook":["LAURIER PAPERS"],"tagName":["Fitzpatrick, Charles"],"tagDate":["1904-10-28T00:00:00.000Z"],"tagDescription":["Elections, Federal"]},"491":{"tagName":["Gauvreau, Charles A."],"tagDescription":["Penitentiaries"],"tagDate":["1902-01-23T00:00:00.000Z"]},"157":{"tagName":["Davies, Louis H."],"tagNotebook":["LAURIER PAPERS"],"tagDescription":["Boundaries, Alaska King, William Frederick Prince Edward Island - Politics"],"tagDate":["1899-09-02T00:00:00.000Z"]},"810":{"tagDate":["1904-10-06T00:00:00.000Z"],"tagDescription":["Riviere Ouelle Pulp & Paper Co."],"tagNotebook":["LAURIER PAPERS"],"tagName":["Fitzpatrick, Charles"]},"97":{"tagName":["Sifton, Clifford Hon."],"tagDate":["1899-06-14T00:00:00.000Z"],"tagDescription":["Indian affairs"]},"643":{"tagDate":["1903-10-17T00:00:00.000Z"],"tagDescription":["Boundaries Alaska"],"tagName":["Sifton, Clifford Hon."]},"792":{"tagDate":["1904-09-19T00:00:00.000Z"],"tagDescription":["Railways, Transcontinental Elections, Federal"],"tagName":["Gauvreau, Charles A."]},"285":{"tagName":["Webster, George M. & Co. "],"tagPerson":["Anger, E.J. Hon."],"tagDate":["1900-05-23T00:00:00.000Z"],"tagDescription":["St. Lawrence River Steamships"]},"814":{"tagNotebook":["LAURIER PAPERS"],"tagName":["Fitzpatrick, Charles"],"tagDate":["1904-10-08T00:00:00.000Z"],"tagDescription":["Levis, P.Q.-Elections (R.)","Elections, General"]},"343":{"tagName":["Perrault, J.E."],"tagDate":["1900-11-24T00:00:00.000Z"],"tagDescription":["Drummond - Arthabaska politics (R.)"]},"507":{"tagName":["Lambly, W. H."],"tagDescription":["Railways Wolfe, Megantic &Lotbinière (R.)"],"tagDate":["1902-03-22T00:00:00.000Z"]},"219":{"tagNotebook":["LAURIER PAPERS"],"tagName":["Bourassa, J. Boutin"],"tagDate":["1899-11-28T00:00:00.000Z"],"tagDescription":["Levis, P.Q. (R. only)"]},"535":{"tagName":["Gauvreau, Charles A."],"tagDate":["1902-11-12T00:00:00.000Z"],"tagDescription":["Railways, Intercolonial"]},"713":{"tagDescription":["(R. only)"],"tagDate":["1904-04-16T00:00:00.000Z"],"tagName":["Fitzpatrick, Charles"],"tagNotebook":["LAURIER PAPERS"]},"627":{"tagDescription":["Algoma Central Ry., Canadian Pacific Ry. (R.)"],"tagDate":["1903-09-29T00:00:00.000Z"],"tagName":["Jaffray, Robert"]},"803":{"tagNotebook":["LAURIER PAPERS"],"tagName":["Fitzpatrick, Charles"],"tagDate":["1904-09-23T00:00:00.000Z"]},"457":{"tagName":["Sifton, Clifford Hon."],"tagDescription":["Indians Caughnawaga (R. only)"],"tagDate":["1901-10-05T00:00:00.000Z"]},"838":{"tagDate":["1904-12-07T00:00:00.000Z"],"tagDescription":["Manitoba Affairs & Politics"],"tagNotebook":["LAURIER PAPERS"],"tagName":["Fitzpatrick, Charles"]},"760":{"tagNotebook":["LAURIER PAPERS"],"tagName":["Fitzpatrick, Charles"],"tagDate":["1904-08-04T00:00:00.000Z"],"tagDescription":["Railways, Grand Trunk Pacific"]},"670":{"tagNotebook":["LAURIER PAPERS"],"tagName":["Denison, George T."],"tagDate":["1903-12-28T00:00:00.000Z"],"tagDescription":["Imperial Preference"]},"479":{"tagName":["Gauvreau, Charles A."],"tagDate":["1901-12-11T00:00:00.000Z"],"tagDescription":["Temiscouata - Affairs & Politics (R.)"]},"700":{"tagName":["Fitzpatrick, Charles"],"tagNotebook":["LAURIER PAPERS"],"tagDescription":["Le Soleil Ernest Pacaud"],"tagDate":["1904-03-18T00:00:00.000Z"]},"831":{"tagDescription":["Dr.A.Lessard (R.)"],"tagDate":["1904-11-21T00:00:00.000Z"],"tagName":["Fitzpatrick, Charles"],"tagNotebook":["LAURIER PAPERS"]},"63":{"tagDate":["1899-04-29T00:00:00.000Z"],"tagDescription":["Lumber"],"tagNotebook":["LAURIER PAPERS"],"tagName":["Burke, Stevenson"]},"539":{"tagName":["Sifton, Clifford Hon."],"tagDescription":["Alaska Boundary Commission"],"tagDate":["1902-11-17T00:00:00.000Z"]},"496":{"tagName":["Fitzpatrick, Charles"],"tagNotebook":["LAURIER PAPERS"],"tagDescription":["Duke of Cornwall & York (R. only)"],"tagDate":["1902-01-29T00:00:00.000Z"]},"612":{"tagName":["Gauvreau, Charles A."],"tagDate":["1903-08-21T00:00:00.000Z"],"tagDescription":["Railways, Intercolonial (R.)"]},"55":{"tagNotebook":["LAURIER PAPERS"],"tagDate":["1899-04-18T00:00:00.000Z"],"tagDescription":["Ontario Lumber Legislation"]},"592":{"tagNotebook":["LAURIER PAPERS"],"tagName":["Fitzpatrick, Charles"],"tagDate":["1903-02-26T00:00:00.000Z"],"tagDescription":["Alaska boundaries"]},"16":{"tagDate":["1899-03-10T00:00:00.000Z"],"tagDescription":["Marine and Fisheries Department"],"tagNotebook":["LAURIER PAPERS"],"tagName":["Davies, Louis H."]},"448":{"tagName":["Demers, L.J."],"tagNotebook":["LAURIER PAPERS"],"tagDescription":["Railways Intercolonial"],"tagDate":["1901-08-19T00:00:00.000Z"],"tagPerson":["Gauvreau, Charles A."]},"377":{"tagName":["Gauvreau, Charles A."],"tagDescription":["Quebec Legislative Council Railways,Intercolonial (R.)"],"tagDate":["1901-01-15T00:00:00.000Z"]},"620":{"tagPerson":["Gauvreau, Chas A."],"tagDate":["1903-09-24T00:00:00.000Z"],"tagDescription":["Railways Intercolonial"],"tagName":["Lapointe, Ernest"]},"450":{"tagDate":["1901-09-07T00:00:00.000Z"],"tagDescription":["Cornwall and York, Duke of"],"tagNotebook":["LAURIER PAPERS"],"tagName":["Davies, Louis H."]},"659":{"tagName":["Sifton, Clifford Hon."],"tagDate":["1903-12-15T00:00:00.000Z"],"tagDescription":["Boundaries - Alaska"]},"24":{"tagDate":["1899-03-13T00:00:00.000Z"],"tagDescription":["Marine and Fisheries Department (Encl.)"],"tagNotebook":["LAURIER PAPERS"],"tagName":["Davies, Louis H."]},"624":{"tagDescription":["Railways, Grand Trunk (R.)"],"tagDate":["1903-09-25T00:00:00.000Z"],"tagName":["Gauvreau, Charles A."]},"742":{"tagDescription":["Public Works Dept. (Encl.)"],"tagDate":["1904-06-04T00:00:00.000Z"],"tagName":["Fitzpatrick, Charles"],"tagNotebook":["LAURIER PAPERS"]},"693":{"tagDate":["1904-02-17T00:00:00.000Z"],"tagDescription":["Post Office (R.)"],"tagName":["Gauvreau, Charles A."]},"10":{"tagName":["Pottinger, David"],"tagDate":["1899-03-06T00:00:00.000Z"],"tagDescription":["Freight Rates"]},"312":{"tagName":["Sifton, Clifford Hon."],"tagDate":["1900-08-08T00:00:00.000Z"],"tagDescription":["Marine Plants Duty (R. only)"]},"677":{"tagName":["Wigle, E. S."],"tagDescription":["Windsor, Ont. Ferry"],"tagDate":["1904-01-01T00:00:00.000Z"],"tagPerson":["Grey, Earl"]},"583":{"tagDate":["1903-02-11T00:00:00.000Z"],"tagDescription":["Ottawa River"],"tagName":["Sutherland, James"]},"150":{"tagDescription":["Yukon (R.)"],"tagDate":["1899-08-25T00:00:00.000Z"],"tagName":["Sifton, Clifford Hon."]},"817":{"tagNotebook":["LAURIER PAPERS"],"tagName":["Fitzpatrick, Charles"],"tagDate":["1904-10-12T00:00:00.000Z"],"tagDescription":["Nicolet, P.Q., Elections Dorchester, P.Q. Elections (R.)"]},"46":{"tagDescription":["(R. only)"],"tagDate":["1899-04-03T00:00:00.000Z"],"tagName":["Sifton, Clifford Hon."]},"148":{"tagDate":["1899-08-23T00:00:00.000Z"],"tagDescription":["Yukon - Railways Ottawa & Gatineau Sutherland, James"],"tagName":["Sifton, Clifford Hon."]},"425":{"tagNotebook":["LAURIER PAPERS"],"tagName":["Davies, Louis H."],"tagDate":["1901-05-25T00:00:00.000Z"],"tagDescription":["Bristish Columbia Yukon"]},"196":{"tagDescription":["Temiscouata, Politics Railways, Intercolonial (Encl.)"],"tagDate":["1899-11-01T00:00:00.000Z"],"tagName":["Gauvreau, Charles A."]},"836":{"tagNotebook":["LAURIER PAPERS"],"tagName":["Fitzpatrick, Charles"],"tagDate":["1904-12-01T00:00:00.000Z"],"tagDescription":["Quebec City Citadel (Encl.)"]},"141":{"tagName":["Sifton, Clifford Hon."],"tagDescription":["Yukon (R. only)"],"tagDate":["1899-08-21T00:00:00.000Z"]},"739":{"tagDate":["1904-05-19T00:00:00.000Z"],"tagDescription":["Post Office"],"tagName":["Perreault, Gedeon"]},"233":{"tagName":["Gauvreau, Charles A."],"tagDate":["1900-01-13T00:00:00.000Z"],"tagDescription":["(R.)"]},"261":{"tagName":["Lumbermen's Assn. of Ontario"],"tagDescription":["Lumber"],"tagDate":["1900-02-24T00:00:00.000Z"]},"872":{"tagNotebook":["LAURIER PAPERS"],"tagName":["Fitzpatrick, Charles"],"tagDate":["1905-02-03T00:00:00.000Z"],"tagDescription":["Elections, Federal"]},"154":{"tagDate":["1899-08-25T00:00:00.000Z"],"tagDescription":["Railways Grand Trunk Tupper, Sir Charles"],"tagName":["Sifton, Clifford Hon."]},"799":{"tagDate":["1904-09-21T00:00:00.000Z"],"tagDescription":["(R. only)"],"tagNotebook":["LAURIER PAPERS"],"tagName":["Fitzpatrick, Charles"]},"117":{"tagDate":["1899-06-24T00:00:00.000Z"],"tagName":["LeBel, Chas. A."]},"71":{"tagDate":["1899-05-11T00:00:00.000Z"],"tagDescription":["(R. only)"],"tagNotebook":["LAURIER PAPERS"],"tagName":["Davies, Louis H."]},"487":{"tagName":["Jaffray, Robert"],"tagDescription":["B. C. politics (R.)"],"tagDate":["1902-01-11T00:00:00.000Z"]},"841":{"tagDate":["1904-12-09T00:00:00.000Z"],"tagDescription":["Elections, Federal"],"tagNotebook":["LAURIER PAPERS"],"tagName":["Fitzpatrick, Charles"]},"64":{"tagDate":["1899-05-05T00:00:00.000Z"],"tagDescription":["Cable, Pacific"],"tagName":["Jones, A. G."]},"220":{"tagName":["Tarte, J. I."],"tagDate":["1899-12-01T00:00:00.000Z"],"tagDescription":["Levis, P.Q."]},"136":{"tagName":["Gagnon, J.S."],"tagDescription":["Temiscouate, Politics"],"tagDate":["1899-08-17T00:00:00.000Z"]},"795":{"tagDescription":["Railway Intercolonial (Encl.)"],"tagDate":["1904-09-20T00:00:00.000Z"],"tagName":["Fitzpatrick, Charles"],"tagNotebook":["LAURIER PAPERS"]},"282":{"tagNotebook":["LAURIER PAPERS"],"tagName":["Davies, Louis H."],"tagDate":["1900-04-14T00:00:00.000Z"],"tagDescription":["Fisheries Inland"]},"608":{"tagDescription":["International Geological Congress"],"tagDate":["1903-07-04T00:00:00.000Z"],"tagName":["Sifton, Clifford Hon."]},"661":{"tagDate":["1903-12-17T00:00:00.000Z"],"tagDescription":["St. Boniface Schools (R.)"],"tagName":["Sifton, Clifford Hon."]},"86":{"tagDate":["1899-05-22T00:00:00.000Z"],"tagPerson":["Mills, David Hon."],"tagDescription":["Redistribution (Encl.)"],"tagName":["McWilliams, I.B."]},"301":{"tagName":["Sifton, Clifford Hon."],"tagDate":["1900-07-21T00:00:00.000Z"],"tagDescription":["(R. only)"]},"778":{"tagDescription":["Steel rails, duty (Encl.)"],"tagDate":["1904-09-06T00:00:00.000Z"],"tagName":["Fitzpatrick, Charles"],"tagNotebook":["LAURIER PAPERS"]},"361":{"tagName":["Gauvreau, Charles A."],"tagDescription":["Railways,Intercolonial (R.)"],"tagDate":["1900-12-26T00:00:00.000Z"]},"771":{"tagName":["Hyman, Charles S."],"tagPerson":["Fitzpatrick, Charles Hon."],"tagDate":["1904-08-15T00:00:00.000Z"],"tagDescription":["St. Vincent de Paul Penitentiary"]},"4":{"tagName":["Fitzpatrick, Charles"],"tagNotebook":["LAURIER PAPERS"],"tagDate":["1899-03-04T00:00:00.000Z"]},"668":{"tagName":["Perrault, J.E."],"tagDate":["1903-12-28T00:00:00.000Z"]},"80":{"tagNotebook":["LAURIER PAPERS"],"tagName":["Davies, Louis H."],"tagDate":["1899-05-13T00:00:00.000Z"],"tagDescription":["Marine and Fisheries Department (R. only.)"]},"545":{"tagDescription":["John S. Willison"],"tagDate":["1902-12-11T00:00:00.000Z"],"tagName":["Jaffray, Robert"]},"333":{"tagName":["Stone, E.B."],"tagDescription":["Federal elections"],"tagDate":["1900-11-01T00:00:00.000Z"]},"422":{"tagDescription":["Railways, Intercolonial"],"tagDate":["1901-05-23T00:00:00.000Z"],"tagName":["Gauvreau, Charles A."]},"652":{"tagName":["Gauvreau, Charles A."],"tagDescription":["Temiscouata politics Railways, Intercolonial (Encl.) (R.)"],"tagDate":["1903-11-07T00:00:00.000Z"]},"51":{"tagDescription":["Royal Canadian Mounted Police (R.)"],"tagDate":["1899-04-11T00:00:00.000Z"],"tagName":["Patterson, C.E.A."]},"526":{"tagDate":["1902-06-05T00:00:00.000Z"],"tagDescription":["Catholic Church Missions (R.)"],"tagName":["Gauvreau, Charles A."]},"385":{"tagName":["Lambly, W. H."],"tagDate":["1901-02-10T00:00:00.000Z"],"tagDescription":["Printing Bureau (Encl.)"]},"103":{"tagDescription":["Privy Council (R.)"],"tagDate":["1899-07-07T00:00:00.000Z"],"tagName":["Gauvreau, Charles A."]},"319":{"tagDate":["1900-09-13T00:00:00.000Z"],"tagDescription":["Railways, Intercolonial (R.)"],"tagName":["Gauvreau, Charles A."]},"180":{"tagDate":["1899-10-12T00:00:00.000Z"],"tagDescription":["Boundaries, Alaska Chamberlain, Rt. Hon. Joseph"],"tagNotebook":["LAURIER PAPERS"],"tagName":["Davies, Louis H."]},"875":{"tagName":["Fitzpatrick, Charles"],"tagNotebook":["LAURIER PAPERS"],"tagDescription":["Alexander Smith (R. only)"],"tagDate":["1905-02-08T00:00:00.000Z"]},"163":{"tagName":["Gauvreau, Charles A."],"tagDescription":["Temiscouata, Affairs & Politics (R. only)"],"tagDate":["1899-09-15T00:00:00.000Z"]},"749":{"tagDate":["1904-06-29T00:00:00.000Z"],"tagDescription":["St. Vincent de Paul Penitentiary (R. only)"],"tagNotebook":["LAURIER PAPERS"],"tagName":["Fitzpatrick, Charles"]},"243":{"tagDescription":["1. Nickel industry 2. Canadian copper company (Encl.)"],"tagDate":["1900-02-08T00:00:00.000Z"],"tagName":["Beatty, Blackstock, Nesbitt, Chadwick & Riddell"],"tagNotebook":["LAURIER PAPERS"]},"39":{"tagName":["Davies, Louis H."],"tagNotebook":["LAURIER PAPERS"],"tagDescription":["Fishing Licenses"],"tagDate":["1899-03-18T00:00:00.000Z"]},"484":{"tagName":["Gauvreau, Charles A."],"tagDescription":["Elections, Federal"],"tagDate":["1902-01-02T00:00:00.000Z"]},"857":{"tagName":["Taschereau, C.E."],"tagDescription":["Henry Morgan"],"tagPerson":["Fitzpatrick, Charles Hon."],"tagDate":["1904-12-31T00:00:00.000Z"]},"306":{"tagName":["Gauvreau, Charles A."],"tagDate":["1900-07-24T00:00:00.000Z"],"tagDescription":["Railways, Intercolonial (R.)"]},"438":{"tagName":["Sifton, Clifford Hon."],"tagDescription":["Montreal Light, Heat and Power Co. (R. only)"],"tagDate":["1901-07-17T00:00:00.000Z"]},"666":{"tagDescription":["Interior Department"],"tagDate":["1903-12-28T00:00:00.000Z"],"tagName":["Sifton, Clifford Hon."]},"879":{"tagName":["Fitzpatrick, Charles"],"tagNotebook":["LAURIER PAPERS"],"tagDescription":["Criminal Code (R.)"],"tagDate":["1905-03-04T00:00:00.000Z"]},"315":{"tagDate":["1900-08-16T00:00:00.000Z"],"tagDescription":["Fox Bay (Anticosti) (R.)"],"tagName":["Webster, George M. & Co."]},"227":{"tagNotebook":["LAURIER PAPERS"],"tagName":["Dandurand, R."],"tagDate":["1899-12-02T00:00:00.000Z"],"tagDescription":["Lebel, Charles A. (R.)"]},"571":{"tagDate":["1903-02-01T00:00:00.000Z"],"tagDescription":["Temiscouata politics"],"tagName":["Gauvreau, Charles A."]},"732":{"tagName":["Molson's Bank"],"tagDescription":["Hon. Charles Fitzpatrcik (R.only)"],"tagDate":["1904-05-09T00:00:00.000Z"]},"745":{"tagDate":["1904-06-21T00:00:00.000Z"],"tagDescription":["Customs Dept. (Encl.)"],"tagNotebook":["LAURIER PAPERS"],"tagName":["Fitzpatrick, Charles"]},"135":{"tagDate":["1899-08-12T00:00:00.000Z"],"tagDescription":["Interior Department (R. only)"],"tagName":["Sifton, Clifford Hon."]},"681":{"tagDescription":["Elections, Federal (R.)"],"tagDate":["1904-01-04T00:00:00.000Z"],"tagName":["Patterson, C.E.A."]},"107":{"tagDescription":["Tanning Industry"],"tagDate":["1899-07-18T00:00:00.000Z"],"tagName":["Falardeau, P.E."],"tagNotebook":["LAURIER PAPERS"]},"439":{"tagDate":["1901-07-21T00:00:00.000Z"],"tagName":["Davies, Louis H."],"tagNotebook":["LAURIER PAPERS"]},"334":{"tagDescription":["Prince Edward Island Elections (R.)"],"tagDate":["1900-11-08T00:00:00.000Z"],"tagName":["Davies, Hon. Benjamin"],"tagNotebook":["LAURIER PAPERS"]},"871":{"tagName":["Fitzpatrick, Charles"],"tagNotebook":["LAURIER PAPERS"],"tagDescription":["Railway, Transcontinental"],"tagDate":["1905-01-31T00:00:00.000Z"]},"262":{"tagName":["Beatty, Blackstock, Nesbitt, Chadwick & Riddell"],"tagNotebook":["LAURIER PAPERS"],"tagDescription":["1. Nickel industry 2. Canadian copper company (Encl.) (R.)"],"tagDate":["1900-03-13T00:00:00.000Z"]},"330":{"tagName":["Duchastel de Montrouge, L. (French Consul at Montreal)"],"tagNotebook":["LAURIER PAPERS"],"tagDescription":["(R. only)"],"tagDate":["1900-10-22T00:00:00.000Z"]},"557":{"tagName":["Gauvreau, Charles A."],"tagDate":["1903-01-17T00:00:00.000Z"],"tagDescription":["Public Works Dept. (R.)"]},"878":{"tagPerson":["Fitzpatrick, L. Hon."],"tagDate":["1905-02-02T00:00:00.000Z"],"tagDescription":["Allan Line"],"tagNotebook":["LAURIER PAPERS"],"tagName":["Allan, Andrew A."]},"167":{"tagName":["Cyr, J. Ernest"],"tagNotebook":["LAURIER PAPERS"],"tagDescription":["(R. only)"],"tagDate":["1899-09-22T00:00:00.000Z"]},"37":{"tagDescription":["Defence, Canada"],"tagDate":["1899-03-18T00:00:00.000Z"],"tagName":["Denison, George T."],"tagNotebook":["LAURIER PAPERS"]},"688":{"tagName":["Gauvreau, Charles A."],"tagDate":["1904-01-29T00:00:00.000Z"],"tagDescription":["Immigration Dept. (Encl.) (R.)"]},"618":{"tagDate":["1903-09-23T00:00:00.000Z"],"tagDescription":["British Columbia Courts (R.)"],"tagName":["New Westminster Board of Trade"]},"290":{"tagNotebook":["LAURIER PAPERS"],"tagName":["Bradley, B."],"tagPerson":["Gregory, J.N."],"tagDate":["1900-05-25T00:00:00.000Z"],"tagDescription":["Marine and Fisheries Department"]},"311":{"tagName":["Gauvreau, Charles A."],"tagDescription":["Marine plants, duty"],"tagDate":["1900-08-06T00:00:00.000Z"]},"754":{"tagNotebook":["LAURIER PAPERS"],"tagName":["Fitzpatrick, Charles"],"tagDate":["1904-07-06T00:00:00.000Z"],"tagDescription":["Railway, Atlantic & L. Superior (Encl.)"]},"598":{"tagName":["Sifton, Clifford Hon."],"tagDescription":["Treadgold Commission (Yukon) (R.)"],"tagDate":["1903-05-29T00:00:00.000Z"]},"435":{"tagName":["Gauvreau, Charles A."],"tagDescription":["Railways, Intercolonial"],"tagDate":["1901-07-09T00:00:00.000Z"]},"826":{"tagDescription":["William Templeman"],"tagDate":["1904-11-14T00:00:00.000Z"],"tagName":["Fitzpatrick, Charles"],"tagNotebook":["LAURIER PAPERS"]},"318":{"tagName":["Sifton, Clifford Hon."],"tagDescription":["Yukon - Mackenzie and Mann - Manitoba Lieut.-Governor"],"tagDate":["1900-08-30T00:00:00.000Z"]},"81":{"tagDescription":["Indian Affairs"],"tagDate":["1899-05-16T00:00:00.000Z"],"tagName":["Sifton, Clifford Hon."]},"750":{"tagDate":["1904-06-30T00:00:00.000Z"],"tagNotebook":["LAURIER PAPERS"],"tagName":["Fitzpatrick, Charles"]},"748":{"tagDescription":["Transatlantic service"],"tagDate":["1904-06-28T00:00:00.000Z"],"tagName":["Fitzpatrick, Charles"],"tagNotebook":["LAURIER PAPERS"]},"686":{"tagName":["LeBel, Chas. A."],"tagDate":["1904-01-16T00:00:00.000Z"],"tagDescription":["Intercolonial Ry."]},"50":{"tagNotebook":["LAURIER PAPERS"],"tagName":["Davies, Louis H."],"tagDate":["1899-04-11T00:00:00.000Z"],"tagDescription":["Fishing Licenses"]},"297":{"tagDescription":["Marine and Fisheries Department (R.)"],"tagDate":["1900-06-19T00:00:00.000Z"],"tagName":["Davies, Louis H."],"tagNotebook":["LAURIER PAPERS"]},"876":{"tagDate":["1905-02-10T00:00:00.000Z"],"tagDescription":["Railway Commision, Transcontinental"],"tagNotebook":["LAURIER PAPERS"],"tagName":["Fitzpatrick, Charles"]},"609":{"tagDescription":["Lead Industry British Columbia Mining & Smelting (R.)"],"tagDate":["1903-07-14T00:00:00.000Z"],"tagName":["Curtis, Smith"],"tagNotebook":["LAURIER PAPERS"]},"273":{"tagDescription":["Newspapers ,patronage (Encl.) (R.)"],"tagDate":["1900-03-23T00:00:00.000Z"],"tagName":["White, R. (Prop. Milton Reformer)"]},"779":{"tagPerson":["Fitzpatrick, C. Hon."],"tagDate":["1904-08-31T00:00:00.000Z"],"tagDescription":["Steel Rails, Dity"],"tagName":["Shields, C."]},"309":{"tagDate":["1900-07-31T00:00:00.000Z"],"tagDescription":["Railways, Intercolonial"],"tagName":["Gauvreau, Charles A."]},"483":{"tagName":["Sifton, Clifford Hon."],"tagDescription":["Immigration (R. only)"],"tagDate":["1901-12-27T00:00:00.000Z"]},"15":{"tagName":["LeBel, Chas. A."],"tagDate":["1899-03-07T00:00:00.000Z"]},"525":{"tagDate":["1902-05-16T00:00:00.000Z"],"tagDescription":["Ship Building"],"tagNotebook":["LAURIER PAPERS"],"tagName":["Bertram Engine Works"]},"746":{"tagDescription":["Customs Dept."],"tagDate":["1904-06-20T00:00:00.000Z"],"tagPerson":["Fitzpatrick, C. Hon."],"tagName":["Latulippe, J.A.G"]},"164":{"tagName":["Gobeil, A."],"tagDate":["1899-09-15T00:00:00.000Z"],"tagDescription":["Temiscouata, affairs & politics (R. only)"]},"100":{"tagNotebook":["LAURIER PAPERS"],"tagName":["Falardeau, P.E."],"tagDate":["1899-06-26T00:00:00.000Z"],"tagDescription":["Freight rates (R.)"]},"828":{"tagName":["Fitzpatrick, Charles"],"tagNotebook":["LAURIER PAPERS"],"tagDescription":["Church furnishings, Duty (Encl.)"],"tagDate":["1904-11-21T00:00:00.000Z"]},"365":{"tagName":["Gauvreau, Charles A."],"tagDescription":["Railways,Intercolonial (Encl.)"],"tagDate":["1901-01-02T00:00:00.000Z"]},"775":{"tagDate":["1904-08-30T00:00:00.000Z"],"tagDescription":["Quebec Central & Intercolonial Railways"],"tagNotebook":["LAURIER PAPERS"],"tagName":["Emmerson, H.R. (from Hon.C. Fitzpatrick)"]},"541":{"tagDate":["1902-11-14T00:00:00.000Z"],"tagName":["Dionne J. Napoleon "],"tagNotebook":["LAURIER PAPERS"]},"32":{"tagName":["Prefontaine, Raymond Hon."],"tagDate":["1899-03-14T00:00:00.000Z"]},"665":{"tagName":["Sifton, Clifford Hon."],"tagDescription":["New Brunswick elections"],"tagDate":["1903-12-24T00:00:00.000Z"]},"492":{"tagName":["Lavoie, J. E."],"tagDate":["1902-01-27T00:00:00.000Z"],"tagDescription":["(R. only)"]},"616":{"tagDescription":["Temiscouata - Affairs (R.)"],"tagDate":["1903-09-09T00:00:00.000Z"],"tagName":["Gauvreau, Charles A."]},"548":{"tagDate":["1902-12-17T00:00:00.000Z"],"tagDescription":["Politics, Canadian, Federal Caroll, Henry George"],"tagName":["Gauvreau, Charles A."]},"821":{"tagDescription":["(R. only)"],"tagDate":["1904-10-14T00:00:00.000Z"],"tagName":["Fitzpatrick, Charles"],"tagNotebook":["LAURIER PAPERS"]},"62":{"tagDate":["1899-04-20T00:00:00.000Z"],"tagDescription":["Indian Schools (R. only)"],"tagName":["Sifton, Clifford Hon."]},"305":{"tagName":["Sifton, Clifford Hon."],"tagDescription":["(R. only)"],"tagDate":["1900-07-24T00:00:00.000Z"]},"240":{"tagName":["Fitzpatrick, Charles"],"tagNotebook":["LAURIER PAPERS"],"tagDescription":["Wire Duty (Encl.)"],"tagDate":["1900-01-29T00:00:00.000Z"]},"160":{"tagName":["Sifton, Clifford Hon."],"tagDate":["1899-09-09T00:00:00.000Z"],"tagDescription":["Railways, Canadian Pacific"]},"258":{"tagName":["Sifton, Clifford Hon."],"tagDate":["1900-02-24T00:00:00.000Z"],"tagDescription":["Indian affairs (Encl.)"]},"529":{"tagName":["Sifton, Clifford Hon."],"tagDescription":["(R. only)"],"tagDate":["1902-06-06T00:00:00.000Z"]},"337":{"tagName":["Sifton, Clifford Hon."],"tagDate":["1900-11-10T00:00:00.000Z"],"tagDescription":["Yale-Cariboo Co."]},"550":{"tagDate":["1902-12-30T00:00:00.000Z"],"tagDescription":["Alaska Boundary (R.)"],"tagName":["Sifton, Clifford Hon."]},"657":{"tagDescription":["Imperial Trade (R.)"],"tagDate":["1903-12-12T00:00:00.000Z"],"tagName":["New Westminster Board of Trade"]},"427":{"tagDescription":["Railways, Intercolonial (R.)"],"tagDate":["1901-06-08T00:00:00.000Z"],"tagName":["Gauvreau, Charles A."]},"143":{"tagName":["Sifton, Clifford Hon."],"tagDescription":["Yukon (R. only)"],"tagDate":["1899-08-21T00:00:00.000Z"]},"866":{"tagName":["Fitzpatrick, Charles"],"tagNotebook":["LAURIER PAPERS"],"tagDescription":["Allan line"],"tagDate":["1905-01-18T00:00:00.000Z"]},"379":{"tagName":["Perrault, J.E."],"tagDescription":["Anticosti"],"tagDate":["1901-01-19T00:00:00.000Z"]},"769":{"tagDescription":["Newspaper, Daily Telegraph (Quebec)"],"tagDate":["1904-08-11T00:00:00.000Z"],"tagPerson":["Fitzpatrick, Charles Hon."],"tagName":["Sifton, Clifford Hon."]},"280":{"tagDescription":["Newspapers"],"tagDate":["1900-03-31T00:00:00.000Z"],"tagName":["Mills, David"]},"203":{"tagDescription":["Fort Erie (Encl.)"],"tagDate":["1899-11-03T00:00:00.000Z"],"tagName":["Denison, George T."],"tagNotebook":["LAURIER PAPERS"]},"709":{"tagName":["Fitzpatrick, Charles"],"tagNotebook":["LAURIER PAPERS"],"tagDescription":["Ontario Bench (Encl.)"],"tagDate":["1904-04-07T00:00:00.000Z"]},"43":{"tagName":["McKenna, J.A.J.","Sifton, Clifford Hon."],"tagDescription":["Hon. Richard Cartwright Joint High Commission (Encl.)"],"tagPerson":["Sifton, Clifford Hon."],"tagDate":["1899-03-27T00:00:00.000Z"]},"470":{"tagDate":["1901-10-26T00:00:00.000Z"],"tagDescription":["Cornwall & York, Duke of (R. only)"],"tagName":["Sifton, Clifford Hon."]},"806":{"tagName":["Fitzpatrick, Charles"],"tagNotebook":["LAURIER PAPERS"],"tagDescription":["Quebec, Judges"],"tagDate":["1904-09-29T00:00:00.000Z"]},"679":{"tagDate":["1904-01-01T00:00:00.000Z"],"tagDescription":["Imperial Preference"],"tagNotebook":["LAURIER PAPERS"],"tagName":["Denison, George T."]},"530":{"tagDescription":["Supreme Court"],"tagDate":["1902-06-07T00:00:00.000Z"],"tagName":["Davies, Louis H."],"tagNotebook":["LAURIER PAPERS"]},"89":{"tagPerson":["Gauvreau, Charles A."],"tagDate":["1899-05-30T00:00:00.000Z"],"tagDescription":["Quebec-Colonization (Encl.)"],"tagNotebook":["LAURIER PAPERS"],"tagName":["Fournier, F.M. Rev."]},"511":{"tagDate":["1902-04-17T00:00:00.000Z"],"tagDescription":["(R.)"],"tagName":["Gauvreau, Charles A."]},"214":{"tagDate":["1899-11-24T00:00:00.000Z"],"tagDescription":["Railways, Intercolonial Public Works Dept. (Encl.) (R.)"],"tagName":["Gauvreau, Charles A."]},"398":{"tagName":["Perrault, J.E."],"tagDate":["1901-03-21T00:00:00.000Z"]},"716":{"tagNotebook":["LAURIER PAPERS"],"tagName":["Fitzpatrick, Charles"],"tagDate":["1904-04-20T00:00:00.000Z"],"tagDescription":["H.A.P. Holland (R. only)"]},"819":{"tagDate":["1904-10-13T00:00:00.000Z"],"tagDescription":["Dorchester, P.Q.- Elections (R. only)"],"tagNotebook":["LAURIER PAPERS"],"tagName":["Fitzpatrick, Charles"]},"443":{"tagDescription":["(R. only)"],"tagDate":["1901-08-19T00:00:00.000Z"],"tagName":["Sifton, Clifford Hon."]},"72":{"tagName":["Sifton, Clifford Hon."],"tagDate":["1899-05-11T00:00:00.000Z"],"tagDescription":["Pelletier, Hon. C.A.P."]},"705":{"tagName":["Royal Canadian Academy (Reid, G.A. et al.)"],"tagDate":["1904-04-01T00:00:00.000Z"],"tagDescription":["Royal Canadian Academy Parliament Buildings"]},"646":{"tagDate":["1903-10-17T00:00:00.000Z"],"tagDescription":["Robert Jaffray"],"tagName":["Rowell, N. W."]},"698":{"tagDate":["1904-03-10T00:00:00.000Z"],"tagDescription":["Supreme Court"],"tagNotebook":["LAURIER PAPERS"],"tagName":["Fitzpatrick, Charles"]},"120":{"tagName":["Gauvreau, Charles A."],"tagDate":["1899-07-28T00:00:00.000Z"],"tagDescription":["Isle Verte"]},"788":{"tagDescription":["Newspapers, La Presse federal elections"],"tagPerson":["Fitzpatrick, Charles Hon."],"tagDate":["1904-09-15T00:00:00.000Z"],"tagName":["Cote, Thos"],"tagNotebook":["LAURIER PAPERS"]},"833":{"tagName":["Fitzpatrick, Charles"],"tagNotebook":["LAURIER PAPERS"],"tagDescription":["Railways, Transcontinental"],"tagDate":["1904-11-21T00:00:00.000Z"]},"236":{"tagName":["LeBel, Chas. A."],"tagDescription":["(R.)"],"tagDate":["1900-01-18T00:00:00.000Z"]},"734":{"tagDate":["1904-05-10T00:00:00.000Z"],"tagDescription":["Railways, Intercolonial (R.)"],"tagNotebook":["LAURIER PAPERS"],"tagName":["Emmerson, H.R. (to C. Fitzpatrick)"]},"808":{"tagName":["Fitzpatrick, Charles"],"tagNotebook":["LAURIER PAPERS"],"tagDescription":["Sir Thomas Shaughnessy"],"tagDate":["1904-10-01T00:00:00.000Z"]},"60":{"tagDescription":["Lumber - Mickel (R. only)"],"tagDate":["1899-04-18T00:00:00.000Z"],"tagName":["Burke, Stevenson"],"tagNotebook":["LAURIER PAPERS"]},"730":{"tagName":["Fitzpatrick, Charles"],"tagNotebook":["LAURIER PAPERS"],"tagDescription":["(R.)"],"tagDate":["1904-05-04T00:00:00.000Z"]},"801":{"tagDate":["1904-09-22T00:00:00.000Z"],"tagDescription":["(R. only)"],"tagName":["Gauvreau, Charles A."]},"325":{"tagDate":["1900-09-29T00:00:00.000Z"],"tagName":["Gauvreau, Charles A."]},"482":{"tagName":["Gauvreau, Charles A."],"tagDescription":["Temiscouata - Affairs & Politics (R.)"],"tagDate":["1901-12-16T00:00:00.000Z"]},"177":{"tagDate":["1899-10-12T00:00:00.000Z"],"tagDescription":["War - South Africa Chamberlain, Rt. Hon. Joseph"],"tagNotebook":["LAURIER PAPERS"],"tagName":["Davies, Louis H."]},"36":{"tagNotebook":["LAURIER PAPERS"],"tagName":["Falardeau, P.E."],"tagDate":["1899-03-17T00:00:00.000Z"],"tagDescription":["Tanbark- Freight rates Railways-Intercolonial (Encl.)"]},"509":{"tagName":["Gauvreau, Antoine Rev."],"tagDate":["1902-04-01T00:00:00.000Z"],"tagDescription":["Customs Dept. (R.)"]},"124":{"tagName":["Girard, L. N"],"tagDate":["1899-08-07T00:00:00.000Z"],"tagDescription":["Isle Verte (Encl.)"]},"516":{"tagName":["Sifton, Clifford Hon."],"tagDate":["1902-04-23T00:00:00.000Z"]},"648":{"tagDescription":["Temiscouata elections"],"tagDate":["1903-10-22T00:00:00.000Z"],"tagName":["Gauvreau, Charles A."]},"287":{"tagName":["Gregory, J.U."],"tagDescription":["Marine & Fisheries Dept. (Encl.)"],"tagPerson":["Davies, L.H. Hon."],"tagDate":["1900-06-06T00:00:00.000Z"]},"696":{"tagDescription":["British Empire League (R.)"],"tagDate":["1904-03-09T00:00:00.000Z"],"tagName":["Denison, George T."],"tagNotebook":["LAURIER PAPERS"]},"412":{"tagName":["Belcourt, N.A."],"tagNotebook":["LAURIER PAPERS"],"tagDescription":["1. Ottawa Reform Association 2. Ottawa, (Encl.) (R.)"],"tagDate":["1901-04-08T00:00:00.000Z"]},"155":{"tagDate":["1899-08-29T00:00:00.000Z"],"tagDescription":["Boundaries, Alaska King, William Frederick (R. only)"],"tagName":["Sifton, Clifford Hon."]},"650":{"tagDate":["1903-10-26T00:00:00.000Z"],"tagDescription":["Robert Jaffray (R.only)"],"tagName":["Ryan, Peter"]},"420":{"tagName":["Sifton, Clifford Hon."],"tagDate":["1901-05-06T00:00:00.000Z"],"tagDescription":["General inspection act"]},"711":{"tagName":["Mackay, Robert"],"tagDescription":["Cotton industry"],"tagDate":["1904-04-07T00:00:00.000Z"]},"459":{"tagDate":["1901-10-08T00:00:00.000Z"],"tagDescription":["Railways, Intercolonial (R.)"],"tagName":["Gauvreau, Charles A."]},"493":{"tagName":["Gauvreau, Charles A."],"tagDate":["1902-01-29T00:00:00.000Z"],"tagDescription":["Temiscouata - Affairs & Politics (R.)"]},"718":{"tagDate":["1904-04-27T00:00:00.000Z"],"tagDescription":["Marriage legislation (R.)"],"tagNotebook":["LAURIER PAPERS"],"tagName":["Fitzpatrick, Charles"]},"537":{"tagDate":["1902-11-14T00:00:00.000Z"],"tagDescription":["C. Devlin (R.)"],"tagName":["Sifton, Clifford Hon."]},"350":{"tagName":["Perrault, J.E."],"tagDate":["1900-12-03T00:00:00.000Z"],"tagDescription":["Drummond - Arthabaska Politics "]},"505":{"tagDate":["1902-02-19T00:00:00.000Z"],"tagDescription":["Ontario Bench (R.)"],"tagName":["Whitney, J. P."]},"396":{"tagDate":["1901-03-12T00:00:00.000Z"],"tagDescription":["(R. only)"],"tagName":["Sifton, Clifford Hon."]},"440":{"tagDate":["1901-08-07T00:00:00.000Z"],"tagDescription":["Railways, Intercolonial (Encl.) (R.)"],"tagName":["Gauvreau, Charles A."]},"649":{"tagName":["Cox, George A."],"tagNotebook":["LAURIER PAPERS"],"tagDescription":["Robert Jaffray"],"tagDate":["1903-10-22T00:00:00.000Z"]},"292":{"tagNotebook":["LAURIER PAPERS"],"tagName":["Cyr, J. Ernest"],"tagDate":["1900-06-10T00:00:00.000Z"],"tagDescription":["Public Works Dept. (R.)"]},"785":{"tagDate":["1904-09-14T00:00:00.000Z"],"tagDescription":["Quebec Central Railways"],"tagNotebook":["LAURIER PAPERS"],"tagName":["Emmerson, H.R. (from C. Fitzpatrick)"]},"805":{"tagDate":["1904-09-29T00:00:00.000Z"],"tagDescription":["Elections, Federal"],"tagNotebook":["LAURIER PAPERS"],"tagName":["Fitzpatrick, Charles"]},"54":{"tagName":["Harris, Robert"],"tagDescription":["Royal Canadian Academy of Arts Exhibition Paris"],"tagDate":["1899-04-18T00:00:00.000Z"]},"628":{"tagName":["Sifton, Clifford Hon."],"tagDate":["1903-10-08T00:00:00.000Z"],"tagDescription":["Boundaries - Alaska"]},"458":{"tagName":["Sifton, Clifford Hon."],"tagDate":["1901-10-07T00:00:00.000Z"],"tagDescription":["Penitentiaries (R. only)"]},"213":{"tagDescription":["Levis, P.Q. (R. only)"],"tagDate":["1899-11-21T00:00:00.000Z"],"tagName":["Bourassa, J. Boutin"],"tagNotebook":["LAURIER PAPERS"]},"451":{"tagDescription":["(R. only)"],"tagDate":["1901-09-16T00:00:00.000Z"],"tagName":["Davies, Louis H."],"tagNotebook":["LAURIER PAPERS"]},"82":{"tagDate":["1899-05-18T00:00:00.000Z"],"tagDescription":["Temiscouata, Affairs & Politics (R.)"],"tagName":["Gauvreau, Charles A."]},"816":{"tagDate":["1904-10-10T00:00:00.000Z"],"tagDescription":["Portneuf Co., Elections"],"tagNotebook":["LAURIER PAPERS"],"tagName":["Fitzpatrick, Charles"]},"865":{"tagDate":["1905-01-16T00:00:00.000Z"],"tagDescription":["North West Territories"],"tagNotebook":["LAURIER PAPERS"],"tagName":["Fitzpatrick, Charles"]},"752":{"tagNotebook":["LAURIER PAPERS"],"tagName":["Fitzpatrick, Charles"],"tagDate":["1904-07-02T00:00:00.000Z"],"tagDescription":["Public Works Dept. (R.)"]},"444":{"tagDate":["1901-08-20T00:00:00.000Z"],"tagName":["Sifton, Clifford Hon."]},"283":{"tagDate":["1900-04-21T00:00:00.000Z"],"tagDescription":["Lumber (R. only)"],"tagName":["Lumbermen's Assn. of Ontario"]},"260":{"tagDescription":["Indian affairs"],"tagPerson":["Sifton, Clifford Hon."],"tagDate":["1900-02-23T00:00:00.000Z"],"tagName":["Fielding, W.S."],"tagNotebook":["LAURIER PAPERS"]},"204":{"tagName":["Bull, Canon G. "],"tagNotebook":["LAURIER PAPERS"],"tagDescription":["Fort Erie (Encl.)"],"tagPerson":["Denison, G.T. Col."],"tagDate":["1899-11-02T00:00:00.000Z"]},"632":{"tagDescription":["Robert Jaffray"],"tagDate":["1903-10-07T00:00:00.000Z"],"tagName":["Ryan, Peter"]},"568":{"tagName":["Davies, Louis H."],"tagNotebook":["LAURIER PAPERS"],"tagDescription":["Judges, Salaries"],"tagDate":["1903-01-28T00:00:00.000Z"]},"140":{"tagNotebook":["LAURIER PAPERS"],"tagName":["Davies, Louis H."],"tagDate":["1899-08-18T00:00:00.000Z"],"tagDescription":["Marine and Fisheries Department"]},"809":{"tagDescription":["Temiscouata politics (R. only)"],"tagDate":["1904-10-03T00:00:00.000Z"],"tagName":["Gauvreau, Charles A."]},"676":{"tagDate":["1903-12-31T00:00:00.000Z"],"tagDescription":["Interior Department (R. only)"],"tagName":["Sifton, Clifford Hon."]},"869":{"tagName":["Lumbermen's Assn. of Ontario"],"tagDate":["1905-01-28T00:00:00.000Z"],"tagDescription":["Lumber (R.)"]},"497":{"tagName":["Davies, Louis H."],"tagNotebook":["LAURIER PAPERS"],"tagDescription":["British Columbia Judges"],"tagDate":["1902-01-30T00:00:00.000Z"]},"766":{"tagDate":["1904-08-08T00:00:00.000Z"],"tagDescription":["(R.)"],"tagNotebook":["LAURIER PAPERS"],"tagName":["Fitzpatrick, Charles"]},"144":{"tagName":["Gauvreau, Charles A."],"tagDescription":["Public Works Dept. (R. only)"],"tagDate":["1899-08-21T00:00:00.000Z"]},"533":{"tagDescription":["Devlin, C. Colonial Conference (R. only)"],"tagDate":["1902-07-25T00:00:00.000Z"],"tagName":["Sifton, Clifford Hon."]},"715":{"tagDescription":["Railways Transcontinental"],"tagDate":["1904-04-20T00:00:00.000Z"],"tagName":["Fitzpatrick, Charles"],"tagNotebook":["LAURIER PAPERS"]},"561":{"tagName":["Cameron, E.R. (to Hon. C. Fitzpatrick)"],"tagNotebook":["LAURIER PAPERS"],"tagDescription":["Supreme Court (Encl.)"],"tagDate":["1903-01-22T00:00:00.000Z"]},"473":{"tagDescription":["Railways, Intercolonial (R.)"],"tagDate":["1901-11-15T00:00:00.000Z"],"tagName":["Gauvreau, Charles A."]},"423":{"tagName":["Gauvreau, Charles A."],"tagDescription":["Temiscouata - Affairs"],"tagDate":["1901-05-23T00:00:00.000Z"]},"399":{"tagName":["Gauvreau, Charles A."],"tagDescription":["Railways, Intercolonial (Encl.)"],"tagDate":["1901-03-26T00:00:00.000Z"]},"102":{"tagName":["Gauvreau, Charles A."],"tagDescription":["North West Territories"],"tagDate":["1899-06-29T00:00:00.000Z"]},"326":{"tagName":["White, R. (Prop. Milton Reformer)"],"tagDescription":["Newspaper,patronage (R.)"],"tagDate":["1900-10-08T00:00:00.000Z"]},"811":{"tagDate":["1904-10-07T00:00:00.000Z"],"tagDescription":["Elections, Federal"],"tagNotebook":["LAURIER PAPERS"],"tagName":["Fitzpatrick, Charles"]},"207":{"tagDate":["1899-11-16T00:00:00.000Z"],"tagDescription":["Public Works Dept. Railways, Intercolonial (R.)"],"tagName":["Gauvreau, Charles A."]},"552":{"tagDate":["1903-01-13T00:00:00.000Z"],"tagDescription":["Supreme Court Exchequer Court (Encl.)"],"tagNotebook":["LAURIER PAPERS"],"tagName":["Fitzpatrick, Charles"]},"456":{"tagName":["Jaffray, Robert"],"tagDescription":["Toronto University "],"tagDate":["1901-09-22T00:00:00.000Z"]},"353":{"tagDescription":["Railways,Intercolonial Temiscouata,Elections (R.)"],"tagDate":["1900-12-10T00:00:00.000Z"],"tagName":["Gauvreau, Charles A."]},"235":{"tagNotebook":["LAURIER PAPERS"],"tagName":["Davies, Louis H."],"tagDate":["1900-01-16T00:00:00.000Z"],"tagDescription":["Ontario Elections"]},"699":{"tagDate":["1904-03-14T00:00:00.000Z"],"tagDescription":["Church furnishings, Duty"],"tagNotebook":["LAURIER PAPERS"],"tagName":["Fitzpatrick, Charles"]},"506":{"tagDescription":["Ontario Bench (R. only)"],"tagDate":["1902-02-20T00:00:00.000Z"],"tagName":["Garrow, J.T."]},"881":{"tagNotebook":["LAURIER PAPERS"],"tagName":["Fitzpatrick, Charles"],"tagDate":["1905-03-06T00:00:00.000Z"],"tagDescription":["Ontario Bench (Encl.)"]},"87":{"tagName":["Davies, Louis H."],"tagNotebook":["LAURIER PAPERS"],"tagDescription":["Marine and Fisheries Department"],"tagDate":["1899-05-23T00:00:00.000Z"]},"447":{"tagDate":["1901-08-29T00:00:00.000Z"],"tagPerson":["Gauvreau, Chas. A."],"tagDescription":["Intercoinial Ry. (Encl.)"],"tagName":["Martineau, P.R."]},"701":{"tagName":["Fitzpatrick, Charles"],"tagNotebook":["LAURIER PAPERS"],"tagDescription":["Railways, Transcontinental"],"tagDate":["1904-03-29T00:00:00.000Z"]},"768":{"tagNotebook":["LAURIER PAPERS"],"tagName":["Dubé, W.A."],"tagDate":["1904-08-10T00:00:00.000Z"],"tagDescription":["Intercolonial Railway (R. only)"]},"371":{"tagName":["Gauvreau, Charles A."],"tagDescription":["Railways,Intercolonial"],"tagDate":["1901-01-02T00:00:00.000Z"]},"761":{"tagDate":["1904-08-05T00:00:00.000Z"],"tagDescription":["Post Office"],"tagNotebook":["LAURIER PAPERS"],"tagName":["Fitzpatrick, Charles"]},"190":{"tagName":["Davies, Louis H."],"tagNotebook":["LAURIER PAPERS"],"tagDescription":["Senate Transatlantic service Boundaries, Alaska Chamberlain, Rt. Hon. Joseph"],"tagDate":["1899-10-20T00:00:00.000Z"]},"834":{"tagDescription":["Allan Steamship Line"],"tagDate":["1904-11-22T00:00:00.000Z"],"tagName":["Fitzpatrick, Charles"],"tagNotebook":["LAURIER PAPERS"]},"462":{"tagNotebook":["LAURIER PAPERS"],"tagName":["Dalton, Morgan et al."],"tagDate":["1901-10-14T00:00:00.000Z"],"tagDescription":["Ontario Beach (R.)"]},"156":{"tagName":["Sifton, Clifford Hon."],"tagDescription":["Yukon (R. only)"],"tagDate":["1899-08-29T00:00:00.000Z"]},"695":{"tagName":["Fitzpatrick, Charles"],"tagNotebook":["LAURIER PAPERS"],"tagDescription":["Post Office"],"tagDate":["1904-03-06T00:00:00.000Z"]},"733":{"tagDescription":["Railways - Intercolonial (Encl.) (R.)"],"tagDate":["1904-05-12T00:00:00.000Z"],"tagName":["Fitzpatrick, Charles"],"tagNotebook":["LAURIER PAPERS"]},"239":{"tagNotebook":["LAURIER PAPERS"],"tagName":["Davies, Louis H."],"tagDate":["1900-01-22T00:00:00.000Z"],"tagDescription":["Harbour Commissions (R. only)"]}}