{"1194":{"tagNotebook":["LEADER OF THE OPPOSITION SUBJECT FILES - 1940 TO 1943. VOLS. 12 TO 85."],"tagDescription":["24. B 200 No. 2 Budget"]},"794":{"tagNotebook":["LEADER OF THE OPPOSITION SUBJECT FILES - 1940 TO 1943. VOLS. 12 TO 85."],"tagDescription":["20. B 120 Beauharnois"]},"915":{"tagNotebook":["LEADER OF THE OPPOSITION SUBJECT FILES - 1940 TO 1943. VOLS. 12 TO 85."],"tagDescription":["22. B 200 Budget and Succession Duties"]},"172":{"tagNotebook":["LEADER OF THE OPPOSITION SUBJECT FILES - 1940 TO 1943. VOLS. 12 TO 85."],"tagDescription":["18. A 400 No. 1 Anonymous"]},"903":{"tagNotebook":["LEADER OF THE OPPOSITION SUBJECT FILES - 1940 TO 1943. VOLS. 12 TO 85."],"tagDescription":["21. B 150 Biographical Material"]},"80":{"tagDescription":["17. A 156 Wheat - Processing Levy"],"tagNotebook":["LEADER OF THE OPPOSITION SUBJECT FILES - 1940 TO 1943. VOLS. 12 TO 85."]},"1312":{"tagNotebook":["LEADER OF THE OPPOSITION SUBJECT FILES - 1940 TO 1943. VOLS. 12 TO 85."],"tagDescription":["25. B 200 No. 3 Budget - to 22 July 1942."]},"531":{"tagNotebook":["LEADER OF THE OPPOSITION SUBJECT FILES - 1940 TO 1943. VOLS. 12 TO 85."],"tagDescription":["19. A 400 No. 2 Anonymous"]},"1003":{"tagNotebook":["LEADER OF THE OPPOSITION SUBJECT FILES - 1940 TO 1943. VOLS. 12 TO 85."],"tagDescription":["23. B 200 No. 1 Budget"]}}