{
  "259": {
    "tagNotebook": ["LAURIER PAPERS"],
    "tagName": ["Camirand, J. O."],
    "tagDate": ["1904-08-30T00:00:00.000Z"],
    "tagDescription": ["Invitation (R.)"]
  },
  "841": {
    "tagNotebook": ["LAURIER PAPERS"],
    "tagName": ["Eckardt, H. P."],
    "tagDate": ["1904-09-21T00:00:00.000Z"],
    "tagDescription": ["Senatorship (R.)"]
  },
  "528": {
    "tagName": ["Lamb, W. D."],
    "tagDate": ["1904-09-12T00:00:00.000Z"],
    "tagDescription": ["Land problems"]
  },
  "854": {
    "tagDescription": ["Murphy, appointment (R.)"],
    "tagDate": ["1904-09-21T00:00:00.000Z"],
    "tagName": ["Hughes, J.J."]
  },
  "172": {
    "tagNotebook": ["LAURIER PAPERS"],
    "tagName": ["Bryce, James"],
    "tagDate": ["1904-08-22T00:00:00.000Z"],
    "tagDescription": ["Visit to U.S. and Canada"]
  },
  "850": {
    "tagName": ["Minto, Lord"],
    "tagDate": ["1904-09-21T00:00:00.000Z"],
    "tagDescription": ["Saskatoon"]
  },
  "277": {
    "tagName": ["Mullarkey, J. P."],
    "tagDate": ["1904-08-31T00:00:00.000Z"],
    "tagDescription": ["Chateauguay & Northern Ry."]
  },
  "34": {
    "tagDescription": ["Appointment"],
    "tagDate": ["1904-08-15T00:00:00.000Z"],
    "tagName": ["Fisher, Sydney A."],
    "tagNotebook": ["LAURIER PAPERS"]
  },
  "1045": {
    "tagDescription": ["Offers assistance in election (R.)"],
    "tagDate": ["1904-09-28T00:00:00.000Z"],
    "tagName": ["Allison, J.W."],
    "tagNotebook": ["LAURIER PAPERS"]
  },
  "187": {
    "tagDate": ["1904-08-23T00:00:00.000Z"],
    "tagDescription": ["Richelieu Politics (R.)"],
    "tagNotebook": ["LAURIER PAPERS"],
    "tagName": ["Bruneau, A.A."]
  },
  "361": {
    "tagDescription": ["Appointment (R.)"],
    "tagDate": ["1904-09-06T00:00:00.000Z"],
    "tagName": ["Lapointe, Ernest"]
  },
  "951": {
    "tagDate": ["1904-09-26T00:00:00.000Z"],
    "tagDescription": ["Ontario politics (R.)"],
    "tagName": ["Lewis, John"]
  },
  "436": {
    "tagNotebook": ["LAURIER PAPERS"],
    "tagName": ["Baynes, G.A."],
    "tagDate": ["1904-09-09T00:00:00.000Z"],
    "tagDescription": ["(R.) (Encl.)"]
  },
  "771": {
    "tagName": ["Limieux, Rodolphe"],
    "tagDate": ["1904-09-20T00:00:00.000Z"],
    "tagDescription": ["Lease of island"]
  },
  "308": {
    "tagDescription": ["Federal election (R.)"],
    "tagDate": ["1904-09-03T00:00:00.000Z"],
    "tagName": ["Hughes, J.J."]
  },
  "1018": {
    "tagName": ["Walsh, J. M. (North West Mounted Police)"],
    "tagDate": ["1904-09-27T00:00:00.000Z"],
    "tagDescription": ["Election campaign (R.)"]
  },
  "601": {
    "tagName": ["Ridington, J."],
    "tagDescription": ["Political situation Winnipeg (R.)"],
    "tagDate": ["1904-09-14T00:00:00.000Z"]
  },
  "608": {
    "tagDescription": ["Senatorship"],
    "tagDate": ["1904-09-14T00:00:00.000Z"],
    "tagName": ["Brown, J.W"],
    "tagNotebook": ["LAURIER PAPERS"]
  },
  "301": {
    "tagDate": ["1904-09-04T00:00:00.000Z"],
    "tagDescription": ["Invitation (R.)"],
    "tagNotebook": ["LAURIER PAPERS"],
    "tagName": ["Cooke, R. S."]
  },
  "958": {
    "tagName": ["Torrance, John"],
    "tagDescription": ["S. S. Victorian Allan (Steamship) Line (R.)"],
    "tagDate": ["1904-09-26T00:00:00.000Z"]
  },
  "825": {
    "tagDate": ["1904-09-20T00:00:00.000Z"],
    "tagDescription": ["Patronage (Encl.) (R.)"],
    "tagName": ["Mulock, Wm."]
  },
  "282": {
    "tagName": ["Thompson, F. W."],
    "tagDescription": ["Steamship line to S. Africa (R. only)"],
    "tagDate": ["1904-09-01T00:00:00.000Z"]
  },
  "749": {
    "tagDate": ["1904-09-19T00:00:00.000Z"],
    "tagDescription": ["Interview"],
    "tagName": ["Germany, Consul General (Bopp, F.)"]
  },
  "1041": {
    "tagDate": ["1904-09-27T00:00:00.000Z"],
    "tagName": ["Malern, Lewis"]
  },
  "685": {
    "tagDate": ["1904-09-17T00:00:00.000Z"],
    "tagDescription": ["Federation election - Ontario (R.)"],
    "tagNotebook": ["LAURIER PAPERS"],
    "tagName": ["Barwick, Walter"]
  },
  "319": {
    "tagName": ["Gauthier, C. H. Rt. Rev."],
    "tagDate": ["1904-09-04T00:00:00.000Z"],
    "tagDescription": ["Appointment (R.)"]
  },
  "947": {
    "tagDate": ["1904-09-26T00:00:00.000Z"],
    "tagName": ["Copeland, G. A. (Boston Advertiser)"],
    "tagNotebook": ["LAURIER PAPERS"]
  },
  "1001": {
    "tagName": ["Campbell, J. E."],
    "tagNotebook": ["LAURIER PAPERS"],
    "tagDescription": ["Dominion election-North Bruce (R.)"],
    "tagDate": ["1904-09-26T00:00:00.000Z"]
  },
  "138": {
    "tagName": ["Ouellette, Octave"],
    "tagDate": ["1904-08-19T00:00:00.000Z"],
    "tagDescription": ["(R. only)"]
  },
  "274": {
    "tagDescription": ["Earl Grey", "Appointment"],
    "tagDate": ["1904-08-30T00:00:00.000Z"],
    "tagName": ["Scott, R.W."]
  },
  "571": {
    "tagDescription": ["Deputy-Ministership, Public Works (R.)"],
    "tagDate": ["1904-09-13T00:00:00.000Z"],
    "tagName": ["Geoffrion, Victor"]
  },
  "689": {
    "tagName": ["Heyd, Chas. B."],
    "tagDescription": ["Election campaign - Ontario (R.)"],
    "tagDate": ["1904-09-17T00:00:00.000Z"]
  },
  "732": {
    "tagDate": ["1904-09-18T00:00:00.000Z"],
    "tagDescription": ["Election campaign Montcalm (R.)"],
    "tagNotebook": ["LAURIER PAPERS"],
    "tagName": ["Dugas, F.O."]
  },
  "956": {
    "tagDate": ["1904-09-26T00:00:00.000Z"],
    "tagDescription": ["Yonge St. Bridge"],
    "tagName": ["Mulock, Wm."]
  },
  "315": {
    "tagDate": ["1904-09-03T00:00:00.000Z"],
    "tagDescription": ["General election, Windsor (R.)"],
    "tagNotebook": ["LAURIER PAPERS"],
    "tagName": ["Casgrain, L. C. A."]
  },
  "306": {
    "tagDate": ["1904-09-02T00:00:00.000Z"],
    "tagNotebook": ["LAURIER PAPERS"],
    "tagName": ["Emmerson, H.R."]
  },
  "923": {
    "tagName": ["Murray, Thos."],
    "tagDescription": ["Pontiac & Pacific Ry. Co. (Encls.) (R.)"],
    "tagDate": ["1904-09-24T00:00:00.000Z"]
  },
  "23": {
    "tagName": ["Stewart, D.A."],
    "tagDate": ["1904-08-15T00:00:00.000Z"],
    "tagDescription": ["N.W.M.P on American border - U.S. boundary (R.)"]
  },
  "110": {
    "tagDate": ["1904-08-18T00:00:00.000Z"],
    "tagDescription": ["Vancouver - New Zealand steamship line (R.)"],
    "tagNotebook": ["LAURIER PAPERS"],
    "tagName": ["Alley, R.A."]
  },
  "994": {
    "tagName": ["Prefontaine, Raymond Hon."],
    "tagDescription": ["Nicolet Co. politics (Encl.)"],
    "tagDate": ["1904-09-26T00:00:00.000Z"]
  },
  "688": {
    "tagDescription": ["Election campaign literature"],
    "tagDate": ["1904-09-17T00:00:00.000Z"],
    "tagName": ["Smith, Alex"]
  },
  "247": {
    "tagDate": ["1904-08-29T00:00:00.000Z"],
    "tagDescription": ["Liberal candidate, Kins&Albert, N.B. politics (R.)"],
    "tagNotebook": ["LAURIER PAPERS"],
    "tagName": ["Emmerson, H.R."]
  },
  "895": {
    "tagNotebook": ["LAURIER PAPERS"],
    "tagName": ["Brown, G.B. Rev."],
    "tagDate": ["1904-09-23T00:00:00.000Z"],
    "tagDescription": ["Election campaign (R.)"]
  },
  "634": {
    "tagDate": ["1904-09-15T00:00:00.000Z"],
    "tagDescription": ["General election"],
    "tagName": ["Hall, R.R."]
  },
  "107": {
    "tagDate": ["1904-08-18T00:00:00.000Z"],
    "tagDescription": ["N.W.M. Police"],
    "tagName": ["Perry, A.B."]
  },
  "630": {
    "tagDescription": ["Invitation: reception for J.E.Redmond,M.P. (R.)"],
    "tagDate": ["1904-09-15T00:00:00.000Z"],
    "tagName": ["Guerin, J. M."]
  },
  "334": {
    "tagDescription": ["Chateauguay & Northern Ry."],
    "tagDate": ["1904-09-05T00:00:00.000Z"],
    "tagName": ["Mullarkey, J. P."]
  },
  "70": {
    "tagNotebook": ["LAURIER PAPERS"],
    "tagName": ["Begy, George, A."],
    "tagDate": ["1904-08-17T00:00:00.000Z"],
    "tagDescription": ["Railway Construction Commission appt. (Encl.) (R.)"]
  },
  "142": {
    "tagDescription": ["Duty on lumber (R.)"],
    "tagDate": ["1904-08-19T00:00:00.000Z"],
    "tagName": ["Carter, W. W."],
    "tagNotebook": ["LAURIER PAPERS"]
  },
  "88": {
    "tagName": ["Mickle, Dyment & Son"],
    "tagDescription": ["Duty on wood imports"],
    "tagDate": ["1904-08-18T00:00:00.000Z"]
  },
  "467": {
    "tagName": ["Griffith, W. L."],
    "tagDate": ["1904-09-10T00:00:00.000Z"],
    "tagDescription": ["Free Food League (R.)"]
  },
  "899": {
    "tagDate": ["1904-09-24T00:00:00.000Z"],
    "tagDescription": ["Solicitor: Grand Trunk Pacific Commission (R.)"],
    "tagName": ["Lawlor, H. W."]
  },
  "796": {
    "tagNotebook": ["LAURIER PAPERS"],
    "tagName": ["Fraser, O.K."],
    "tagDate": ["1904-09-20T00:00:00.000Z"],
    "tagDescription": ["Murphy, appointment"]
  },
  "318": {
    "tagName": ["Lewis, John"],
    "tagDate": ["1904-09-04T00:00:00.000Z"]
  },
  "1035": {
    "tagDate": ["1904-09-27T00:00:00.000Z"],
    "tagNotebook": ["LAURIER PAPERS"],
    "tagName": ["Costigan, Hon. J."]
  },
  "591": {
    "tagName": ["McNee, Achibald"],
    "tagDate": ["1904-09-14T00:00:00.000Z"],
    "tagDescription": ["General election: - Essex Co. (R.)"]
  },
  "750": {
    "tagName": ["Allan, Andrew A."],
    "tagNotebook": ["LAURIER PAPERS"],
    "tagDescription": [
      "Extension of mail contact; Allan Steamship line (Encl.)"
    ],
    "tagDate": ["1904-09-19T00:00:00.000Z"]
  },
  "618": {
    "tagDate": ["1904-09-15T00:00:00.000Z"],
    "tagDescription": ["Portrait of the King (R.)"],
    "tagNotebook": ["LAURIER PAPERS"],
    "tagName": ["Forbes, J. C."]
  },
  "311": {
    "tagName": ["Allan, Hugh Montagu"],
    "tagNotebook": ["LAURIER PAPERS"],
    "tagDescription": ["Thanks for K.C.M.G."],
    "tagDate": ["1904-09-03T00:00:00.000Z"]
  },
  "575": {
    "tagDate": ["1904-09-13T00:00:00.000Z"],
    "tagDescription": ["Senatorship (R.)"],
    "tagPlace": ["North Bay"],
    "tagName": ["McKenzie, Wm."]
  },
  "741": {
    "tagDate": ["1904-09-19T00:00:00.000Z"],
    "tagDescription": ["John Lewis and the globe (R. only)"],
    "tagName": ["Macdonald, J.A. Rev."]
  },
  "139": {
    "tagDate": ["1904-08-19T00:00:00.000Z"],
    "tagDescription": ["Lt.-Governorship of Quebec (R.)"],
    "tagName": ["Macpherson, R.G."]
  },
  "386": {
    "tagDate": ["1904-09-07T00:00:00.000Z"],
    "tagDescription": ["Irish Catholic voters"],
    "tagNotebook": ["LAURIER PAPERS"],
    "tagName": ["Fitzpatrick, Charles"]
  },
  "15": {
    "tagName": ["Desmarais, Jules"],
    "tagNotebook": ["LAURIER PAPERS"],
    "tagDescription": ["Professional porspects (R.)"],
    "tagDate": ["1904-08-15T00:00:00.000Z"]
  },
  "977": {
    "tagName": ["Demers, L.J."],
    "tagNotebook": ["LAURIER PAPERS"],
    "tagDescription": ["Electoral lists "],
    "tagDate": ["1904-09-26T00:00:00.000Z"]
  },
  "1020": {
    "tagName": ["Graham, G.P."],
    "tagDate": ["1904-09-27T00:00:00.000Z"],
    "tagDescription": ["Election campaign (R.)"]
  },
  "993": {
    "tagDescription": ["Inquiries re. government finance etc. (R. only)"],
    "tagDate": ["1904-09-26T00:00:00.000Z"],
    "tagName": ["Duncan, Hon. J."],
    "tagNotebook": ["LAURIER PAPERS"]
  },
  "400": {
    "tagDate": ["1904-09-08T00:00:00.000Z"],
    "tagDescription": ["Appointment (Encls.)"],
    "tagNotebook": ["LAURIER PAPERS"],
    "tagName": ["Farrell, Edward Dr."]
  },
  "876": {
    "tagName": ["Pitt, Alex."],
    "tagDescription": ["Party division in Pontiac (R. only)"],
    "tagDate": ["1904-09-22T00:00:00.000Z"]
  },
  "113": {
    "tagDescription": ["Grand Trunk Pacific Railway (R.)"],
    "tagDate": ["1904-08-18T00:00:00.000Z"],
    "tagName": ["Borron, E.B."],
    "tagNotebook": ["LAURIER PAPERS"]
  },
  "369": {
    "tagNotebook": ["LAURIER PAPERS"],
    "tagName": ["Fitzpatrick, Charles"],
    "tagDate": ["1904-09-06T00:00:00.000Z"],
    "tagDescription": ["Sheds on wharf Montreal Harbour (Encl.)"]
  },
  "779": {
    "tagDate": ["1904-09-19T00:00:00.000Z"],
    "tagDescription": ["Interview (R.)"],
    "tagNotebook": ["LAURIER PAPERS"],
    "tagName": ["Canadian Steamship Line"]
  },
  "464": {
    "tagDescription": ["Application for timber limits (R.)"],
    "tagDate": ["1904-09-10T00:00:00.000Z"],
    "tagName": ["Prince, Antonio"]
  },
  "920": {
    "tagName": ["Macpherson, R.G."],
    "tagDate": ["1904-09-24T00:00:00.000Z"],
    "tagDescription": ["B.C. judgeship (R.)"]
  },
  "845": {
    "tagName": ["Cantin, Fred"],
    "tagNotebook": ["LAURIER PAPERS"],
    "tagDescription": ["Federal election"],
    "tagDate": ["1904-09-21T00:00:00.000Z"]
  },
  "297": {
    "tagNotebook": ["LAURIER PAPERS"],
    "tagName": ["Emmerson, H.R."],
    "tagDate": ["1904-09-01T00:00:00.000Z"],
    "tagDescription": ["Levis, P.O (R. only)"]
  },
  "160": {
    "tagDate": ["1904-08-22T00:00:00.000Z"],
    "tagDescription": ["Routine business"],
    "tagName": ["Japan, Consul-General of"]
  },
  "183": {
    "tagNotebook": ["LAURIER PAPERS"],
    "tagName": ["Brisbane Chamber of Commerce"],
    "tagDate": ["1904-08-23T00:00:00.000Z"],
    "tagDescription": ["Pacific Empire cables (R.)"]
  },
  "791": {
    "tagDate": ["1904-09-20T00:00:00.000Z"],
    "tagDescription": ["C. Murphy, Grand Trunk Pacific Commission (R.)"],
    "tagName": ["Halpin, P.K."]
  },
  "337": {
    "tagDescription": ["Chateauguay & Northern Ry."],
    "tagDate": ["1904-09-05T00:00:00.000Z"],
    "tagName": ["Mullarkey, J. P."]
  },
  "616": {
    "tagDate": ["1904-09-15T00:00:00.000Z"],
    "tagDescription": ["Appointment"],
    "tagName": ["Giguere, L.C."]
  },
  "596": {
    "tagName": ["Harris, C.A.E."],
    "tagDate": ["1904-09-14T00:00:00.000Z"],
    "tagDescription": ["Musical concert (R.)"]
  },
  "305": {
    "tagDescription": ["Private car (R. only)"],
    "tagDate": ["1904-09-02T00:00:00.000Z"],
    "tagName": ["Dubé, W.A."],
    "tagNotebook": ["LAURIER PAPERS"]
  },
  "982": {
    "tagDate": ["1904-09-26T00:00:00.000Z"],
    "tagDescription": ["Complaint re. I.C.R., Levis station (R. only)"],
    "tagNotebook": ["LAURIER PAPERS"],
    "tagName": ["Fafard, E. Rev."]
  },
  "365": {
    "tagDescription": ["North West Mounted Police"],
    "tagDate": ["1904-09-06T00:00:00.000Z"],
    "tagName": ["White, Fred"]
  },
  "1058": {
    "tagName": ["Griffith, W. L."],
    "tagDescription": ["(R.)"],
    "tagDate": ["1904-09-28T00:00:00.000Z"]
  },
  "605": {
    "tagDate": ["1904-09-14T00:00:00.000Z"],
    "tagDescription": ["Grand Trunk Ry. (R.)"],
    "tagName": ["Riley, George"]
  },
  "798": {
    "tagDate": ["1904-09-20T00:00:00.000Z"],
    "tagDescription": ["Murphy, appointment (R.)"],
    "tagNotebook": ["LAURIER PAPERS"],
    "tagName": ["Coffey, Thos."]
  },
  "849": {
    "tagDate": ["1904-09-21T00:00:00.000Z"],
    "tagDescription": ["Ride with Lord Minto Edmonton to Saskatoon"],
    "tagName": ["Minto, Lord"]
  },
  "100": {
    "tagName": ["Mackinnon, David Alex. Hon."],
    "tagDescription": ["Lt.-Governorship - P.E.I."],
    "tagDate": ["1904-08-18T00:00:00.000Z"]
  },
  "967": {
    "tagName": ["Dandurand, R."],
    "tagNotebook": ["LAURIER PAPERS"],
    "tagDescription": ["French steamship subsidy (Encl.) (R.)"],
    "tagDate": ["1904-09-26T00:00:00.000Z"]
  },
  "889": {
    "tagDescription": ["Judgeship (Encl.) (R.)"],
    "tagDate": ["1904-09-23T00:00:00.000Z"],
    "tagName": ["Langelier, Francois"]
  },
  "57": {
    "tagName": ["Ouellette, Octave"],
    "tagDescription": ["Savoie - Guay Co."],
    "tagDate": ["1904-08-17T00:00:00.000Z"]
  },
  "203": {
    "tagDate": ["1904-08-25T00:00:00.000Z"],
    "tagDescription": ["Grand Trunk Pacific Ry. (R.)"],
    "tagName": ["Greenwood, W.H."]
  },
  "43": {
    "tagName": ["Joly de Lotbiniere, H.G."],
    "tagDate": ["1904-08-16T00:00:00.000Z"],
    "tagDescription": ["(R.only)"]
  },
  "284": {
    "tagDate": ["1904-09-01T00:00:00.000Z"],
    "tagDescription": ["Hon. Jas. Sutherland (R.)"],
    "tagNotebook": ["LAURIER PAPERS"],
    "tagName": ["Ford, C.Y."]
  },
  "679": {
    "tagDate": ["1904-09-17T00:00:00.000Z"],
    "tagDescription": ["Swearing in of Governor-General"],
    "tagName": ["Taschereau, H. E."]
  },
  "866": {
    "tagDate": ["1904-09-22T00:00:00.000Z"],
    "tagDescription": ["Solicitor: Grand Trunk Pacific Commission"],
    "tagName": ["Murphy, F."]
  },
  "815": {
    "tagName": ["Belcourt, Hon. N.A."],
    "tagNotebook": ["LAURIER PAPERS"],
    "tagDescription": ["Holiday to visit exhibition (R.)"],
    "tagDate": ["1904-09-20T00:00:00.000Z"]
  },
  "263": {
    "tagName": ["Jones, A. G."],
    "tagDate": ["1904-08-30T00:00:00.000Z"],
    "tagDescription": ["Duches of Marlborough"]
  },
  "942": {
    "tagDescription": ["Hering Sea; Arrival of new Lord Grey"],
    "tagDate": ["1904-09-25T00:00:00.000Z"],
    "tagName": ["Minto, Lord"]
  },
  "280": {
    "tagDate": ["1904-09-01T00:00:00.000Z"],
    "tagDescription": ["Date of election"],
    "tagName": ["Macdonald, J.A. Rev."]
  },
  "1053": {
    "tagDate": ["1904-09-28T00:00:00.000Z"],
    "tagDescription": ["Yonge St. bridge (R.)"],
    "tagName": ["Urquhart, T."]
  },
  "1037": {
    "tagName": ["Guerin, Edmund"],
    "tagDate": ["1904-09-27T00:00:00.000Z"],
    "tagDescription": ["Invitation (R.)"]
  },
  "170": {
    "tagName": ["Hutcheson, R.J."],
    "tagDate": ["1904-08-22T00:00:00.000Z"],
    "tagDescription": ["Duty on lumber (R.)"]
  },
  "518": {
    "tagName": ["Russell, Chas."],
    "tagDescription": ["Rev. Lambert (Encl.) (R.)"],
    "tagDate": ["1904-09-12T00:00:00.000Z"]
  },
  "885": {
    "tagName": ["Hellencourt, H. d'"],
    "tagDate": ["1904-09-23T00:00:00.000Z"],
    "tagDescription": ["L'Echo du Manitoba"]
  },
  "391": {
    "tagDescription": ["B.C. sealers (R.)"],
    "tagDate": ["1904-09-07T00:00:00.000Z"],
    "tagName": ["Cox, John G."],
    "tagNotebook": ["LAURIER PAPERS"]
  },
  "1025": {
    "tagDescription": ["Ste-Marie Co. (Montreal) (R.)"],
    "tagDate": ["1904-10-08T00:00:00.000Z"],
    "tagName": ["David, L.O."],
    "tagNotebook": ["LAURIER PAPERS"]
  },
  "765": {
    "tagDescription": ["General election (R.)"],
    "tagDate": ["1904-09-20T00:00:00.000Z"],
    "tagName": ["Lavergne, L."]
  },
  "89": {
    "tagDate": ["1904-08-18T00:00:00.000Z"],
    "tagDescription": ["France-Canada steamship line (R.)"],
    "tagName": ["Gow, Walter"]
  },
  "174": {
    "tagName": ["Robertson, J. E."],
    "tagDescription": ["Election, P.E.I. politics (R.)"],
    "tagDate": ["1904-08-23T00:00:00.000Z"]
  },
  "214": {
    "tagNotebook": ["LAURIER PAPERS"],
    "tagName": ["Brodeur, Louis Philippe Hon."],
    "tagDate": ["1904-08-25T00:00:00.000Z"],
    "tagDescription": ["Quebec election campaign (R.)"]
  },
  "1006": {
    "tagNotebook": ["LAURIER PAPERS"],
    "tagName": ["Bédard, J.E."],
    "tagDate": ["1904-09-27T00:00:00.000Z"],
    "tagDescription": [
      "Appointment of Routhier as Chief Justice of Quebec (R.)"
    ]
  },
  "852": {
    "tagDescription": ["Murphy, Appointment (R.)"],
    "tagDate": ["1904-09-21T00:00:00.000Z"],
    "tagName": ["Mulvey, Thomas"]
  },
  "124": {
    "tagName": ["Herbette, Louis"],
    "tagDescription": ["St. Louis Exposition"],
    "tagDate": ["1904-08-18T00:00:00.000Z"]
  },
  "586": {
    "tagName": ["Parent, S.N. Hon."],
    "tagDate": ["1904-09-13T00:00:00.000Z"],
    "tagDescription": ["Liberal candidate Portneuf Co. (R.)"]
  },
  "801": {
    "tagNotebook": ["LAURIER PAPERS"],
    "tagName": ["Bryce, James"],
    "tagDate": ["1904-09-20T00:00:00.000Z"],
    "tagDescription": ["Interview (R.)"]
  },
  "1030": {
    "tagNotebook": ["LAURIER PAPERS"],
    "tagName": ["Cowan, M. K."],
    "tagDate": ["1904-09-27T00:00:00.000Z"],
    "tagDescription": ["Dominion elections-Windsor (R.)"]
  },
  "177": {
    "tagName": ["Mackay"],
    "tagDate": ["1904-08-23T00:00:00.000Z"],
    "tagDescription": ["Australian natives (R.)"]
  },
  "36": {
    "tagName": ["Lecoq, C. Rev."],
    "tagDescription": ["Oka Indians"],
    "tagDate": ["1904-08-15T00:00:00.000Z"]
  },
  "77": {
    "tagName": ["Mingan, Michel Parant"],
    "tagDescription": ["Seigniories in St. Lawrence"],
    "tagDate": ["1904-08-17T00:00:00.000Z"]
  },
  "833": {
    "tagName": ["Emmerson, H.R."],
    "tagNotebook": ["LAURIER PAPERS"],
    "tagDescription": ["Judgeship"],
    "tagDate": ["1904-09-20T00:00:00.000Z"]
  },
  "569": {
    "tagName": ["Lewis, John"],
    "tagDate": ["1904-09-13T00:00:00.000Z"]
  },
  "1004": {
    "tagDescription": ["Dominion elections"],
    "tagDate": ["1904-09-27T00:00:00.000Z"],
    "tagName": ["Power, L.G."]
  },
  "348": {
    "tagDate": ["1904-01-01T00:00:00.000Z"],
    "tagDescription": ["Purchase, repair of fur coats"],
    "tagName": ["Laliberté, J. B."]
  },
  "84": {
    "tagDescription": ["Militia matters (R.)"],
    "tagDate": ["1904-08-17T00:00:00.000Z"],
    "tagName": ["Pgold, Nore S."]
  },
  "537": {
    "tagName": ["Armstrong, Whitworth and Co."],
    "tagNotebook": ["LAURIER PAPERS"],
    "tagDescription": ["Re. Carbonneau"],
    "tagDate": ["1904-09-12T00:00:00.000Z"]
  },
  "960": {
    "tagName": ["Smith, C.W."],
    "tagDescription": ["Militia claim"],
    "tagDate": ["1904-09-26T00:00:00.000Z"]
  },
  "424": {
    "tagName": ["Dandurand, R."],
    "tagNotebook": ["LAURIER PAPERS"],
    "tagDescription": ["Interview (R.)"],
    "tagDate": ["1904-09-08T00:00:00.000Z"]
  },
  "654": {
    "tagDescription": ["Invitation(R.) (Encl.)"],
    "tagDate": ["1904-09-16T00:00:00.000Z"],
    "tagName": ["Canadian Manufacturers Assn."],
    "tagNotebook": ["LAURIER PAPERS"]
  },
  "650": {
    "tagDescription": ["Fishery rights P.E.I. (R.)"],
    "tagDate": ["1904-09-16T00:00:00.000Z"],
    "tagName": ["Peters, Hon. Arthur"]
  },
  "459": {
    "tagName": ["Monet, D."],
    "tagDate": ["1904-09-10T00:00:00.000Z"],
    "tagDescription": ["Faithfulness to party"]
  },
  "516": {
    "tagDate": ["1904-09-12T00:00:00.000Z"],
    "tagDescription": ["General election; Haldimand Co. (Encl.) (R.)"],
    "tagName": ["Thompson, A.T."]
  },
  "1044": {
    "tagNotebook": ["LAURIER PAPERS"],
    "tagName": ["Beique, Hon. F.L."],
    "tagDate": ["1904-09-28T00:00:00.000Z"],
    "tagDescription": ["Visit of Métin and Labour Unions delegates"]
  },
  "341": {
    "tagDescription": ["Senatorship (R.)"],
    "tagDate": ["1904-09-05T00:00:00.000Z"],
    "tagName": ["Gillmor, Dan"]
  },
  "412": {
    "tagName": ["Carr, M."],
    "tagNotebook": ["LAURIER PAPERS"],
    "tagDescription": ["Senatorship (R.)"],
    "tagDate": ["1904-09-08T00:00:00.000Z"]
  },
  "155": {
    "tagDate": ["1904-08-20T00:00:00.000Z"],
    "tagDescription": ["Lt.-Governorship - P.E.I."],
    "tagName": ["Mackinnon, David Alex. Hon."]
  },
  "444": {
    "tagDescription": ["Fisheries Questions"],
    "tagDate": ["1904-09-09T00:00:00.000Z"],
    "tagName": ["Peters, Hon. Arthur"]
  },
  "972": {
    "tagDescription": ["General election B.C. (R.)"],
    "tagDate": ["1904-09-26T00:00:00.000Z"],
    "tagName": ["Prenter, S.L."]
  },
  "9": {
    "tagName": ["Patent, S.N. Hon."],
    "tagDescription": ["Appt. Railway Commission"],
    "tagDate": ["1904-08-15T00:00:00.000Z"]
  },
  "936": {
    "tagName": ["Malouin, Albert"],
    "tagDescription": ["Judgeship Liberal candidate (R.)"],
    "tagDate": ["1904-09-25T00:00:00.000Z"]
  },
  "865": {
    "tagDate": ["1904-09-22T00:00:00.000Z"],
    "tagDescription": ["Interview"],
    "tagName": ["Murphy, Charles"]
  },
  "54": {
    "tagName": ["Snowball, J.B."],
    "tagDate": ["1904-08-16T00:00:00.000Z"],
    "tagDescription": ["Invitation"]
  },
  "649": {
    "tagName": ["McManamy, D."],
    "tagDate": ["1904-09-16T00:00:00.000Z"],
    "tagDescription": ["Liberal candidacy Sheerbrooke (R. only)"]
  },
  "561": {
    "tagDate": ["1904-09-13T00:00:00.000Z"],
    "tagDescription": ["Senatorship (R.)"],
    "tagNotebook": ["LAURIER PAPERS"],
    "tagName": ["Choquette, P. A."]
  },
  "200": {
    "tagDate": ["1904-08-24T00:00:00.000Z"],
    "tagDescription": ["Robert Jaffray"],
    "tagName": ["Rowell, N. W."]
  },
  "345": {
    "tagDescription": ["Le Soleil (R.)"],
    "tagDate": ["1904-09-05T00:00:00.000Z"],
    "tagName": ["Simard, C.J."]
  },
  "1047": {
    "tagDate": ["1904-09-28T00:00:00.000Z"],
    "tagDescription": ["United Irish League - invitation (R.)"],
    "tagNotebook": ["LAURIER PAPERS"],
    "tagName": ["Bergin, Joseph"]
  },
  "497": {
    "tagName": ["Pion, George A."],
    "tagDescription": ["Legal appointment: Grand Trunk Pacific Railway (R.)"],
    "tagDate": ["1904-09-12T00:00:00.000Z"]
  },
  "144": {
    "tagName": ["Parent, S.N. Hon."],
    "tagDate": ["1904-08-19T00:00:00.000Z"],
    "tagDescription": ["Director of Grand Trunk Pacific Railway Co."]
  },
  "987": {
    "tagNotebook": ["LAURIER PAPERS"],
    "tagName": ["Dugas, F.O."],
    "tagDate": ["1904-09-26T00:00:00.000Z"],
    "tagDescription": ["Great Northern Railway (R.)"]
  },
  "676": {
    "tagDate": ["1904-09-17T00:00:00.000Z"],
    "tagDescription": ["Yonge St. Bridge (R.)"],
    "tagNotebook": ["LAURIER PAPERS"],
    "tagName": ["Drinkwater, C."]
  },
  "283": {
    "tagDate": ["1904-09-01T00:00:00.000Z"],
    "tagDescription": ["Compensation"],
    "tagNotebook": ["LAURIER PAPERS"],
    "tagName": ["Boulanger, G. Capt."]
  },
  "158": {
    "tagName": ["Thompson, F. W."],
    "tagDate": ["1904-08-22T00:00:00.000Z"],
    "tagDescription": ["South Africa steamship line"]
  },
  "501": {
    "tagName": ["Urquhart, T."],
    "tagDescription": ["Yonge St. bridge (R.)"],
    "tagDate": ["1904-09-12T00:00:00.000Z"]
  },
  "632": {
    "tagName": ["Case, E. W."],
    "tagNotebook": ["LAURIER PAPERS"],
    "tagDescription": ["Date of election (R.)"],
    "tagDate": ["1904-09-15T00:00:00.000Z"]
  },
  "1012": {
    "tagDescription": ["Invitation Visit to Goldwin Smith (Encl.)"],
    "tagDate": ["1904-09-27T00:00:00.000Z"],
    "tagName": ["Bryce, James"],
    "tagNotebook": ["LAURIER PAPERS"]
  },
  "519": {
    "tagName": ["Urquhart, T."],
    "tagDate": ["1904-09-12T00:00:00.000Z"],
    "tagDescription": ["Yonge St. bridge (R.) (R. only)"]
  },
  "242": {
    "tagNotebook": ["LAURIER PAPERS"],
    "tagName": ["Blair, Andrew George Hon."],
    "tagDate": ["1904-08-28T00:00:00.000Z"],
    "tagDescription": ["Railway Commission"]
  },
  "980": {
    "tagNotebook": ["LAURIER PAPERS"],
    "tagName": ["Day, James E."],
    "tagDate": ["1904-09-26T00:00:00.000Z"],
    "tagDescription": [
      "C. Murphy solicitor for Grand Trunk Pacific commission (R.)"
    ]
  },
  "490": {
    "tagDate": ["1904-09-12T00:00:00.000Z"],
    "tagDescription": ["Election campaign - E. Hastings (Encl.) (R.)"],
    "tagNotebook": ["LAURIER PAPERS"],
    "tagName": ["Deroche, G.E."]
  },
  "811": {
    "tagName": ["Turgeon, Adelard"],
    "tagDescription": ["School situation, Winnipeg (R.)"],
    "tagDate": ["1904-09-20T00:00:00.000Z"]
  },
  "61": {
    "tagName": ["Smith, R. Wilson"],
    "tagDescription": ["Invitation (R.)"],
    "tagDate": ["1904-08-17T00:00:00.000Z"]
  },
  "552": {
    "tagName": ["Mackay, E."],
    "tagDate": ["1904-09-12T00:00:00.000Z"],
    "tagDescription": ["Essex Co. politics"]
  },
  "59": {
    "tagName": ["Minto, Lord"],
    "tagDescription": ["Honours"],
    "tagDate": ["1904-08-17T00:00:00.000Z"]
  },
  "102": {
    "tagDescription": ["Quebec railways (R.)"],
    "tagDate": ["1904-08-18T00:00:00.000Z"],
    "tagName": ["Mackenzie, Wm. (Mackenzie and Mann)"]
  },
  "31": {
    "tagName": ["Wade, F. B."],
    "tagDescription": ["Appointment: G.T.P. Commission (Encl.) (R.)"],
    "tagDate": ["1904-08-15T00:00:00.000Z"]
  },
  "74": {
    "tagDate": ["1904-08-17T00:00:00.000Z"],
    "tagDescription": ["Montreal Horticultural Society - invitation (R.)"],
    "tagName": ["Smith, R. Wilson"]
  },
  "156": {
    "tagDescription": ["L'Echo du Manitoba (Encl.)"],
    "tagDate": ["1904-08-22T00:00:00.000Z"],
    "tagName": ["Hellencourt, H. d'"]
  },
  "695": {
    "tagDescription": ["Homesteading (Encl.) (R.)"],
    "tagDate": ["1904-09-17T00:00:00.000Z"],
    "tagName": ["Bourget, L.G."],
    "tagNotebook": ["LAURIER PAPERS"]
  },
  "566": {
    "tagDate": ["1904-09-13T00:00:00.000Z"],
    "tagDescription": ["Judgeship (R. only)"],
    "tagName": ["Grant, D."]
  },
  "914": {
    "tagDate": ["1904-09-24T00:00:00.000Z"],
    "tagDescription": ["Thanksgiving Day(R.)"],
    "tagNotebook": ["LAURIER PAPERS"],
    "tagName": ["Cowan, H. B."]
  },
  "678": {
    "tagDate": ["1904-09-17T00:00:00.000Z"],
    "tagDescription": ["Translation & printing, House of Commons Speeches"],
    "tagNotebook": ["LAURIER PAPERS"],
    "tagName": ["Fielding, W.S."]
  },
  "834": {
    "tagName": ["Congdon, F. T."],
    "tagNotebook": ["LAURIER PAPERS"],
    "tagDescription": ["Yukon election (R.)"],
    "tagDate": ["1904-09-21T00:00:00.000Z"]
  },
  "194": {
    "tagDate": ["1904-08-24T00:00:00.000Z"],
    "tagDescription": ["Membership: railway commission"],
    "tagNotebook": ["LAURIER PAPERS"],
    "tagName": ["Brunet, A."]
  },
  "589": {
    "tagName": ["Sawyer, Ernest E."],
    "tagDescription": ["Interviews"],
    "tagDate": ["1904-09-14T00:00:00.000Z"]
  },
  "830": {
    "tagDescription": ["Visit to Canada"],
    "tagDate": ["1904-09-20T00:00:00.000Z"],
    "tagName": ["Morley, John"]
  },
  "378": {
    "tagDescription": ["Railway extension (R.)"],
    "tagDate": ["1904-09-07T00:00:00.000Z"],
    "tagName": ["Brodie, J.L."],
    "tagNotebook": ["LAURIER PAPERS"]
  },
  "768": {
    "tagName": ["Pelletier, C.A.P Sir"],
    "tagDescription": ["Federal election (R.)"],
    "tagDate": ["1904-09-20T00:00:00.000Z"]
  },
  "881": {
    "tagName": ["Pelletier, C.A.P Sir"],
    "tagDescription": ["Resignation and appointment (R.)"],
    "tagDate": ["1904-09-22T00:00:00.000Z"]
  },
  "395": {
    "tagName": ["Lemay, E. H."],
    "tagDescription": ["Invitation (R.)"],
    "tagDate": ["1904-09-07T00:00:00.000Z"]
  },
  "1040": {
    "tagDate": ["1904-09-27T00:00:00.000Z"],
    "tagDescription": ["Dominion election-L'Islet"],
    "tagName": ["Rioux, Narcisse"]
  },
  "134": {
    "tagName": ["Graham, G.P."],
    "tagDescription": ["Ontario politics (R.)"],
    "tagDate": ["1904-08-19T00:00:00.000Z"]
  },
  "307": {
    "tagName": ["Prefontaine, Raymond Hon."],
    "tagDate": ["1904-09-02T00:00:00.000Z"],
    "tagDescription": ["Interview"]
  },
  "759": {
    "tagDate": ["1904-09-19T00:00:00.000Z"],
    "tagDescription": ["Reciprocity with U.S. (R.)"],
    "tagName": ["Ingraham, J.E."]
  },
  "411": {
    "tagNotebook": ["LAURIER PAPERS"],
    "tagName": ["Birt, Potter & Hughes"],
    "tagDate": ["1904-09-08T00:00:00.000Z"],
    "tagDescription": ["Steamship line"]
  },
  "856": {
    "tagName": ["Canadian Society of Civil Engineers"],
    "tagNotebook": ["LAURIER PAPERS"],
    "tagDescription": ["Invitation(R.)"],
    "tagDate": ["1904-09-21T00:00:00.000Z"]
  },
  "642": {
    "tagDescription": ["Canadian Politics (Encl.)(R.)"],
    "tagDate": ["1904-09-16T00:00:00.000Z"],
    "tagName": ["Long, J.R."]
  },
  "635": {
    "tagName": ["Walsh, J. M. (North West Mounted Police)"],
    "tagDescription": ["Election campaign"],
    "tagDate": ["1904-09-15T00:00:00.000Z"]
  },
  "418": {
    "tagDescription": ["Election campaign, Ontario (R.)"],
    "tagDate": ["1904-09-08T00:00:00.000Z"],
    "tagName": ["Walsh, J. M. (North West Mounted Police)"]
  },
  "181": {
    "tagDate": ["1904-08-23T00:00:00.000Z"],
    "tagDescription": ["Early political experiences Gaspe politics"],
    "tagName": ["Limieux, F.X."]
  },
  "130": {
    "tagName": ["Morgan, Arthur"],
    "tagDate": ["1904-08-18T00:00:00.000Z"],
    "tagDescription": ["Australia L. Pereira (Encl.) (R.)"]
  },
  "226": {
    "tagName": ["Smith, Alex"],
    "tagDescription": ["Federal election (R.)"],
    "tagDate": ["1904-08-26T00:00:00.000Z"]
  },
  "367": {
    "tagName": ["Mauntel, J.J."],
    "tagDate": ["1904-09-06T00:00:00.000Z"],
    "tagDescription": ["St. Vincent de Paul Society - Invitation (R.)"]
  },
  "574": {
    "tagName": ["Shaughnessy, Thomas G. Sir"],
    "tagDate": ["1904-09-13T00:00:00.000Z"],
    "tagDescription": ["Interview"]
  },
  "28": {
    "tagName": ["Ross, Sir Charles"],
    "tagDate": ["1904-08-15T00:00:00.000Z"],
    "tagDescription": ["Location of small arms factory (R.)"]
  },
  "975": {
    "tagDate": ["1904-09-26T00:00:00.000Z"],
    "tagDescription": ["(R.)"],
    "tagName": ["Lovell, H."]
  },
  "339": {
    "tagName": ["Thompson, F. P."],
    "tagDescription": ["Patronage (R.)"],
    "tagDate": ["1904-09-05T00:00:00.000Z"]
  },
  "755": {
    "tagName": ["Delisle, Michel Simeon"],
    "tagNotebook": ["LAURIER PAPERS"],
    "tagDescription": ["Party division Portneuf Co."],
    "tagDate": ["1904-09-19T00:00:00.000Z"]
  },
  "47": {
    "tagName": ["Sutherland, R.F."],
    "tagDate": ["1904-08-16T00:00:00.000Z"],
    "tagDescription": ["Senatorship (Encl.) (R.)"]
  },
  "639": {
    "tagDate": ["1904-09-16T00:00:00.000Z"],
    "tagDescription": ["(R.)"],
    "tagName": ["Lewis, John"]
  },
  "847": {
    "tagDescription": ["Chaplain: Transportation Commission (R.)"],
    "tagDate": ["1901-09-21T00:00:00.000Z"],
    "tagName": ["Whelan, M. J. Rev."]
  },
  "481": {
    "tagName": ["labranche, Ferdinand"],
    "tagDescription": ["Dominion election-Portneuf Co. (R.)"],
    "tagDate": ["1904-09-10T00:00:00.000Z"]
  },
  "520": {
    "tagName": ["Dugas, G. Rev."],
    "tagNotebook": ["LAURIER PAPERS"],
    "tagDescription": ["Book: L'Ouest Canadien (R.)"],
    "tagDate": ["1904-09-12T00:00:00.000Z"]
  },
  "228": {
    "tagDescription": ["General Lake"],
    "tagDate": ["1904-08-27T00:00:00.000Z"],
    "tagName": ["Grey, Lord"]
  },
  "743": {
    "tagName": ["Griffin, Martin J. (Library of Parliament)"],
    "tagDescription": ["Memos & books sent to Laurier"],
    "tagDate": ["1904-09-19T00:00:00.000Z"]
  },
  "42": {
    "tagNotebook": ["LAURIER PAPERS"],
    "tagName": ["Emmerson, H.R."],
    "tagDate": ["1904-08-15T00:00:00.000Z"],
    "tagDescription": ["Le Soleil"]
  },
  "692": {
    "tagName": ["Bruneau, A.A."],
    "tagNotebook": ["LAURIER PAPERS"],
    "tagDescription": ["Richelieu County"],
    "tagDate": ["1904-09-17T00:00:00.000Z"]
  },
  "858": {
    "tagDescription": ["Interview"],
    "tagDate": ["1904-09-22T00:00:00.000Z"],
    "tagName": ["Dandurand, R."],
    "tagNotebook": ["LAURIER PAPERS"]
  },
  "577": {
    "tagPerson": ["Fitzpatrick, Charles Hon."],
    "tagDate": ["1904-09-13T00:00:00.000Z"],
    "tagDescription": ["(Encl.)"],
    "tagName": ["Hyman, Charles S."]
  },
  "221": {
    "tagName": ["Minto, Lord"],
    "tagDescription": ["Imperial Service Order"],
    "tagDate": ["1904-08-26T00:00:00.000Z"]
  },
  "613": {
    "tagName": ["Mulock, Wm."],
    "tagDescription": ["R.J.McLaughlin Dominion election (Encl.) (R.)"],
    "tagDate": ["1904-09-15T00:00:00.000Z"]
  },
  "840": {
    "tagDate": ["1904-09-21T00:00:00.000Z"],
    "tagNotebook": ["LAURIER PAPERS"],
    "tagName": ["Dyment, A.E."]
  },
  "109": {
    "tagName": ["Belcourt, Hon. N.A."],
    "tagNotebook": ["LAURIER PAPERS"],
    "tagDescription": ["Appointment G. T. P. Commission"],
    "tagDate": ["1904-08-18T00:00:00.000Z"]
  },
  "593": {
    "tagName": ["Rousseau, A."],
    "tagDescription": ["Political issues (R.)"],
    "tagDate": ["1904-09-14T00:00:00.000Z"]
  },
  "12": {
    "tagName": ["Health Food Co."],
    "tagDescription": ["Gluten bread for Laurier (R.)"],
    "tagDate": ["1904-08-15T00:00:00.000Z"]
  },
  "555": {
    "tagDate": ["1904-09-12T00:00:00.000Z"],
    "tagDescription": ["Hudson Bay views"],
    "tagName": ["White, Fred"]
  },
  "727": {
    "tagDescription": ["Dominion elections-East Elgin (R.)"],
    "tagDate": ["1904-09-18T00:00:00.000Z"],
    "tagName": ["Wilson, Amelia A."]
  },
  "660": {
    "tagNotebook": ["LAURIER PAPERS"],
    "tagName": ["Courtice, A. C. Rev."],
    "tagDate": ["1904-09-16T00:00:00.000Z"],
    "tagDescription": ["Peace Society (Encl.)"]
  },
  "897": {
    "tagName": ["Ross, George W."],
    "tagDate": ["1904-09-24T00:00:00.000Z"],
    "tagDescription": ["Hon. Devlin (R.)"]
  },
  "469": {
    "tagName": ["Parent, George W."],
    "tagDescription": ["Hon. Fitzpatrick"],
    "tagDate": ["1904-09-10T00:00:00.000Z"]
  },
  "409": {
    "tagName": ["Sawyer, Ernest E."],
    "tagDate": ["1904-09-08T00:00:00.000Z"],
    "tagDescription": ["Interview (R.)"]
  },
  "996": {
    "tagDescription": ["Liberal candidate L'Islet Co. (Encl.)"],
    "tagDate": ["1904-09-26T00:00:00.000Z"],
    "tagName": ["Parent, S.N. Hon."]
  },
  "948": {
    "tagDescription": ["Invitation (Encl.) (R.)"],
    "tagDate": ["1904-09-26T00:00:00.000Z"],
    "tagName": ["Peterson, W."]
  },
  "26": {
    "tagNotebook": ["LAURIER PAPERS"],
    "tagDate": ["1904-08-15T00:00:00.000Z"]
  },
  "747": {
    "tagDescription": ["G.T.P.Ry. Solicitorship (Encl.)"],
    "tagDate": ["1904-09-19T00:00:00.000Z"],
    "tagName": ["Murphy, Charles"]
  },
  "6": {
    "tagName": ["Templeman, Wm."],
    "tagDate": ["1904-08-13T00:00:00.000Z"]
  },
  "461": {
    "tagNotebook": ["LAURIER PAPERS"],
    "tagName": ["Casgrain, L. C. A."],
    "tagDate": ["1904-09-10T00:00:00.000Z"],
    "tagDescription": ["Liberal candidate, Essex Co."]
  },
  "433": {
    "tagDate": ["1904-09-08T00:00:00.000Z"],
    "tagDescription": ["B.C. judgeship (R.)"],
    "tagName": ["Macpherson, R.G."]
  },
  "372": {
    "tagDate": ["1904-09-07T00:00:00.000Z"],
    "tagDescription": ["Interview (R.)"],
    "tagNotebook": ["LAURIER PAPERS"],
    "tagName": ["Canadian Manufacturers Assn."]
  },
  "877": {
    "tagName": ["Macpherson, H."],
    "tagDate": ["1904-09-22T00:00:00.000Z"],
    "tagDescription": ["Senatorship for J. Tolmic, M.P. (R.)"]
  },
  "558": {
    "tagName": ["Robinette, Thos. C."],
    "tagDate": ["1904-09-12T00:00:00.000Z"],
    "tagDescription": ["Yonge St. bridge"]
  },
  "229": {
    "tagName": ["Tomlinson, W.M."],
    "tagDate": ["1904-08-27T00:00:00.000Z"],
    "tagDescription": ["Sherbrooke Exhibition invitation (R.)"]
  },
  "44": {
    "tagDescription": ["Solicitor - Grand Trunk Pacific Railway (R.)"],
    "tagDate": ["1904-08-16T00:00:00.000Z"],
    "tagName": ["Deroche, G.E."],
    "tagNotebook": ["LAURIER PAPERS"]
  },
  "250": {
    "tagName": ["Markey, Fred H."],
    "tagDescription": ["Lease- Selkirk Co. (R.)"],
    "tagDate": ["1904-08-29T00:00:00.000Z"]
  },
  "893": {
    "tagName": ["Trades & Labour congress"],
    "tagDate": ["1904-09-23T00:00:00.000Z"],
    "tagDescription": ["Re. Invitation (R.)"]
  },
  "540": {
    "tagName": ["Pacaud, Ernest Mrs."],
    "tagDate": ["1904-09-12T00:00:00.000Z"],
    "tagDescription": ["Le Soleil (R.)"]
  },
  "387": {
    "tagDescription": [
      "Subsidy: Atlantic and Lake Superior Railway Co. (Encl.) (R.)"
    ],
    "tagDate": ["1904-09-07T00:00:00.000Z"],
    "tagName": ["Perreault, Z."]
  },
  "859": {
    "tagDate": ["1904-09-22T00:00:00.000Z"],
    "tagDescription": ["Haldimand Co. (R.)"],
    "tagName": ["Thompson, A.T."]
  },
  "1023": {
    "tagDate": ["1904-09-27T00:00:00.000Z"],
    "tagDescription": ["General election - Richelieu Co. (Encl.) (R.)"],
    "tagNotebook": ["LAURIER PAPERS"],
    "tagName": ["David, L.O."]
  },
  "108": {
    "tagDate": ["1904-08-18T00:00:00.000Z"],
    "tagDescription": ["Senatorship"],
    "tagNotebook": ["LAURIER PAPERS"],
    "tagName": ["Dickenson, H."]
  },
  "945": {
    "tagName": ["Siegfried, Jules"],
    "tagDescription": ["Introduction"],
    "tagDate": ["1904-09-25T00:00:00.000Z"]
  },
  "254": {
    "tagDescription": ["Invitation (R.)"],
    "tagDate": ["1904-08-29T00:00:00.000Z"],
    "tagName": ["Jetter, Louis Amable Sir"]
  },
  "1009": {
    "tagName": ["Mackay, Robert"],
    "tagDate": ["1904-09-27T00:00:00.000Z"],
    "tagDescription": ["Special Fund - (Election) (R. only)"]
  },
  "303": {
    "tagDescription": ["New Steamer, Allan steamship Line"],
    "tagDate": ["1904-09-02T00:00:00.000Z"],
    "tagName": ["Allan, Hugh & Andrew"],
    "tagNotebook": ["LAURIER PAPERS"]
  },
  "999": {
    "tagDescription": ["Appointments (R.)"],
    "tagDate": ["1904-09-26T00:00:00.000Z"],
    "tagName": ["Laurier, Henri"]
  },
  "384": {
    "tagNotebook": ["LAURIER PAPERS"],
    "tagName": ["Fitzpatrick, Charles"],
    "tagDate": ["1904-09-07T00:00:00.000Z"],
    "tagDescription": ["Manitoba schools (R.)"]
  },
  "1022": {
    "tagName": ["Stephens, George W."],
    "tagDate": ["1904-09-27T00:00:00.000Z"],
    "tagDescription": ["Special Election fund (R.)"]
  },
  "257": {
    "tagDescription": ["Governor General's business"],
    "tagDate": ["1904-08-29T00:00:00.000Z"],
    "tagName": ["Grey, Lord"]
  },
  "870": {
    "tagName": ["Dansereau, A.", "Prefontaine, Raymond Hon."],
    "tagNotebook": ["LAURIER PAPERS"],
    "tagDescription": ["Political situation Prescott (Encl.)"],
    "tagDate": ["1904-09-22T00:00:00.000Z"]
  },
  "152": {
    "tagNotebook": ["LAURIER PAPERS"],
    "tagName": ["Fitzpatrick, Charles"],
    "tagDate": ["1904-08-19T00:00:00.000Z"],
    "tagDescription": ["Itinerary (R. only)"]
  },
  "874": {
    "tagDescription": ["Liberal candidate Levis (R.)"],
    "tagDate": ["1904-09-22T00:00:00.000Z"],
    "tagName": ["Demers, L.J."],
    "tagNotebook": ["LAURIER PAPERS"]
  },
  "1049": {
    "tagName": ["Griffiths, Thos. J. (National Trades & Labor Congress)"],
    "tagDescription": ["Working hours, Quebec fortifications (R.)"],
    "tagDate": ["1904-09-28T00:00:00.000Z"]
  },
  "119": {
    "tagName": ["McLean, D.L."],
    "tagDescription": ["Appointment - Grand Trunk Pacific Railway"],
    "tagDate": ["1904-08-18T00:00:00.000Z"]
  },
  "1051": {
    "tagNotebook": ["LAURIER PAPERS"],
    "tagName": ["Duhamel Joseph"],
    "tagDate": ["1904-09-28T00:00:00.000Z"],
    "tagDescription": ["Invitation (R.)"]
  },
  "363": {
    "tagName": ["White, Fred"],
    "tagDescription": ["Supplies on Arctic"],
    "tagDate": ["1904-09-06T00:00:00.000Z"]
  },
  "684": {
    "tagDescription": ["Laliberte, sculptor"],
    "tagPerson": ["Fitzpatrick, Charles Hon."],
    "tagDate": ["1904-09-17T00:00:00.000Z"],
    "tagName": ["Cote, Thos"],
    "tagNotebook": ["LAURIER PAPERS"]
  },
  "380": {
    "tagName": ["Wade, F. B."],
    "tagDate": ["1904-09-07T00:00:00.000Z"],
    "tagDescription": ["Appointment: Assistant Engineer (R.)"]
  },
  "485": {
    "tagDescription": ["French delegation of workers to Canada (Encl.) (R.)"],
    "tagDate": ["1904-09-11T00:00:00.000Z"],
    "tagName": ["Metin, A."]
  },
  "978": {
    "tagDate": ["1904-09-26T00:00:00.000Z"],
    "tagDescription": ["Invitation"],
    "tagName": ["Minto, Lord"]
  },
  "291": {
    "tagName": ["Pelletier, C.A.P Sir"],
    "tagDate": ["1904-09-01T00:00:00.000Z"],
    "tagDescription": ["L'Islet Co. Politics Affaire Pacaud (R.)"]
  },
  "758": {
    "tagName": ["Girard, M."],
    "tagDate": ["1904-09-19T00:00:00.000Z"],
    "tagDescription": ["Liberal candidate, Nicolet (R.)"]
  },
  "310": {
    "tagDescription": ["Cable from War Office"],
    "tagDate": ["1904-09-03T00:00:00.000Z"],
    "tagName": ["Borden, Hon. F.W."],
    "tagNotebook": ["LAURIER PAPERS"]
  },
  "610": {
    "tagDescription": ["Grand Trunk Pacific Railway solicitorship (R.)"],
    "tagDate": ["1904-09-15T00:00:00.000Z"],
    "tagName": ["Harty, Wm. Hon"]
  },
  "298": {
    "tagDescription": ["Public Trust office - New Zealand (R.)"],
    "tagDate": ["1904-09-01T00:00:00.000Z"],
    "tagName": ["Oswin, H.R.H."]
  },
  "843": {
    "tagDate": ["1904-09-21T00:00:00.000Z"],
    "tagDescription": ["Manual of procedure - British House of Commons (R.)"],
    "tagName": ["Pope, Sir Joseph"]
  },
  "556": {
    "tagName": ["Templeman, Wm."],
    "tagDescription": ["B. C. judgeship (R.)"],
    "tagDate": ["1904-09-12T00:00:00.000Z"]
  },
  "275": {
    "tagDate": ["1904-08-31T00:00:00.000Z"],
    "tagDescription": ["Federal election (R.)"],
    "tagName": ["Macdonald, Peter Dr."]
  },
  "744": {
    "tagDescription": ["Election campaign - Ontario"],
    "tagDate": ["1904-09-19T00:00:00.000Z"],
    "tagName": ["Preston, T.H."]
  },
  "452": {
    "tagName": ["Mackenzie and Mann Company"],
    "tagDescription": ["St.-Jacques Branch"],
    "tagDate": ["1904-09-09T00:00:00.000Z"]
  },
  "121": {
    "tagDescription": ["Duty on lumber (R.)"],
    "tagDate": ["1904-08-18T00:00:00.000Z"],
    "tagName": ["Carter, W. W."],
    "tagNotebook": ["LAURIER PAPERS"]
  },
  "673": {
    "tagName": ["Campbell, J. E."],
    "tagNotebook": ["LAURIER PAPERS"],
    "tagDescription": ["(R.)"],
    "tagDate": ["1904-09-16T00:00:00.000Z"]
  },
  "804": {
    "tagDescription": ["North Atlantic Trading Co. (immigration)"],
    "tagDate": ["1904-09-20T00:00:00.000Z"],
    "tagName": ["Privy Council Office"]
  },
  "149": {
    "tagDate": ["1904-08-20T00:00:00.000Z"],
    "tagDescription": ["Personal finances"],
    "tagNotebook": ["LAURIER PAPERS"],
    "tagName": ["Choquette, P. A."]
  },
  "397": {
    "tagDate": ["1904-09-07T00:00:00.000Z"],
    "tagDescription": ["B.C. judgeship (R.)"],
    "tagName": ["McQueen, J."]
  },
  "763": {
    "tagDate": ["1904-09-19T00:00:00.000Z"],
    "tagDescription": ["Appointment"],
    "tagName": ["Harty, Wm. Hon"]
  },
  "722": {
    "tagName": ["Urquhart, T."],
    "tagDescription": ["Yonge St. bridge Toronto"],
    "tagDate": ["1904-09-17T00:00:00.000Z"]
  },
  "901": {
    "tagName": ["Beck, J.F."],
    "tagNotebook": ["LAURIER PAPERS"],
    "tagDescription": ["Lumbermen's deputation from E. Simcoe (R.)"],
    "tagDate": ["1904-09-24T00:00:00.000Z"]
  },
  "358": {
    "tagDescription": ["Chateauguay & Northern Ry."],
    "tagDate": ["1904-09-06T00:00:00.000Z"],
    "tagName": ["Mullarkey, J. P."]
  },
  "428": {
    "tagName": ["MacLeod, Alberta Catholics of"],
    "tagDescription": ["Senatorship (R.) (Encl.)"],
    "tagDate": ["1904-09-08T00:00:00.000Z"]
  },
  "658": {
    "tagDescription": ["Appointment (Encl.)"],
    "tagDate": ["1904-09-16T00:00:00.000Z"],
    "tagName": ["Templeman, Wm."]
  },
  "351": {
    "tagName": ["Lecoq, C. Rev."],
    "tagDate": ["1904-09-06T00:00:00.000Z"],
    "tagDescription": ["Freres de Saint Francois Regis"]
  },
  "145": {
    "tagName": ["Canadian Manufacturers Assn."],
    "tagNotebook": ["LAURIER PAPERS"],
    "tagDescription": ["Canadian building in London"],
    "tagDate": ["1904-08-20T00:00:00.000Z"]
  },
  "961": {
    "tagDate": ["1904-09-26T00:00:00.000Z"],
    "tagDescription": ["Speech: S. Africa"],
    "tagName": ["Malan, F. S."]
  },
  "1033": {
    "tagName": ["Greenshields, J. N."],
    "tagDate": ["1904-02-27T00:00:00.000Z"],
    "tagDescription": ["Poupore vs. Rex"]
  },
  "908": {
    "tagDate": ["1904-09-24T00:00:00.000Z"],
    "tagDescription": ["L'Union Nationale Francaise"],
    "tagName": ["Prefontaine, Raymond Hon."]
  },
  "344": {
    "tagDate": ["1904-09-05T00:00:00.000Z"],
    "tagDescription": ["Complaint (R. only)"],
    "tagName": ["Germany, Consul General (Bopp, F.)"]
  },
  "11": {
    "tagName": ["Roy, Charles T."],
    "tagDate": ["1904-08-15T00:00:00.000Z"],
    "tagDescription": ["Treatment of inerbriates (R.only)"]
  },
  "27": {
    "tagDate": ["1904-08-15T00:00:00.000Z"],
    "tagDescription": ["Interview (R.)"],
    "tagName": ["Graham, G.P."]
  },
  "503": {
    "tagDescription": ["Yonge St. bridge (R.)"],
    "tagDate": ["1904-09-08T00:00:00.000Z"],
    "tagName": ["Urquhart, T."]
  },
  "478": {
    "tagName": ["Choquette, P. A."],
    "tagNotebook": ["LAURIER PAPERS"],
    "tagDescription": ["Appointment, Senatorship"],
    "tagDate": ["1904-09-10T00:00:00.000Z"]
  },
  "1032": {
    "tagName": ["Hodgson, Jonathan"],
    "tagDescription": ["Financial Election Special Fund"],
    "tagDate": ["1904-09-27T00:00:00.000Z"]
  },
  "584": {
    "tagDescription": ["Intercolonial Ry."],
    "tagDate": ["1904-09-13T00:00:00.000Z"],
    "tagName": ["Talbot, O. E."]
  },
  "288": {
    "tagDescription": ["Routine business "],
    "tagDate": ["1904-09-01T00:00:00.000Z"],
    "tagName": ["Japan, Consul-General of"]
  },
  "153": {
    "tagDescription": ["Quebec colonization"],
    "tagDate": ["1904-08-20T00:00:00.000Z"],
    "tagName": ["Carufel, L. E."],
    "tagNotebook": ["LAURIER PAPERS"]
  },
  "839": {
    "tagName": ["McIntosh, J.A."],
    "tagDescription": ["Appointment"],
    "tagDate": ["1904-09-21T00:00:00.000Z"]
  },
  "7": {
    "tagNotebook": ["LAURIER PAPERS"],
    "tagName": ["Bureau, Jacques"],
    "tagDate": ["1904-08-14T00:00:00.000Z"],
    "tagDescription": ["Federal Election campaign (R.)"]
  },
  "471": {
    "tagName": ["Parent, George W."],
    "tagDescription": [
      "Dominion election - St. Laurent Co. Montreal (Encl.) (R.)"
    ],
    "tagDate": ["1904-09-10T00:00:00.000Z"]
  },
  "580": {
    "tagDescription": ["Dominion election (R.)"],
    "tagDate": ["1904-09-13T00:00:00.000Z"],
    "tagName": ["Thomson, E. W."]
  },
  "99": {
    "tagDescription": ["Appointment"],
    "tagDate": ["1904-08-18T00:00:00.000Z"],
    "tagName": ["Fisher, Sydney A."],
    "tagNotebook": ["LAURIER PAPERS"]
  },
  "1028": {
    "tagName": ["Rioux, Narcisse"],
    "tagDescription": ["Judgeship (R.)"],
    "tagDate": ["1904-09-27T00:00:00.000Z"]
  },
  "772": {
    "tagDescription": ["Dominion Exhibition at Halifax (Encls.) (R.)"],
    "tagDate": ["1904-09-20T00:00:00.000Z"],
    "tagName": ["Fielding, W.S."],
    "tagNotebook": ["LAURIER PAPERS"]
  },
  "499": {
    "tagDate": ["1904-09-12T00:00:00.000Z"],
    "tagDescription": [
      "Appointment to Construction Commission - Grand Trunk Pacific Railway of J. Butler"
    ],
    "tagName": ["Scott, Wm. J."]
  },
  "867": {
    "tagDescription": ["Claim re. Threadgold Commission (Encl.)"],
    "tagDate": ["1904-09-22T00:00:00.000Z"],
    "tagName": ["Prefontaine, Raymond Hon."]
  },
  "218": {
    "tagNotebook": ["LAURIER PAPERS"],
    "tagName": ["Ballantyne, C.C"],
    "tagDate": ["1904-08-26T00:00:00.000Z"],
    "tagDescription": ["Opening of new factory (R.)"]
  },
  "394": {
    "tagDescription": ["(R. only)"],
    "tagDate": ["1904-09-07T00:00:00.000Z"],
    "tagName": ["Macpherson, R.G."]
  },
  "1016": {
    "tagDate": ["1904-09-27T00:00:00.000Z"],
    "tagDescription": ["Finances, Special Election Fund (R.)"],
    "tagName": ["Lyall, P."]
  },
  "323": {
    "tagDescription": ["Introduction"],
    "tagDate": ["1904-09-04T00:00:00.000Z"],
    "tagName": ["Siegfried, Andre"]
  },
  "510": {
    "tagDescription": ["Appointment"],
    "tagDate": ["1904-09-12T00:00:00.000Z"],
    "tagName": ["Gauvreau, P. B."]
  },
  "426": {
    "tagDescription": ["Appointment (Encl.)"],
    "tagDate": ["1904-09-08T00:00:00.000Z"],
    "tagName": ["Prefontaine, Raymond Hon."]
  },
  "446": {
    "tagName": ["Holmes, Robert"],
    "tagDescription": ["Appointment (R.)"],
    "tagDate": ["1904-09-09T00:00:00.000Z"]
  },
  "179": {
    "tagName": ["Gilman, F. E."],
    "tagDescription": ["Interview (R.)"],
    "tagDate": ["1904-08-23T00:00:00.000Z"]
  },
  "814": {
    "tagName": ["St. Jean Baptiste Society"],
    "tagDate": ["1904-09-20T00:00:00.000Z"],
    "tagDescription": ["Means of celebrating national holiday"]
  },
  "507": {
    "tagName": ["Prefontaine, Raymond Hon."],
    "tagDate": ["1904-09-12T00:00:00.000Z"],
    "tagDescription": ["(Encl.)"]
  },
  "567": {
    "tagDescription": ["Camplaints: Cornwall Canal (R.)"],
    "tagDate": ["1904-09-13T00:00:00.000Z"],
    "tagName": ["Young, C.W."]
  },
  "863": {
    "tagName": ["Fraser, O.K."],
    "tagNotebook": ["LAURIER PAPERS"],
    "tagDate": ["1904-09-22T00:00:00.000Z"]
  },
  "266": {
    "tagNotebook": ["LAURIER PAPERS"],
    "tagName": ["Foran, J.K.", "Macpherson, R.G."],
    "tagDate": ["1904-08-30T00:00:00.000Z"],
    "tagDescription": ["Literary efforts (R.)", "Railway Commission"]
  },
  "327": {
    "tagNotebook": ["LAURIER PAPERS"],
    "tagName": ["Corbeil, O. Rev."],
    "tagDate": ["1904-09-04T00:00:00.000Z"],
    "tagDescription": ["Post Office: White Horse (Encl.) (R.)"]
  },
  "539": {
    "tagName": ["Latchford, F.R."],
    "tagDate": ["1904-09-12T00:00:00.000Z"],
    "tagDescription": ["Election"]
  },
  "374": {
    "tagName": ["McMullen, James Hon."],
    "tagDate": ["1904-09-07T00:00:00.000Z"],
    "tagDescription": ["Tariffs (Encl.) (R.)"]
  },
  "911": {
    "tagDescription": ["Montreal Symphony Orchestra (R.)"],
    "tagDate": ["1904-09-24T00:00:00.000Z"],
    "tagName": ["Pelletier, Victor"]
  },
  "198": {
    "tagName": ["Gautier, Fred E."],
    "tagDescription": ["Dundonald"],
    "tagDate": ["1904-08-24T00:00:00.000Z"]
  },
  "831": {
    "tagName": ["Pitt, Alex."],
    "tagDescription": ["Pontiac Co. politics"],
    "tagDate": ["1904-09-20T00:00:00.000Z"]
  },
  "63": {
    "tagDate": ["1904-08-17T00:00:00.000Z"],
    "tagDescription": ["Lord & Lady Minto (Encl.)"],
    "tagNotebook": ["LAURIER PAPERS"],
    "tagName": ["Clark, William M."]
  },
  "191": {
    "tagName": ["Filion, A."],
    "tagNotebook": ["LAURIER PAPERS"],
    "tagDescription": ["Lumber contracts"],
    "tagDate": ["1904-08-24T00:00:00.000Z"]
  },
  "783": {
    "tagDescription": ["Senatorship (Encl.)"],
    "tagDate": ["1904-09-20T00:00:00.000Z"],
    "tagName": ["Choquette, P. A."],
    "tagNotebook": ["LAURIER PAPERS"]
  },
  "289": {
    "tagName": ["Minto, Lord"],
    "tagDate": ["1904-09-01T00:00:00.000Z"],
    "tagDescription": ["His successor"]
  },
  "918": {
    "tagName": ["others", "Robitaille, L.S."],
    "tagDate": ["1904-09-24T00:00:00.000Z"],
    "tagDescription": ["Richelieu Co."]
  },
  "884": {
    "tagName": ["Scott, R.W."],
    "tagDate": ["1904-09-22T00:00:00.000Z"],
    "tagDescription": ["Printing Bureau"]
  },
  "206": {
    "tagName": ["Pacaud, Ernest Mrs."],
    "tagDate": ["1904-08-25T00:00:00.000Z"],
    "tagDescription": ["Appointment (R.)"]
  },
  "457": {
    "tagDescription": ["Liberal candidate, Two Mountains Co."],
    "tagDate": ["1904-09-10T00:00:00.000Z"],
    "tagName": ["Grothe, L. O."]
  },
  "627": {
    "tagName": ["Watson, R. J."],
    "tagDate": ["1904-09-15T00:00:00.000Z"],
    "tagDescription": ["Date of election (R.)"]
  },
  "1010": {
    "tagDescription": [
      "Wm. Pugsley: election to House of Commons; New Brunswick politics (R.)"
    ],
    "tagDate": ["1904-09-27T00:00:00.000Z"],
    "tagName": ["Coates, H. N."],
    "tagNotebook": ["LAURIER PAPERS"]
  },
  "10": {
    "tagDate": ["1904-08-15T00:00:00.000Z"],
    "tagDescription": ["Delegates"],
    "tagName": ["Tuberculoses, American Congress on -"]
  },
  "441": {
    "tagName": ["Stewart, C.J."],
    "tagDate": ["1904-09-09T00:00:00.000Z"],
    "tagDescription": ["Election campaign West (R.)"]
  },
  "707": {
    "tagName": ["Neyron, F."],
    "tagDescription": ["Application for homestead (Encl.) (R.)"],
    "tagDate": ["1904-09-17T00:00:00.000Z"]
  },
  "624": {
    "tagName": ["Hartman, C.W."],
    "tagDescription": ["Senatorhip (R.)"],
    "tagDate": ["1904-09-15T00:00:00.000Z"]
  },
  "454": {
    "tagName": ["Ellis, J. N."],
    "tagNotebook": ["LAURIER PAPERS"],
    "tagDescription": ["B. C. judgeship (R.)"],
    "tagDate": ["1904-09-10T00:00:00.000Z"]
  },
  "742": {
    "tagDescription": ["Interview"],
    "tagDate": ["1904-09-19T00:00:00.000Z"],
    "tagName": ["McIntosh, J.A."]
  },
  "887": {
    "tagName": ["Dessaulles, G.C."],
    "tagNotebook": ["LAURIER PAPERS"],
    "tagDescription": ["Sorel rally"],
    "tagDate": ["1904-09-23T00:00:00.000Z"]
  },
  "450": {
    "tagDescription": ["Dominion elections (R.)"],
    "tagDate": ["1904-09-09T00:00:00.000Z"],
    "tagName": ["Ross, George W."]
  },
  "909": {
    "tagNotebook": ["LAURIER PAPERS"],
    "tagName": ["Casgrain, J.P.B."],
    "tagDate": ["1904-09-24T00:00:00.000Z"],
    "tagDescription": ["Grand Trunk Pacific contract"]
  },
  "496": {
    "tagName": ["Mullarkey, J. P."],
    "tagDate": ["1904-09-12T00:00:00.000Z"],
    "tagDescription": ["Ottawa River Ry. (Encl.)"]
  },
  "55": {
    "tagName": ["Dickenson, H."],
    "tagNotebook": ["LAURIER PAPERS"],
    "tagDescription": ["Toronto Exhibition - Invitation (R.)"],
    "tagDate": ["1904-08-16T00:00:00.000Z"]
  },
  "767": {
    "tagName": ["Bruneau, A.A."],
    "tagNotebook": ["LAURIER PAPERS"],
    "tagDescription": ["Interviews"],
    "tagDate": ["1904-09-20T00:00:00.000Z"]
  },
  "261": {
    "tagDate": ["1904-08-30T00:00:00.000Z"],
    "tagDescription": ["Banquet-invitation (R.)"],
    "tagName": ["Knight, C. C."]
  },
  "836": {
    "tagDate": ["1904-09-21T00:00:00.000Z"],
    "tagDescription": ["P.E.I. judgeship (Encl.) (R.)"],
    "tagName": ["Hughes, J.J."]
  },
  "40": {
    "tagName": ["Mulock, Wm."],
    "tagDate": ["1904-08-15T00:00:00.000Z"],
    "tagDescription": ["Resignation"]
  },
  "916": {
    "tagName": ["Pringle, H."],
    "tagDate": ["1904-09-24T00:00:00.000Z"],
    "tagDescription": ["Senatorship (R.)"]
  },
  "739": {
    "tagDescription": ["Liberal party"],
    "tagDate": ["1904-09-18T00:00:00.000Z"],
    "tagName": ["Martineau, Joseph"]
  },
  "233": {
    "tagDate": ["1904-08-28T00:00:00.000Z"],
    "tagDescription": ["North West Rebellion"],
    "tagName": ["Thynne, J.G."]
  },
  "148": {
    "tagName": ["Transvaal, Premier of -"],
    "tagDate": ["1904-08-20T00:00:00.000Z"],
    "tagDescription": ["Inquiries re. gov't finance, etc."]
  },
  "196": {
    "tagDate": ["1904-08-24T00:00:00.000Z"],
    "tagDescription": ["Statue of Laurier"],
    "tagName": ["Morgan, Henry & Co."]
  },
  "583": {
    "tagName": ["Dansereau, A."],
    "tagNotebook": ["LAURIER PAPERS"],
    "tagDescription": ["Thanksgiving Day"],
    "tagDate": ["1904-09-13T00:00:00.000Z"]
  },
  "504": {
    "tagDate": ["1904-09-12T00:00:00.000Z"],
    "tagDescription": ["Atlantic fisheries (Encl.)"],
    "tagName": ["Prefontaine, Raymond Hon."]
  },
  "201": {
    "tagDescription": ["Transcontinental Ry."],
    "tagDate": ["1904-08-24T00:00:00.000Z"],
    "tagName": ["Wade, F. B."]
  },
  "150": {
    "tagDescription": ["Medal claim (R.)"],
    "tagDate": ["1904-08-20T00:00:00.000Z"],
    "tagName": ["Whitby, H. S. (Crimean & Indian Mutiny Veterans Assn.)"]
  },
  "817": {
    "tagDate": ["1904-09-21T00:00:00.000Z"],
    "tagDescription": ["Kelly vs. Journal Printing Co. (Encl.) (R.)"],
    "tagName": ["macCraken, Henderson and McDougall"]
  },
  "268": {
    "tagDate": ["1904-08-30T00:00:00.000Z"],
    "tagDescription": ["Transcontinental Commission (R.)"],
    "tagName": ["Wade, F. B."]
  },
  "1042": {
    "tagName": ["Torrance, John"],
    "tagDescription": ["Dominion steamship line (R.)"],
    "tagDate": ["1904-09-28T00:00:00.000Z"]
  }
}
