{
  "158": {
    "tagPerson": ["Turner", "Sewell, Jonathan", "Goodall"],
    "tagDate": ["1807-04-08T00:00:00.000Z"],
    "tagDescription": ["Goods sent"],
    "tagPlace": ["London"]
  },
  "283": {
    "tagDescription": ["Choice of constituency, Death of - Narcisse Panet"],
    "tagPerson": ["Sewell, Jonathan", "Sewell, Stephen"],
    "tagDate": ["1809-06-22T00:00:00.000Z"],
    "tagPlace": ["Montreal"]
  },
  "886": {
    "tagPlace": ["London"],
    "tagDescription": [
      "Suspension of Stephen Sewell on suspicion of having written libels, Sir George Prevost, General Drummond, Personal"
    ],
    "tagPerson": ["Sewell, Jonathan", "Salton, Gilbert"],
    "tagDate": ["1815-06-10T00:00:00.000Z"]
  },
  "627": {
    "tagPlace": ["Montreal"],
    "tagDescription": ["Impeachment, Sir George Prevost"],
    "tagDate": ["1814-02-24T00:00:00.000Z"],
    "tagPerson": ["Sewell, Jonathan", "Richardson, John"]
  },
  "706": {
    "tagDate": ["1814-05-12T00:00:00.000Z"],
    "tagPerson": ["Sewell, Jonathan", "Monk, James"],
    "tagDescription": ["Proposed visit to Quebec, Impeachment"],
    "tagPlace": ["Montreal"]
  },
  "809": {
    "tagPlace": ["Montreal"],
    "tagPerson": ["Sewell, Stephen", "Sewell, Jonathan"],
    "tagDate": ["1814-10-04T00:00:00.000Z"],
    "tagDescription": ["Defeat at Plattsburg New law society"]
  },
  "146": {
    "tagDescription": ["Financial R."],
    "tagDate": ["1806-11-11T00:00:00.000Z"],
    "tagPerson": ["Goodall", "Turner", "Sewell, Jonathan"],
    "tagPlace": ["Quebec"]
  },
  "374": {
    "tagDate": ["1811-07-12T00:00:00.000Z"],
    "tagPerson": ["Prevost, George Sir", "Gordon, Adam"],
    "tagDescription": ["Introducing Jonathan Sewell"],
    "tagPlace": ["Downing Street"]
  },
  "911": {
    "tagDescription": ["Personal"],
    "tagPerson": ["Sewell, Jonathan", "Bowen, Edward"],
    "tagDate": ["1815-06-26T00:00:00.000Z"],
    "tagPlace": ["Quebec"]
  },
  "670": {
    "tagDescription": ["Personal"],
    "tagPerson": ["Coltman, W.B.", "Sewell, Jonathan"],
    "tagDate": ["1814-03-29T00:00:00.000Z"],
    "tagPlace": ["Quebec"]
  },
  "700": {
    "tagPerson": ["Sewell, Jonathan", "Brenton, E.W."],
    "tagDate": ["1814-05-09T00:00:00.000Z"],
    "tagDescription": ["Papers relating to Assembly proceedings"],
    "tagPlace": ["Montreal"]
  },
  "715": {
    "tagPlace": ["Montreal"],
    "tagDescription": ["Returning papers"],
    "tagDate": ["1814-06-02T00:00:00.000Z"],
    "tagPerson": ["Sewell, Jonathan", "Richardson, John"]
  },
  "376": {
    "tagDescription": ["Financial, Ensign J. Sewell"],
    "tagPerson": ["Sewell, Jonathan", "Thomas Coutts and Co."],
    "tagDate": ["1811-08-15T00:00:00.000Z"],
    "tagPlace": ["London"]
  },
  "880": {
    "tagPlace": ["London"],
    "tagDescription": ["Interview"],
    "tagDate": ["1815-05-27T00:00:00.000Z"],
    "tagPerson": ["Sewell, Jonathan", "Putnam, J."]
  },
  "822": {
    "tagDescription": ["Personal"],
    "tagDate": ["1814-10-10T00:00:00.000Z"],
    "tagPerson": ["Somerville, W.", "Sewell, Jonathan"],
    "tagPlace": ["Edinburgh"]
  },
  "917": {
    "tagDescription": ["Arrangements for visit"],
    "tagPerson": ["Cockin, William", "Sewell, Jonathan"],
    "tagDate": ["1815-07-09T00:00:00.000Z"]
  },
  "643": {
    "tagDate": ["1814-03-10T00:00:00.000Z"],
    "tagPerson": ["Sewell, Jonathan", "Fletcher, J."],
    "tagDescription": ["Resolutions of Assembly"]
  },
  "54": {
    "tagPerson": ["Sewell, Jonathan", "Gale, S."],
    "tagDate": ["1804-11-27T00:00:00.000Z"],
    "tagDescription": ["Bourymarie siegneury"],
    "tagPlace": ["Farnham"],
    "tagName": ["Bourgmarie"]
  },
  "792": {
    "tagDescription": ["Memorandum of letter regarding impeachment R."],
    "tagPerson": ["Sewell, Jonathan", "Atcheson"],
    "tagDate": ["1814-08-12T00:00:00.000Z"]
  },
  "930": {
    "tagPerson": ["Sewell, Jonathan", "Putnam, J."],
    "tagDate": ["1815-08-12T00:00:00.000Z"],
    "tagDescription": ["Costs in impeachment proceedings, Duke of Kent"],
    "tagPlace": ["Cavendish Square"]
  },
  "252": {
    "tagDescription": ["Ward Chipman Jr., future prospects"],
    "tagPerson": ["Chipman, Ward", "Sewell, Jonathan"],
    "tagDate": ["1808-10-28T00:00:00.000Z"],
    "tagName": ["Chipman, Ward Jr."],
    "tagPlace": ["Saint John"]
  },
  "82": {
    "tagPerson": ["Sewell, Jonathan", "Sewell, Stephen"],
    "tagDate": ["1805-05-16T00:00:00.000Z"],
    "tagDescription": ["Personal, Case of King and Baribeau"],
    "tagPlace": ["Montreal"]
  },
  "865": {
    "tagDate": ["1815-02-20T00:00:00.000Z"],
    "tagPerson": ["Sewell, Jonathan", "Gibbon, A."],
    "tagDescription": ["Judges as Privy Councillors"]
  },
  "752": {
    "tagPlace": ["Quebec"],
    "tagDescription": [
      "Personal, Progress of war on the lakes-Sir George Prevost"
    ],
    "tagDate": ["1814-07-01T00:00:00.000Z"],
    "tagPerson": ["Sewell, Jonathan", "Smith, William"]
  },
  "713": {
    "tagPerson": ["Sewell, Jonathan", "Prevost, George Sir"],
    "tagDate": ["1814-06-01T00:00:00.000Z"],
    "tagDescription": ["Departure for England R."],
    "tagPlace": ["Quebec"]
  },
  "349": {
    "tagPlace": ["Saint John"],
    "tagDescription": ["Death of Thomas Aston Coffin, Bond, Ward Chipman Jr."],
    "tagDate": ["1810-08-13T00:00:00.000Z"],
    "tagPerson": ["Chipman, Ward", "Sewell, Jonathan"]
  },
  "446": {
    "tagPerson": ["Sewell, Jonathan", "Brenton, E.B."],
    "tagDate": ["1813-01-01T00:00:00.000Z"],
    "tagDescription": ["War news"]
  },
  "79": {
    "tagPlace": ["Vaudreuil"],
    "tagPerson": ["de Lotbiniere, Chartier", "Sewell, Jonathan"],
    "tagDate": ["1805-05-08T00:00:00.000Z"],
    "tagDescription": ["Legal, Militia"]
  },
  "560": {
    "tagPlace": ["Monk Ville"],
    "tagDescription": ["Unable to come to Quebec, War news"],
    "tagDate": ["1814-01-05T00:00:00.000Z"],
    "tagPerson": ["Sewell, Jonathan", "Monk, James"]
  },
  "395": {
    "tagDate": ["1812-08-19T00:00:00.000Z"],
    "tagPerson": ["Sewell, Jonathan", "Gordon, A."],
    "tagDescription": ["War news, R."],
    "tagPlace": ["Quebec"]
  },
  "817": {
    "tagPerson": ["Smith, William", "Sewell, Jonathan"],
    "tagDate": ["1814-10-08T00:00:00.000Z"],
    "tagDescription": ["Sir George Prevost, Loyal address, Personal"],
    "tagPlace": ["Quebec"],
    "tagName": ["Prevost, George Sir"]
  },
  "402": {
    "tagPerson": ["Sewell, Jonathan", "Brenton, E.B."],
    "tagDate": ["1812-09-01T00:00:00.000Z"],
    "tagDescription": ["Militia, Magistrates, Defences, Lower Canada"],
    "tagPlace": ["Montreal"]
  },
  "46": {
    "tagDate": ["1804-07-21T00:00:00.000Z"],
    "tagPerson": ["Sewell, Jonathan", "Sewell, Stephen"],
    "tagDescription": [
      "Death of Aunt, Election, Aulojo, Jordon and Taylor case"
    ],
    "tagPlace": ["Montreal"]
  },
  "196": {
    "tagDate": ["1808-03-04T00:00:00.000Z"],
    "tagPerson": ["Pyke, George", "Sewell, Jonathan"],
    "tagDescription": [
      "Claim on Indians to part of seigneury of La Prairie, Encl."
    ],
    "tagPlace": ["Quebec"]
  },
  "836": {
    "tagPlace": ["Montreal"],
    "tagPerson": ["Sewell, Jonathan", "Sewell, Stephen"],
    "tagDate": ["1814-11-03T00:00:00.000Z"],
    "tagDescription": [
      "Rules of practice, Sir George Prevost, Plattsburg, Capt., Dounie, War news, Financial"
    ]
  },
  "92": {
    "tagPlace": ["Montreal"],
    "tagDate": ["1805-08-26T00:00:00.000Z"],
    "tagPerson": ["Sewell, Jonathan", "Sewell, Stephen"],
    "tagDescription": ["Account"]
  },
  "371": {
    "tagDescription": ["Financial"],
    "tagDate": ["1811-04-27T00:00:00.000Z"],
    "tagPerson": ["Goodall", "Turner", "Sewell, Jonathan"],
    "tagPlace": ["London"]
  },
  "914": {
    "tagPlace": ["London"],
    "tagDescription": ["Impeachment charges denied"],
    "tagDate": ["1815-07-05T00:00:00.000Z"],
    "tagPerson": ["Sewell, Jonathan", "Salton, Gilbert"]
  },
  "564": {
    "tagPerson": ["Monk, James", "Sewell, Jonathan"],
    "tagDate": ["1814-01-30T00:00:00.000Z"],
    "tagDescription": [
      "Suit, Disloyalty, Sir George Prevost, Appointment of Judges to Legislative Council"
    ],
    "tagPlace": ["Monk Ville"]
  },
  "154": {
    "tagDescription": ["Napoleonic war, Personal"],
    "tagPerson": ["Scott, James", "Sewell, Jonathan"],
    "tagDate": ["1807-02-06T00:00:00.000Z"],
    "tagPlace": ["Boston"]
  },
  "496": {
    "tagPlace": ["Montreal"],
    "tagDescription": [
      "Proclamation, Replacements for Messrs., Young and Buchesnay"
    ],
    "tagDate": ["1813-10-19T00:00:00.000Z"],
    "tagPerson": ["Sewell, Jonathan", "Ryland, H.W."]
  },
  "767": {
    "tagPerson": ["Smith, William", "Sewell, Jonathan"],
    "tagDate": ["1814-07-20T00:00:00.000Z"],
    "tagDescription": ["War news, Appointment to Executive Council"],
    "tagPlace": ["Quebec"]
  },
  "320": {
    "tagDescription": ["Present situation of Canada (draft) R."],
    "tagPerson": ["Craig, James Sir", "Sewell, Stephen"],
    "tagDate": ["1810-05-01T00:00:00.000Z"]
  },
  "624": {
    "tagDescription": ["Impeachment"],
    "tagPerson": ["Coltman, W.B.", "Sewell, Jonathan"],
    "tagDate": ["1814-02-22T00:00:00.000Z"]
  },
  "207": {
    "tagPlace": ["Montreal"],
    "tagDescription": ["Legal"],
    "tagDate": ["1808-05-05T00:00:00.000Z"],
    "tagPerson": ["Ross, David", "Sewell, Jonathan"]
  },
  "61": {
    "tagDescription": [
      "Draft report on action against Louis Gugy to determine the rear line of the fief of Grand Pre R. only"
    ],
    "tagDate": ["1805-02-22T00:00:00.000Z"],
    "tagPerson": ["Milnes, Robert Shore", "Sewell, Jonathan"]
  },
  "235": {
    "tagPlace": ["Fredericton"],
    "tagName": ["Chipman, Ward Jr."],
    "tagPerson": ["Chipman, Ward", "Sewell, Jonathan"],
    "tagDate": ["1808-07-08T00:00:00.000Z"],
    "tagDescription": [
      "Ward Chipman Jr., Aspirations to appointment as chief justice"
    ]
  },
  "587": {
    "tagPlace": ["Montreal"],
    "tagDate": ["1814-02-07T00:00:00.000Z"],
    "tagPerson": ["Sewell, Jonathan", "Richardson, John"],
    "tagDescription": ["Resolutions and action to be taken"]
  },
  "174": {
    "tagPlace": ["Quebec"],
    "tagDate": ["1807-10-26T00:00:00.000Z"],
    "tagPerson": ["Turner", "Sewell, Jonathan", "Goodall"],
    "tagDescription": ["Financial R."]
  },
  "265": {
    "tagDate": ["1808-12-07T00:00:00.000Z"],
    "tagPerson": [
      "Christie, Robert",
      "Sewell, Jonathan",
      "Gaspe, P.",
      "Perrault, J. Jr."
    ],
    "tagDescription": ["Patronage of Societe Litteraire"],
    "tagPlace": ["Quebec"]
  },
  "691": {
    "tagPerson": ["Sewell, Jonathan", "Irvine, James"],
    "tagDate": ["1814-04-21T00:00:00.000Z"],
    "tagDescription": ["Rules of Practice in appeal"]
  },
  "89": {
    "tagDescription": [
      "Negotiations regarding his appointment as Chief Justice"
    ],
    "tagDate": ["1805-08-04T00:00:00.000Z"],
    "tagPerson": ["Sewell, Jonathan", "Coffin, Thomas Aston"],
    "tagPlace": ["London"]
  },
  "346": {
    "tagDescription": ["Land, His attendance at Quebec"],
    "tagDate": ["1810-08-09T00:00:00.000Z"],
    "tagPerson": ["Sewell, Stephen", "Sewell, Jonathan"],
    "tagPlace": ["Montreal"]
  },
  "132": {
    "tagDescription": ["Legal, Napoleonic war"],
    "tagDate": ["1806-03-31T00:00:00.000Z"],
    "tagPerson": ["Sewell, Stephen", "Sewell, Jonathan"],
    "tagPlace": ["Montreal"]
  },
  "127": {
    "tagPlace": ["Quebec"],
    "tagDescription": ["Personal"],
    "tagDate": ["1806-03-10T00:00:00.000Z"],
    "tagPerson": ["Sewell, Jonathan", "Sewell, Harriet"]
  },
  "675": {
    "tagDate": ["1814-04-09T00:00:00.000Z"],
    "tagPerson": ["Monk, James", "Sewell, Jonathan"],
    "tagDescription": ["Impeachment"],
    "tagPlace": ["Montreal"]
  },
  "421": {
    "tagPlace": ["Montreal"],
    "tagDescription": ["War"],
    "tagPerson": ["Sewell, Jonathan", "Brenton, E.B."],
    "tagDate": ["1812-11-06T00:00:00.000Z"]
  },
  "646": {
    "tagPlace": ["Quebec"],
    "tagDescription": ["Leave, R."],
    "tagDate": ["1814-03-12T00:00:00.000Z"],
    "tagPerson": ["Sewell, Jonathan", "Brenton, E.B."]
  },
  "170": {
    "tagDescription": ["Financial"],
    "tagDate": ["1807-07-30T00:00:00.000Z"],
    "tagPerson": ["Goodall", "Sewell, Jonathan", "Turner"]
  },
  "210": {
    "tagPerson": ["Coffin, V.", "Sewell, Jonathan"],
    "tagDate": ["1808-05-09T00:00:00.000Z"],
    "tagDescription": ["Memorial regarding recruiting methods, Election"],
    "tagPlace": ["Riviere du Loup"]
  },
  "722": {
    "tagDescription": ["Personal"],
    "tagDate": ["1814-06-04T00:00:00.000Z"],
    "tagPerson": ["Richardson, John", "Sewell, Jonathan"],
    "tagPlace": ["Montreal"]
  },
  "800": {
    "tagPlace": ["Downing Street"],
    "tagDescription": ["Appointment with Lord Bathurst"],
    "tagDate": ["1814-08-20T00:00:00.000Z"],
    "tagPerson": ["Sewell, Jonathan", "Gordon, Adam"]
  },
  "935": {
    "tagDate": ["1815-08-18T00:00:00.000Z"],
    "tagPerson": ["Bowen, Edward", "Sewell, Jonathan"],
    "tagDescription": [
      "Personal, Jurisdiction of courts, Money voted to Sir George Prevost, Case of Francis Ansell"
    ],
    "tagPlace": ["Quebec"]
  },
  "397": {
    "tagPerson": ["Brenton, E.B.", "Sewell, Jonathan"],
    "tagDate": ["1812-08-25T00:00:00.000Z"],
    "tagDescription": ["Capture of Schooner, Amherstburg, Detroit"],
    "tagPlace": ["Montreal"]
  },
  "43": {
    "tagPerson": ["Sewell, Jonathan", "Doyle, William"],
    "tagDate": ["1804-04-13T00:00:00.000Z"],
    "tagDescription": [
      "Personal, George Doyle William Smith's engagement, Defences in Ireland"
    ],
    "tagPlace": ["Ballinasloe"],
    "tagName": [" "]
  },
  "709": {
    "tagDescription": ["Approving defence of rules in appeal"],
    "tagPerson": ["Richardson, John", "Sewell, Jonathan"],
    "tagDate": ["1814-05-21T00:00:00.000Z"]
  },
  "697": {
    "tagPlace": ["Quebec"],
    "tagDate": ["1814-05-05T00:00:00.000Z"],
    "tagPerson": ["Coltman, William B.", "Sewell, Jonathan"],
    "tagDescription": ["Assembly resolutions, Appeals"]
  },
  "806": {
    "tagPlace": ["Montreal"],
    "tagPerson": ["Monk, James", "Sewell, Jonathan"],
    "tagDate": ["1814-10-03T00:00:00.000Z"],
    "tagDescription": ["Conduct of war"]
  },
  "883": {
    "tagPlace": ["Quebec"],
    "tagDescription": [
      "Judges' salaries, Court cases, Court House addition, Personal"
    ],
    "tagDate": ["1815-06-01T00:00:00.000Z"],
    "tagPerson": ["Bowen, Edward", "Sewell, Jonathan"]
  },
  "738": {
    "tagDescription": [
      "Deposition authenticating signature of William Lindsay on letter to E.B. Brenton relating to Impeachment"
    ],
    "tagPerson": ["Brenton, E.B.", "Green, William"],
    "tagDate": ["1814-06-14T00:00:00.000Z"],
    "tagPlace": ["Quebec"]
  },
  "470": {
    "tagPlace": ["Montreal"],
    "tagDate": ["1813-04-05T00:00:00.000Z"],
    "tagPerson": ["Sewell, Jonathan", "Sewell, Stephen"],
    "tagDescription": [
      "Monk's questions relating to government and the role of the judiciary"
    ]
  },
  "786": {
    "tagDescription": ["Privileges of Legislative Council, Libel"],
    "tagDate": ["1814-08-02T00:00:00.000Z"],
    "tagPerson": ["Bowen, Edward", "Sewell, Jonathan"],
    "tagPlace": ["Quebec"]
  },
  "703": {
    "tagPlace": ["Monk Ville"],
    "tagName": ["Sewell"],
    "tagPerson": ["Monk, James", "Sewell, Jonathan"],
    "tagDate": ["1814-05-09T00:00:00.000Z"],
    "tagDescription": ["Sewell's trip to England"]
  },
  "673": {
    "tagDescription": ["Personal, R."],
    "tagDate": ["1814-03-30T00:00:00.000Z"],
    "tagPerson": ["Coltman, W.B.", "Sewell, Jonathan"],
    "tagPlace": ["Quebec"]
  },
  "287": {
    "tagDescription": ["Personal"],
    "tagPerson": ["Sewell, Stephen", "Sewell, Jonathan"],
    "tagDate": ["1809-07-03T00:00:00.000Z"],
    "tagPlace": ["Montreal"]
  },
  "694": {
    "tagPlace": ["Montreal"],
    "tagDate": ["1814-04-25T00:00:00.000Z"],
    "tagPerson": ["Sewell, Jonathan", "Monk, James"],
    "tagDescription": ["Rights of the Courts, Personal"]
  },
  "648": {
    "tagPlace": ["Three Rivers"],
    "tagDescription": ["Leave, Army bill"],
    "tagPerson": ["Sewell, Jonathan", "Monk, James"],
    "tagDate": ["1814-03-15T00:00:00.000Z"]
  },
  "52": {
    "tagPerson": ["Colton, Charles", "Sewell, Jonathan"],
    "tagDate": ["1804-09-21T00:00:00.000Z"],
    "tagDescription": ["Requesting further information R."],
    "tagPlace": ["Quebec"]
  },
  "453": {
    "tagDescription": [
      "Relationship between the bench and Council, Impeachment"
    ],
    "tagPerson": ["Sewell, Jonathan", "Monk, James"],
    "tagDate": ["1813-01-22T00:00:00.000Z"],
    "tagPlace": ["Monk Ville"]
  },
  "412": {
    "tagPerson": ["Brenton, E.B.", "Sewell, Jonathan"],
    "tagDate": ["1812-10-13T00:00:00.000Z"],
    "tagDescription": ["Petitions sent, - Bedard, War"],
    "tagPlace": ["Montreal"]
  },
  "711": {
    "tagDescription": ["Approving defences of rules in appeal"],
    "tagPerson": ["Sewell, Jonathan", "Mountain, Jacob (Bishop of Quebec)"],
    "tagDate": ["1814-05-28T00:00:00.000Z"]
  },
  "354": {
    "tagPlace": ["Quebec"],
    "tagDate": ["1810-08-17T00:00:00.000Z"],
    "tagPerson": ["Craig, James Sir"],
    "tagDescription": [
      "Report on memorial of Indians of La Jeune Lorrette, R. only"
    ]
  },
  "654": {
    "tagPlace": ["Quebec"],
    "tagDescription": ["Impeachment, Request for leave of absence, R."],
    "tagPerson": ["Bathurst, Lord", "Sewell, Jonathan"],
    "tagDate": ["1814-03-21T00:00:00.000Z"]
  },
  "218": {
    "tagName": ["Chipman, Ward Jr."],
    "tagPlace": ["Fredericton"],
    "tagDescription": ["Ward Chipman Jr."],
    "tagPerson": ["Sewell, Jonathan", "Chipman, Ward"],
    "tagDate": ["1808-05-24T00:00:00.000Z"]
  },
  "499": {
    "tagPlace": ["Kingston"],
    "tagDescription": ["Threat of American invasion. Defences"],
    "tagDate": ["1813-10-22T00:00:00.000Z"],
    "tagPerson": ["Plenderleath, Charles Lt.-Col.", "Sewell, Jonathan"]
  },
  "477": {
    "tagPlace": ["Kingston"],
    "tagDescription": ["Attack on Sackett's Harbour, York"],
    "tagPerson": ["Sewell, Jonathan", "Brenton, E.B."],
    "tagDate": ["1813-06-01T00:00:00.000Z"]
  },
  "178": {
    "tagDate": ["1807-12-31T00:00:00.000Z"],
    "tagPerson": ["Craig, James Sir", "Sewell, Jonathan"],
    "tagDescription": [
      "Draft report of proceedings in actions ordered against the debtors of the Jesuits estate, R. only"
    ],
    "tagPlace": ["Quebec"]
  },
  "833": {
    "tagPlace": ["Quebec"],
    "tagPerson": ["Sewell, Jonathan", "Bowen, Edward"],
    "tagDate": ["1814-10-31T00:00:00.000Z"],
    "tagDescription": ["War news, Library, Judges' Salaries"]
  },
  "772": {
    "tagDate": ["1814-08-01T00:00:00.000Z"],
    "tagPerson": ["Executive Council", "Prince Regent"],
    "tagDescription": [
      "Petition for relief against proceedings of the Assembly"
    ]
  },
  "48": {
    "tagPlace": ["Boston"],
    "tagDescription": ["Personal, Prince of Wales, Napoleonic threat"],
    "tagDate": ["1804-09-18T00:00:00.000Z"],
    "tagPerson": ["Scott, James", "Sewell, Jonathan"]
  },
  "569": {
    "tagDescription": ["Defence to resolutions of assembly, R."],
    "tagDate": ["1814-02-01T00:00:00.000Z"],
    "tagPerson": ["Richardson, John", "Sewell, Jonathan"]
  },
  "580": {
    "tagDate": ["1814-02-02T00:00:00.000Z"],
    "tagPerson": ["Monk, James", "Sewell, Jonathan"],
    "tagDescription": ["Bankruptcy"],
    "tagPlace": ["Monk Ville"]
  },
  "861": {
    "tagPerson": ["Bowen, Edward", "Sewell, Jonathan"],
    "tagDate": ["1815-01-30T00:00:00.000Z"],
    "tagDescription": [
      "Financial, Illness of Janet Smith, James Stuart, Personal, Political activities"
    ],
    "tagPlace": ["Quebec"]
  },
  "919": {
    "tagPerson": ["Bathurst, Lord", "Drummond, Gordon Sir"],
    "tagDate": ["1815-07-12T00:00:00.000Z"],
    "tagDescription": ["Acquittal of Sewell and Monk, Sir James Craig"],
    "tagPlace": ["Downing Street"]
  },
  "868": {
    "tagDate": ["1815-02-28T00:00:00.000Z"],
    "tagPerson": ["Sewell, Jonathan", "Bowen, Edward"],
    "tagDescription": [
      "Provincial Parliament proceedings, Dispute regarding representation, from Caspe, Personal"
    ],
    "tagPlace": ["Quebec"]
  },
  "730": {
    "tagPlace": ["Montreal"],
    "tagPerson": ["Richardson, John", "Sewell, Jonathan"],
    "tagDate": ["1814-06-11T00:00:00.000Z"],
    "tagDescription": ["Papers received"]
  },
  "503": {
    "tagDescription": ["War news"],
    "tagDate": ["1813-11-22T00:00:00.000Z"],
    "tagPerson": ["Sewell, Jonathan", "Brenton, E.B."],
    "tagPlace": ["Montreal"]
  },
  "77": {
    "tagPerson": ["Sewell, Stephen", "Sewell, Jonathan"],
    "tagDate": ["1805-05-06T00:00:00.000Z"],
    "tagDescription": ["Legal, Death of Chief Justice, Personal"],
    "tagPlace": ["Montreal"]
  },
  "95": {
    "tagDescription": ["Personal"],
    "tagPerson": ["Sewell, Jonathan", "Sewell, Harriet"],
    "tagDate": ["1805-09-02T00:00:00.000Z"],
    "tagPlace": ["Montreal"]
  },
  "36": {
    "tagPlace": ["Montreal"],
    "tagDescription": ["Personal, Palmura Esther Syno"],
    "tagPerson": ["Sewell, Harriet", "Sewell, Jonathan"],
    "tagDate": ["1804-03-05T00:00:00.000Z"]
  },
  "584": {
    "tagDescription": [
      "Resolutions regarding courts of law, Pierre Bedard, R."
    ],
    "tagDate": ["1814-02-03T00:00:00.000Z"],
    "tagPerson": ["Monk, James", "Sewell, Jonathan"],
    "tagPlace": ["Quebec"]
  },
  "124": {
    "tagPlace": ["Quebec"],
    "tagPerson": ["Sewell, Harriet", "Sewell, Jonathan"],
    "tagDate": ["1806-03-05T00:00:00.000Z"],
    "tagDescription": ["Personal"]
  },
  "302": {
    "tagName": ["Amyot, Mr."],
    "tagPlace": ["Downing Street"],
    "tagDescription": ["Mr. Amyot"],
    "tagPerson": ["Sewell, Jonathan", "Gordon, Adam"],
    "tagDate": ["1810-01-09T00:00:00.000Z"]
  },
  "717": {
    "tagPlace": ["Montreal"],
    "tagDescription": ["Accommodation aboard Phoenix, Thanks"],
    "tagDate": ["1814-06-03T00:00:00.000Z"],
    "tagPerson": ["Brenton, E.B.", "Sewell, Jonathan"]
  },
  "509": {
    "tagDescription": ["Letters and diary relating to mission in Chile"],
    "tagPerson": ["Millyar, James"],
    "tagDate": ["1814-01-01T00:00:00.000Z"]
  },
  "193": {
    "tagPlace": ["Montreal"],
    "tagDate": ["1808-02-29T00:00:00.000Z"],
    "tagPerson": ["Sewell, Stephen", "Sewell, Jonathan"],
    "tagDescription": ["Business"]
  },
  "387": {
    "tagPerson": ["Provost, C.A.", "Sewell, Jonathan"],
    "tagDate": ["1812-07-16T00:00:00.000Z"],
    "tagDescription": ["Requesting permission to attend house"]
  },
  "290": {
    "tagPlace": ["Saint John"],
    "tagDate": ["1809-08-15T00:00:00.000Z"],
    "tagPerson": ["Sewell, Jonathan", "Chipman, Ward"],
    "tagDescription": [
      "Appointment to Supreme Court of New Brunswick, Ward Chipman Jr., Thomas Aston Coffin"
    ]
  },
  "311": {
    "tagDescription": ["Funeral of Esther Sewell, His absence from Quebec"],
    "tagDate": ["1810-01-25T00:00:00.000Z"],
    "tagPerson": ["Sewell, Stephen", "Sewell, Jonathan"],
    "tagPlace": ["Montreal"]
  },
  "442": {
    "tagPerson": ["Plenderleath, Charles", "Sewell, Jonathan"],
    "tagDate": ["1813-01-01T00:00:00.000Z"],
    "tagDescription": ["Military news"]
  },
  "296": {
    "tagPlace": ["Montreal"],
    "tagDate": ["1809-11-19T00:00:00.000Z"],
    "tagPerson": ["Sewell, Stephen", "Sewell, Jonathan"],
    "tagDescription": ["Health of Esther Sewell"]
  },
  "223": {
    "tagDescription": [
      "Report on claim of Indians of Caugnawagha to land within limits of seigneurie of La Prairie de la Magdaleine, R. only"
    ],
    "tagDate": ["1808-06-22T00:00:00.000Z"],
    "tagPerson": ["Sewell, Jonathan", "Craig, James Sir"],
    "tagPlace": ["Quebec"]
  },
  "899": {
    "tagDescription": [
      "State of Government in the province, Legal cases, Municipal police, Houses of industry and correction, Judges' salaries"
    ],
    "tagPerson": ["McCord, Thomas", "Sewell, Jonathan"],
    "tagDate": ["1815-06-26T00:00:00.000Z"],
    "tagPlace": ["Montreal"]
  },
  "748": {
    "tagDescription": ["Defence of judiciary"],
    "tagDate": ["1814-06-29T00:00:00.000Z"],
    "tagPerson": ["Monk, James", "Sewell, Jonathan"],
    "tagPlace": ["Montreal"]
  },
  "794": {
    "tagPlace": ["Quebec"],
    "tagPerson": ["Smith, William", "Sewell, Jonathan"],
    "tagDate": ["1814-08-15T00:00:00.000Z"],
    "tagDescription": [
      "Arrival of General Kempt, Sir George Prevost, War news, Appointment to council"
    ]
  },
  "467": {
    "tagName": ["Sewell, John"],
    "tagPerson": ["Plenderleath, Charles", "Sewell, Jonathan"],
    "tagDate": ["1813-02-21T00:00:00.000Z"],
    "tagDescription": ["John Sewell, Defences on Niagara frontier"]
  },
  "101": {
    "tagPlace": ["Haverhill, N.H."],
    "tagDescription": ["Legal"],
    "tagDate": ["1805-09-17T00:00:00.000Z"],
    "tagPerson": ["Porter, Asa", "Sewell, Jonathan"]
  },
  "723": {
    "tagDate": ["1814-06-06T00:00:00.000Z"],
    "tagPerson": ["Monk, James", "Sewell, Jonathan"],
    "tagDescription": ["Impeachment"],
    "tagPlace": ["Montreal"]
  },
  "229": {
    "tagDate": ["1808-06-22T00:00:00.000Z"],
    "tagPerson": ["Sewell, Jonathan", "Craig, James Sir"],
    "tagDescription": [
      "Report on claim of Iroqusis to seigneury of Lake of Two Mountains, Encl., R. only"
    ],
    "tagPlace": ["Quebec"]
  },
  "20": {
    "tagDescription": [
      "Visit to England, Duke of Rent, (First part of letter missing)"
    ],
    "tagDate": ["1803-11-01T00:00:00.000Z"],
    "tagPerson": ["Sewell, Jonathan", "Smith, William"]
  },
  "135": {
    "tagDate": ["1806-09-05T00:00:00.000Z"],
    "tagPerson": ["Coffin, Thomas Aston", "Sewell, Jonathan"],
    "tagDescription": ["Quebec fleet, Financial"]
  },
  "142": {
    "tagDate": ["1806-10-06T00:00:00.000Z"],
    "tagPerson": ["Sewell, Harriet", "Sewell, Jonathan"],
    "tagDescription": ["Personal"],
    "tagPlace": ["Quebec"]
  },
  "433": {
    "tagDescription": ["Defences, Queenstown"],
    "tagDate": ["1812-11-16T00:00:00.000Z"],
    "tagPerson": ["Sewell, Jonathan", "Brenton, E.B."],
    "tagPlace": ["Montreal"]
  },
  "762": {
    "tagPerson": ["Sewell, Jonathan", "Sewell, Stephen"],
    "tagDate": ["1814-07-14T00:00:00.000Z"],
    "tagDescription": [
      "Personal, Progress of war in Upper Canada, Battle of Fort Erie"
    ],
    "tagPlace": ["Montreal"]
  },
  "630": {
    "tagPerson": ["Monk, James", "Sewell, Jonathan"],
    "tagDate": ["1814-02-25T00:00:00.000Z"],
    "tagDescription": ["Impeachment"],
    "tagPlace": ["Montreal"]
  },
  "70": {
    "tagPerson": ["Sewell, Jonathan", "Sewell, Stephen"],
    "tagDate": ["1805-04-01T00:00:00.000Z"],
    "tagDescription": ["Parishes and the power of the bishop in France R."]
  },
  "928": {
    "tagDate": ["1815-08-07T00:00:00.000Z"],
    "tagPerson": ["Sewell, Jonathan", "Cockin, William"],
    "tagDescription": ["Personal"]
  },
  "107": {
    "tagPerson": ["Chipman, Ward", "Sewell, Jonathan"],
    "tagDate": ["1805-11-16T00:00:00.000Z"],
    "tagDescription": ["Education of Ward Chipman Jr."],
    "tagPlace": ["Saint John"]
  },
  "878": {
    "tagPlace": ["House of Commons"],
    "tagPerson": ["Sewell, Jonathan", "Keene, W."],
    "tagDate": ["1815-05-19T00:00:00.000Z"],
    "tagDescription": ["Conversation with Lord Bathurst, Emigration scheme"]
  },
  "636": {
    "tagPerson": ["Sewell, Jonathan", "Monk, James"],
    "tagDate": ["1814-03-07T00:00:00.000Z"],
    "tagDescription": ["Impeachment"],
    "tagPlace": ["Montreal"]
  },
  "688": {
    "tagPerson": ["Monk, James", "Sewell, Jonathan"],
    "tagDate": ["1814-04-18T00:00:00.000Z"],
    "tagDescription": ["Acknowledgment of letters"],
    "tagPlace": ["Montreal"]
  },
  "26": {
    "tagDate": ["1804-01-30T00:00:00.000Z"],
    "tagPerson": ["Sewell, Stephen", "Sewell, Jonathan"],
    "tagDescription": ["Personal"],
    "tagPlace": ["Montreal"]
  },
  "381": {
    "tagDescription": ["War news"],
    "tagPerson": ["Brenton, E.B.", "Sewell, Jonathan"],
    "tagDate": ["1812-01-01T00:00:00.000Z"]
  },
  "164": {
    "tagDate": ["1807-07-17T00:00:00.000Z"],
    "tagPerson": ["Sewell, Jonathan", "Dunn, Thomas"],
    "tagDescription": [
      "Draft report on necessity of letters of ratification of grants during the French regime, R. only"
    ]
  },
  "746": {
    "tagDescription": ["Increase in salary"],
    "tagDate": ["1814-06-16T00:00:00.000Z"],
    "tagPerson": ["Bowen, Edward", "Sewell, Jonathan"]
  },
  "98": {
    "tagPlace": ["Three Rivers"],
    "tagDescription": ["Personal"],
    "tagPerson": ["Sewell, Harriet", "Sewell, Jonathan"],
    "tagDate": ["1805-09-13T00:00:00.000Z"]
  },
  "115": {
    "tagPlace": ["Montreal"],
    "tagDate": ["1806-02-20T00:00:00.000Z"],
    "tagPerson": ["Sewell, Jonathan", "Sewell, Stephen"],
    "tagDescription": ["Death of daughter"]
  },
  "622": {
    "tagDescription": [
      "Report of Assembly, Summoning of Legislative Council, War news"
    ],
    "tagDate": ["1814-02-21T00:00:00.000Z"],
    "tagPerson": ["Richardson, John", "Sewell, Jonathan"],
    "tagPlace": ["Montreal"]
  },
  "590": {
    "tagDate": ["1814-02-07T00:00:00.000Z"],
    "tagPerson": ["Monk, James", "Richardson, John"],
    "tagDescription": ["Impeachment, Memorial from judges"],
    "tagPlace": ["Monk Ville"]
  },
  "32": {
    "tagPlace": ["Montreal"],
    "tagName": ["Houchette, Joseph"],
    "tagPerson": ["Sewell, Jonathan", "Sewell, Harriet"],
    "tagDate": ["1804-03-01T00:00:00.000Z"],
    "tagDescription": ["Joseph Houchette, Personal"]
  },
  "298": {
    "tagPerson": ["Sewell, Jonathan", "Sewell, Stephen"],
    "tagDate": ["1809-11-23T00:00:00.000Z"],
    "tagDescription": ["Health of Esther Sewell"],
    "tagPlace": ["Montreal"]
  },
  "244": {
    "tagDescription": ["Account"],
    "tagDate": ["1808-09-28T00:00:00.000Z"],
    "tagPerson": ["Sewell, Jonathan", "Thomas Coutts and Co."],
    "tagPlace": ["London"]
  },
  "610": {
    "tagPlace": ["Monk Ville"],
    "tagDate": ["1814-02-14T00:00:00.000Z"],
    "tagPerson": ["Sewell, Jonathan", "Monk, James"],
    "tagDescription": ["Impeachment"]
  },
  "492": {
    "tagDescription": [
      "Lake fever, Military news, System of promotion, Storey Creek, Harvey"
    ],
    "tagPerson": ["Sewell, Jonathan", "Plenderleath, Charles Lt.-Col."],
    "tagDate": ["1813-09-03T00:00:00.000Z"]
  },
  "240": {
    "tagDescription": ["Congratulations on appointment as chief justice"],
    "tagDate": ["1808-08-25T00:00:00.000Z"],
    "tagPerson": ["Sewell, Jonathan", "Ross, David"],
    "tagPlace": ["Montreal"]
  },
  "596": {
    "tagPlace": ["Monk Ville"],
    "tagDescription": ["Impeachment"],
    "tagDate": ["1814-02-09T00:00:00.000Z"],
    "tagPerson": ["Monk, James", "Sewell, Jonathan"]
  },
  "160": {
    "tagPlace": ["Quebec"],
    "tagDate": ["1807-07-09T00:00:00.000Z"],
    "tagPerson": ["Sewell, Jonathan", "Ogden, J.L."],
    "tagDescription": ["Financial R."]
  },
  "485": {
    "tagPlace": ["Kingston"],
    "tagDescription": ["Niagara frontier, Naval force, Action near Gananoque"],
    "tagPerson": ["Brenton, E.B.", "Sewell, Jonathan"],
    "tagDate": ["1813-07-24T00:00:00.000Z"]
  },
  "104": {
    "tagPlace": ["Lotbiniere"],
    "tagDate": ["1805-09-25T00:00:00.000Z"],
    "tagPerson": ["de Lotbiniere, Chartier", "Sewell, Jonathan"],
    "tagDescription": ["Employment of schoolmaster"]
  },
  "845": {
    "tagPerson": ["Sewell, Jonathan", "Monk, James"],
    "tagDate": ["1814-11-04T00:00:00.000Z"],
    "tagDescription": [
      "Government of colony, Capt., Pring, Judges' allowances"
    ],
    "tagPlace": ["Monk Ville"]
  },
  "827": {
    "tagDate": ["1814-10-28T00:00:00.000Z"],
    "tagPerson": ["Richardson, John", "Sewell, Jonathan"],
    "tagDescription": [
      "War news, Sir George Prevost, Address to Prince Regent"
    ],
    "tagPlace": ["Montreal"]
  },
  "380": {
    "tagPlace": ["Montreal"],
    "tagDescription": ["Apples"],
    "tagDate": ["1811-09-19T00:00:00.000Z"],
    "tagPerson": ["Sewell, Jonathan", "Ross, David"]
  },
  "363": {
    "tagPerson": ["Sewell, Jonathan", "Cartwright, James"],
    "tagDate": ["1810-10-01T00:00:00.000Z"],
    "tagDescription": ["Personal"],
    "tagPlace": ["Montreal"]
  },
  "797": {
    "tagDescription": ["War news, Personal"],
    "tagPerson": ["Bowen, Edward", "Sewell, Jonathan"],
    "tagDate": ["1814-08-17T00:00:00.000Z"],
    "tagPlace": ["Quebec"]
  },
  "924": {
    "tagPlace": ["Cavendish Square"],
    "tagPerson": ["Putnam, J.", "Sewell, Jonathan"],
    "tagDate": ["1815-07-31T00:00:00.000Z"],
    "tagDescription": ["Papers, Impeachment charges denied, Duke of Kent"]
  },
  "118": {
    "tagDescription": ["Personal, Napoleon"],
    "tagDate": ["1806-03-03T00:00:00.000Z"],
    "tagPerson": ["Sewell, Harriet", "Sewell, Jonathan"],
    "tagPlace": ["Montreal"]
  },
  "802": {
    "tagDescription": ["Defeat at Plattsburg Sir George Prevost"],
    "tagDate": ["1814-10-01T00:00:00.000Z"],
    "tagPerson": ["Sewell, Jonathan", "Smith, William"]
  },
  "633": {
    "tagPerson": ["Gibbon, A."],
    "tagDate": ["1814-03-06T00:00:00.000Z"],
    "tagDescription": ["Seizure of ship"],
    "tagPlace": ["Alfred Place"]
  },
  "86": {
    "tagPerson": ["Sewell, Jonathan", "Milnes, Robert Shore"],
    "tagDate": ["1805-07-05T00:00:00.000Z"],
    "tagDescription": [
      "Report on memorial of Patrick Langan and D.A. Grant regarding seignieury of Matapedia, R. only"
    ],
    "tagPlace": ["Quebec"]
  },
  "825": {
    "tagPerson": ["Sewell, Jonathan", "Gordon, Adam"],
    "tagDate": ["1814-10-25T00:00:00.000Z"],
    "tagDescription": [
      "Requesting letters relating to military operations in Canada"
    ],
    "tagPlace": ["Downing Street"]
  },
  "639": {
    "tagPerson": ["Sewell, Jonathan", "Monk, James"],
    "tagDate": ["1814-03-08T00:00:00.000Z"],
    "tagDescription": ["Impeachment"],
    "tagPlace": ["Montreal"]
  },
  "755": {
    "tagPlace": ["Montreal"],
    "tagDescription": ["Law society dispute in Montreal, Birth of son"],
    "tagDate": ["1814-07-05T00:00:00.000Z"],
    "tagPerson": ["Sewell, Jonathan", "Sewell, Stephen"]
  },
  "668": {
    "tagPlace": ["Montreal"],
    "tagPerson": ["Ogden, Isaac", "Sewell, Jonathan"],
    "tagDate": ["1814-03-28T00:00:00.000Z"],
    "tagDescription": ["Impeachment, James Stuart, Denis Viger"]
  },
  "862": {
    "tagPlace": ["Luke Street"],
    "tagPerson": ["Sewell, Jonathan", "Atcheson, N."],
    "tagDate": ["1815-02-01T00:00:00.000Z"],
    "tagDescription": ["Meeting of Privy Council on the Accusations"]
  },
  "187": {
    "tagPlace": ["Three Rivers"],
    "tagPerson": ["Sewell, Jonathan", "Coffin, V."],
    "tagDate": ["1808-02-05T00:00:00.000Z"],
    "tagDescription": ["Election of Ezekiel Hart"]
  },
  "130": {
    "tagPlace": ["Montreal"],
    "tagDate": ["1806-03-10T00:00:00.000Z"],
    "tagPerson": ["Sewell, Harriet", "Sewell, Jonathan"],
    "tagDescription": ["Personal"]
  },
  "607": {
    "tagPlace": ["Montreal"],
    "tagDate": ["1814-02-14T00:00:00.000Z"],
    "tagPerson": ["Sewell, Jonathan", "Richardson, John"],
    "tagDescription": ["Impeachment, War news"]
  },
  "848": {
    "tagPlace": ["Quebec"],
    "tagDate": ["1814-11-18T00:00:00.000Z"],
    "tagPerson": ["Sewell, Jonathan", "Ferguson, A."],
    "tagDescription": ["Financial"]
  },
  "367": {
    "tagDate": ["1811-03-11T00:00:00.000Z"],
    "tagPerson": ["Sewell, Jonathan", "Montizambert, Louis"],
    "tagDescription": ["Land, Tingwick"],
    "tagPlace": ["Quebec"]
  },
  "17": {
    "tagDate": ["1803-09-22T00:00:00.000Z"],
    "tagPerson": ["Sewell, Jonathan", "Scott, James"],
    "tagDescription": ["Personal"],
    "tagPlace": ["Boston"]
  },
  "277": {
    "tagDate": ["1809-05-29T00:00:00.000Z"],
    "tagPerson": ["Sewell, Jonathan", "Sewell, Stephen"],
    "tagDescription": ["Aspirations to office of solicitor-general"],
    "tagPlace": ["Montreal"]
  },
  "726": {
    "tagPerson": ["Sewell, Jonathan", "Richardson, John"],
    "tagDate": ["1814-06-07T00:00:00.000Z"],
    "tagDescription": ["Preparation of Papers"],
    "tagPlace": ["Montreal"]
  },
  "720": {
    "tagPerson": ["Sewell, Jonathan", "Baynes, Edward"],
    "tagDate": ["1814-06-03T00:00:00.000Z"],
    "tagDescription": ["Leave"],
    "tagPlace": ["Montreal"]
  },
  "342": {
    "tagDescription": ["Militia - Loyalty, - Henri"],
    "tagPerson": ["Sewell, Jonathan", "Sewell, Stephen"],
    "tagDate": ["1810-06-21T00:00:00.000Z"],
    "tagPlace": ["Montreal"]
  },
  "854": {
    "tagPlace": ["Quebec"],
    "tagDate": ["1815-01-15T00:00:00.000Z"],
    "tagPerson": ["Sewell, Jonathan", "Bowen, Edward"],
    "tagDescription": [
      "Legal cases, Courts and salaries, Library, Opening of Assembly, Court martial of Procter, Personal"
    ]
  },
  "172": {
    "tagPlace": ["Quebec"],
    "tagPerson": ["Goodall", "Turner", "Sewell, Jonathan"],
    "tagDate": ["1807-08-25T00:00:00.000Z"],
    "tagDescription": ["Financial R."]
  },
  "259": {
    "tagDescription": ["Personal, Legal, John Jones"],
    "tagPerson": ["Sewell, Stephen", "Sewell, Jonathan"],
    "tagDate": ["1808-11-17T00:00:00.000Z"],
    "tagPlace": ["Montreal"]
  },
  "890": {
    "tagPerson": ["Salton, Gilbert", "Sewell, Jonathan"],
    "tagDate": ["1815-06-15T00:00:00.000Z"],
    "tagDescription": ["Advice regarding libel charges against Stephen Sewell"],
    "tagPlace": ["London"]
  },
  "270": {
    "tagPlace": ["Saint John"],
    "tagDescription": [
      "Aspirations to appointment as chief justice of New Brunswick"
    ],
    "tagDate": ["1808-12-19T00:00:00.000Z"],
    "tagPerson": ["Chipman, Ward", "Sewell, Jonathan"]
  },
  "389": {
    "tagDescription": ["Personal, War"],
    "tagPerson": ["Sewell, Jonathan", "Brenton, E.B."],
    "tagDate": ["1812-08-18T00:00:00.000Z"],
    "tagPlace": ["Montreal"]
  },
  "110": {
    "tagDescription": [
      "Appointment of Alcock as Chief Justice, His employment in Ireland, Rental of House in Quebec"
    ],
    "tagDate": ["1805-12-09T00:00:00.000Z"],
    "tagPerson": ["Sewell, Jonathan", "Doyle, William"],
    "tagPlace": ["Birmingham Lodge Ireland"]
  },
  "664": {
    "tagPlace": ["Montreal"],
    "tagDate": ["1814-03-27T00:00:00.000Z"],
    "tagPerson": ["Monk, James", "Sewell, Jonathan"],
    "tagDescription": ["Court of Appeal, Impeachment"]
  },
  "306": {
    "tagPerson": ["Sewell, Stephen", "Sewell, Jonathan"],
    "tagDate": ["1810-01-22T00:00:00.000Z"],
    "tagDescription": ["Death of Esther Sewell"],
    "tagPlace": ["Montreal"]
  },
  "409": {
    "tagPlace": ["Montreal"],
    "tagDescription": ["Jesuits estates, Militia expenditure"],
    "tagDate": ["1812-09-01T00:00:00.000Z"],
    "tagPerson": ["Prevost, George Sir", "Sewell, Jonathan"]
  },
  "73": {
    "tagDescription": [
      "Papers of Jonathan Sewell Sr. Wish for appointment as consul at Boston"
    ],
    "tagPerson": ["Chipman, Ward", "Sewell, Jonathan"],
    "tagDate": ["1805-04-22T00:00:00.000Z"],
    "tagPlace": ["Saint John"]
  },
  "58": {
    "tagDescription": ["Debt"],
    "tagPerson": ["Sewell, Jonathan", "Colden, Cadwallader D."],
    "tagDate": ["1805-01-26T00:00:00.000Z"],
    "tagPlace": ["New York"]
  },
  "683": {
    "tagDescription": ["Support of judiciary"],
    "tagDate": ["1814-04-15T00:00:00.000Z"],
    "tagPerson": ["Coltman, W.B.", "Sewell, Jonathan"]
  },
  "604": {
    "tagPerson": ["Sewell, Jonathan", "Monk, James"],
    "tagDate": ["1814-02-11T00:00:00.000Z"],
    "tagDescription": ["Impeachment"],
    "tagPlace": ["Monk Ville"]
  },
  "315": {
    "tagPlace": ["Montreal"],
    "tagDescription": ["Sale of printing office to - Ogilvy, Marriages"],
    "tagDate": ["1810-04-30T00:00:00.000Z"],
    "tagPerson": ["Sewell, Stephen", "Sewell, Jonathan"]
  },
  "431": {
    "tagDescription": ["Enclosure"],
    "tagDate": ["1812-11-16T00:00:00.000Z"],
    "tagPerson": ["Brenton", "Sewell, Jonathan"]
  },
  "463": {
    "tagDate": ["1813-02-04T00:00:00.000Z"],
    "tagPerson": ["Monk, James", "Sewell, Jonathan"],
    "tagDescription": ["Impeachment"],
    "tagPlace": ["Montreal"]
  },
  "941": {
    "tagPlace": ["Quebec"],
    "tagPerson": ["Bowen, Edward", "Sewell, Jonathan"],
    "tagDate": ["1815-09-21T00:00:00.000Z"],
    "tagDescription": [
      "Case of Francis Ansell, Jurisdiction of Court of Vice Admiralty"
    ]
  },
  "873": {
    "tagPlace": ["Montreal"],
    "tagPerson": ["Sewell, Stephen", "Robinson, Commissary General"],
    "tagDate": ["1815-03-27T00:00:00.000Z"],
    "tagDescription": ["Denying authorship of libels"]
  },
  "732": {
    "tagDescription": ["Impeachment"],
    "tagDate": ["1814-06-12T00:00:00.000Z"],
    "tagPerson": ["Sewell, Jonathan", "Ryland, Herman Witsius"],
    "tagPlace": ["Beauport"]
  },
  "12": {
    "tagDescription": ["Personal"],
    "tagPerson": ["Sewell, Esther", "Scott, James"],
    "tagDate": ["1803-09-06T00:00:00.000Z"],
    "tagPlace": ["Montreal"]
  },
  "613": {
    "tagPlace": ["Monk Ville"],
    "tagDescription": ["Impeachment, Encl. Copy of resolutions"],
    "tagPerson": ["Monk, James", "Sewell, Jonathan"],
    "tagDate": ["1814-02-16T00:00:00.000Z"]
  },
  "652": {
    "tagDate": ["1814-03-21T00:00:00.000Z"],
    "tagPerson": ["Sewell, Jonathan", "Gordon, Adam"],
    "tagDescription": ["Impeachment, R."],
    "tagPlace": ["Quebec"]
  },
  "593": {
    "tagPlace": ["Monk Ville"],
    "tagDescription": ["Impeachment"],
    "tagDate": ["1814-02-07T00:00:00.000Z"],
    "tagPerson": ["Monk, James", "Sewell, Jonathan"]
  },
  "69": {
    "tagDescription": ["Account"],
    "tagPerson": ["Sewell, Jonathan", "Turner", "Goodall"],
    "tagDate": ["1805-03-19T00:00:00.000Z"],
    "tagPlace": ["London"]
  },
  "138": {
    "tagPlace": ["Quebec"],
    "tagDescription": ["Personal"],
    "tagDate": ["1806-09-07T00:00:00.000Z"],
    "tagPerson": ["Sewell, Harriet", "Sewell, Jonathan"]
  },
  "619": {
    "tagPlace": ["Monk Ville"],
    "tagDescription": ["War news, Impeachment"],
    "tagDate": ["1814-02-18T00:00:00.000Z"],
    "tagPerson": ["Sewell, Jonathan", "Monk, James"]
  },
  "599": {
    "tagPlace": ["Monk Ville"],
    "tagPerson": ["Monk, James", "Sewell, Jonathan"],
    "tagDate": ["1814-02-10T00:00:00.000Z"],
    "tagDescription": ["Impeachment, School bill, Agent Bill"]
  },
  "65": {
    "tagPlace": ["Riviere des Loups"],
    "tagPerson": ["Sewell, Jonathan", "Sewell, Harriet"],
    "tagDate": ["1805-02-27T00:00:00.000Z"],
    "tagDescription": ["Personal"]
  },
  "851": {
    "tagDate": ["1814-11-20T00:00:00.000Z"],
    "tagPerson": ["Sewell, Jonathan", "Bowen, Edward"],
    "tagDescription": [
      "War news, Address in support of Sir George Prevost, Courts, Personal"
    ],
    "tagPlace": ["Quebec"]
  },
  "313": {
    "tagPlace": ["London"],
    "tagPerson": ["Goodall", "Sewell, Jonathan", "Turner"],
    "tagDate": ["1810-02-23T00:00:00.000Z"],
    "tagDescription": ["Financial"]
  },
  "39": {
    "tagDescription": [
      "William Doyle, Replacement for Joseph Bouchette, Plenderleath family, Gossip"
    ],
    "tagPerson": ["Sewell, Jonathan", "Smith, William"],
    "tagDate": ["1804-03-09T00:00:00.000Z"],
    "tagName": ["Doyle, William"],
    "tagPlace": ["London"]
  },
  "685": {
    "tagDate": ["1814-04-15T00:00:00.000Z"],
    "tagPerson": ["Monk, James", "Sewell, Jonathan"],
    "tagDescription": ["State of the government"],
    "tagPlace": ["Montreal"]
  }
}
