{
  "type": "committees",
  "pubmax": "1983-11-30",
  "node": [
    ["eng", "c", "committees", "32-1", 75],
    ["fra", "c", "committees", "32-1", 156]
  ],
  "chamber": ["c"],
  "primeMinisters": "Trudeau, Pierre Elliott",
  "pubmin": "1980-04-14",
  "callNumber": "1980/83 H4 A1 no.57-67",
  "label": "House of Commons Committees, 32nd Parliament, 1st Session : Standing Committee on Health, Welfare and Social Affairs, vol. 4 no. 57-67 = Comités de la Chambre des communes, 32e Législature, 1re Session : Comité permanent de la santé, du bien-être social et des affaires sociales, vol. 4 no. 57-67",
  "language": ["eng", "fra"],
  "session": ["32-1"]
}
